Workbook

Sheet はじめに
A1: 嫁子のスカッと朗読劇場【スカッとする話】 転載対策シート
A2: 作成日 | B2: 2026-09-16
A4: シート | B4: 内容
A5: ラウンド0_検索上位の転載 | B5: 本家より検索上位に表示されている転載164本。最優先で削除申請する。
A6: ラウンド1 | B6: 上位100チャンネルに1本ずつ＋101位以降はまとめて。警告1回目。
A7: ラウンド2 | B7: ラウンド1の削除実行後、上位100チャンネルにもう1本ずつ。
A8: ラウンド3 | B8: ラウンド2の実行後にもう1本ずつ。ここで相手チャンネル停止。
A9: チャンネル別集計 | B9: 819チャンネルの転載本数。全転載一覧の申請日・削除確認を埋めると自動で集計される。
A10: 全転載一覧 | B10: 現存する転載2,412本の全件。
A11: 本家が圏外 | B11: 本家が検索100位以内に出なかった元動画12本。転載以外の原因を確認。
A13: 黄色のセル | B13: 申請日・削除確認・メモを記入する欄。
A14: 一致率 | B14: タイトルの文字一致率。100%はタイトルが一言一句同じ。
A15: 注意 | B15: 申請前に転載動画を10秒再生し、ナレーションが嫁子の音声であることを確認する。虚偽申請は自チャンネルの停止リスク。
... A17: 記入例 | B17: 申請日「9/17」、削除確認「9/20」のように日付を入れる。

Sheet チャンネル別集計
A1: 順位 | B1: チャンネル名 | C1: チャンネルURL | D1: 転載本数 | E1: 直近の投稿 | F1: 主な形式 | G1: 申請済み本数 | H1: 削除済み本数 | I1: メモ
A2: 1 | B2: 藤田 七海 | C2: https://www.youtube.com/channel/UCe0KTxGVR84qUjkAHQb-wGg | D2: =COUNTIF(全転載一覧!$B$2:$B$2413,B2) | E2: 2 週間前 | F2: 朗読/同形式 | G2: =COUNTIFS(全転載一覧!$B$2:$B$2413,B2,全転載一覧!$N$2:$N$2413,"<>") | H2: =COUNTIFS(全転載一覧!$B$2:$B$2413,B2,全転載一覧!$O$2:$O$2413,"<>")
A3: 2 | B3: スカッと物語 | C3: https://www.youtube.com/channel/UCLz5UoQMIAja9LyZIOCYmQg | D3: =COUNTIF(全転載一覧!$B$2:$B$2413,B3) | E3: 8 日前 | F3: 朗読/同形式 | G3: =COUNTIFS(全転載一覧!$B$2:$B$2413,B3,全転載一覧!$N$2:$N$2413,"<>") | H3: =COUNTIFS(全転載一覧!$B$2:$B$2413,B3,全転載一覧!$O$2:$O$2413,"<>")
A4: 3 | B4: 出る杭は打たれる | C4: https://www.youtube.com/channel/UCAmIDIbiOxKA9YSVK0aYSZQ | D4: =COUNTIF(全転載一覧!$B$2:$B$2413,B4) | E4: 2 か月前 | F4: 朗読/同形式 | G4: =COUNTIFS(全転載一覧!$B$2:$B$2413,B4,全転載一覧!$N$2:$N$2413,"<>") | H4: =COUNTIFS(全転載一覧!$B$2:$B$2413,B4,全転載一覧!$O$2:$O$2413,"<>")
A5: 4 | B5: 良い話 | C5: https://www.youtube.com/channel/UCSrk1OzKlw4sCvRbksLDgcQ | D5: =COUNTIF(全転載一覧!$B$2:$B$2413,B5) | E5: 5 日前 | F5: 朗読/同形式 | G5: =COUNTIFS(全転載一覧!$B$2:$B$2413,B5,全転載一覧!$N$2:$N$2413,"<>") | H5: =COUNTIFS(全転載一覧!$B$2:$B$2413,B5,全転載一覧!$O$2:$O$2413,"<>")
A6: 5 | B6: 家庭の真実 5497 | C6: https://www.youtube.com/channel/UCqzVZHS7_AHD3WczZdnOkwg | D6: =COUNTIF(全転載一覧!$B$2:$B$2413,B6) | E6: 3 週間前 | F6: 朗読/同形式 | G6: =COUNTIFS(全転載一覧!$B$2:$B$2413,B6,全転載一覧!$N$2:$N$2413,"<>") | H6: =COUNTIFS(全転載一覧!$B$2:$B$2413,B6,全転載一覧!$O$2:$O$2413,"<>")
A7: 6 | B7: スカッとストーリー 5006 | C7: https://www.youtube.com/channel/UC1x3I0LM2SzXkpn57uaFuQA | D7: =COUNTIF(全転載一覧!$B$2:$B$2413,B7) | E7: 1 か月前 | F7: 朗読/同形式 | G7: =COUNTIFS(全転載一覧!$B$2:$B$2413,B7,全転載一覧!$N$2:$N$2413,"<>") | H7: =COUNTIFS(全転載一覧!$B$2:$B$2413,B7,全転載一覧!$O$2:$O$2413,"<>")
A8: 7 | B8: 嫁ゴコロ逆転朗読館 | C8: https://www.youtube.com/channel/UCQDSjWHn0tvkuVZav4jZnXQ | D8: =COUNTIF(全転載一覧!$B$2:$B$2413,B8) | E8: 6 日前 | F8: 朗読/同形式 | G8: =COUNTIFS(全転載一覧!$B$2:$B$2413,B8,全転載一覧!$N$2:$N$2413,"<>") | H8: =COUNTIFS(全転載一覧!$B$2:$B$2413,B8,全転載一覧!$O$2:$O$2413,"<>")
A9: 8 | B9: 読書室【スカッとする話】 | C9: https://www.youtube.com/channel/UCjQd7ZVm5BPbGpB_V9B6kgQ | D9: =COUNTIF(全転載一覧!$B$2:$B$2413,B9) | E9: 1 年前 | F9: 朗読/同形式 | G9: =COUNTIFS(全転載一覧!$B$2:$B$2413,B9,全転載一覧!$N$2:$N$2413,"<>") | H9: =COUNTIFS(全転載一覧!$B$2:$B$2413,B9,全転載一覧!$O$2:$O$2413,"<>")
A10: 9 | B10: 憂鬱よりスカッと | C10: https://www.youtube.com/channel/UC8bvniIkSPPf_5ELr1VNZCQ | D10: =COUNTIF(全転載一覧!$B$2:$B$2413,B10) | E10: 2 年前 | F10: 朗読/同形式 | G10: =COUNTIFS(全転載一覧!$B$2:$B$2413,B10,全転載一覧!$N$2:$N$2413,"<>") | H10: =COUNTIFS(全転載一覧!$B$2:$B$2413,B10,全転載一覧!$O$2:$O$2413,"<>")
A11: 10 | B11: とする話 | C11: https://www.youtube.com/channel/UC-1KoQRWd1ijwgKpAmRTQ7A | D11: =COUNTIF(全転載一覧!$B$2:$B$2413,B11) | E11: 1 年前 | F11: 朗読/同形式 | G11: =COUNTIFS(全転載一覧!$B$2:$B$2413,B11,全転載一覧!$N$2:$N$2413,"<>") | H11: =COUNTIFS(全転載一覧!$B$2:$B$2413,B11,全転載一覧!$O$2:$O$2413,"<>")
A12: 11 | B12: Dima Tomashevich | C12: https://www.youtube.com/channel/UCkfiH3lPVPodePE4eNSDpWg | D12: =COUNTIF(全転載一覧!$B$2:$B$2413,B12) | E12: 2 年前 | F12: 朗読/同形式 | G12: =COUNTIFS(全転載一覧!$B$2:$B$2413,B12,全転載一覧!$N$2:$N$2413,"<>") | H12: =COUNTIFS(全転載一覧!$B$2:$B$2413,B12,全転載一覧!$O$2:$O$2413,"<>")
A13: 12 | B13: さあ、どうぞ | C13: https://www.youtube.com/channel/UCG-XF2tttCtNESz__p6GQ7w | D13: =COUNTIF(全転載一覧!$B$2:$B$2413,B13) | E13: 2 か月前 | F13: 朗読/同形式 | G13: =COUNTIFS(全転載一覧!$B$2:$B$2413,B13,全転載一覧!$N$2:$N$2413,"<>") | H13: =COUNTIFS(全転載一覧!$B$2:$B$2413,B13,全転載一覧!$O$2:$O$2413,"<>")
... A18: 17 | B18: 義家族スカッと物語帳 | C18: https://www.youtube.com/channel/UCIZ41RBpQd7wBp_oOTGv1zw | D18: =COUNTIF(全転載一覧!$B$2:$B$2413,B18) | E18: 6 日前 | F18: 朗読/同形式 | G18: =COUNTIFS(全転載一覧!$B$2:$B$2413,B18,全転載一覧!$N$2:$N$2413,"<>") | H18: =COUNTIFS(全転載一覧!$B$2:$B$2413,B18,全転載一覧!$O$2:$O$2413,"<>")
A19: 18 | B19: 静かな夜の物語、雨の中の記憶 | D19: =COUNTIF(全転載一覧!$B$2:$B$2413,B19) | E19: 2 週間前 | F19: 朗読/同形式 | G19: =COUNTIFS(全転載一覧!$B$2:$B$2413,B19,全転載一覧!$N$2:$N$2413,"<>") | H19: =COUNTIFS(全転載一覧!$B$2:$B$2413,B19,全転載一覧!$O$2:$O$2413,"<>")
A20: 19 | B20: Noah Qumi | C20: https://www.youtube.com/channel/UCH4l3-r5NgR2RlKdoRwfzAw | D20: =COUNTIF(全転載一覧!$B$2:$B$2413,B20) | E20: 7 日前 | F20: 朗読/同形式 | G20: =COUNTIFS(全転載一覧!$B$2:$B$2413,B20,全転載一覧!$N$2:$N$2413,"<>") | H20: =COUNTIFS(全転載一覧!$B$2:$B$2413,B20,全転載一覧!$O$2:$O$2413,"<>")
A21: 20 | B21: Shinji Datの人生物語 | C21: https://www.youtube.com/channel/UCpdX_bFCePsYvPWZAMQoaeg | D21: =COUNTIF(全転載一覧!$B$2:$B$2413,B21) | E21: 2 か月前 | F21: 朗読/同形式 | G21: =COUNTIFS(全転載一覧!$B$2:$B$2413,B21,全転載一覧!$N$2:$N$2413,"<>") | H21: =COUNTIFS(全転載一覧!$B$2:$B$2413,B21,全転載一覧!$O$2:$O$2413,"<>")
A22: 21 | B22: スカッとする話 5020 | C22: https://www.youtube.com/channel/UCAG5eZR0aJpGuShtjtimSEg | D22: =COUNTIF(全転載一覧!$B$2:$B$2413,B22) | E22: 4 週間前 | F22: 朗読/同形式 | G22: =COUNTIFS(全転載一覧!$B$2:$B$2413,B22,全転載一覧!$N$2:$N$2413,"<>") | H22: =COUNTIFS(全転載一覧!$B$2:$B$2413,B22,全転載一覧!$O$2:$O$2413,"<>")
A23: 22 | B23: 人生の光と影 | C23: https://www.youtube.com/channel/UCYX4tsWpykTmtfNq_i36C_w | D23: =COUNTIF(全転載一覧!$B$2:$B$2413,B23) | E23: 8 日前 | F23: 朗読/同形式 | G23: =COUNTIFS(全転載一覧!$B$2:$B$2413,B23,全転載一覧!$N$2:$N$2413,"<>") | H23: =COUNTIFS(全転載一覧!$B$2:$B$2413,B23,全転載一覧!$O$2:$O$2413,"<>")
A24: 23 | B24: 美しい木 | C24: https://www.youtube.com/channel/UCKDhvWl0boDNeo65NQzjbOg | D24: =COUNTIF(全転載一覧!$B$2:$B$2413,B24) | E24: 3 か月前 | F24: 朗読/同形式 | G24: =COUNTIFS(全転載一覧!$B$2:$B$2413,B24,全転載一覧!$N$2:$N$2413,"<>") | H24: =COUNTIFS(全転載一覧!$B$2:$B$2413,B24,全転載一覧!$O$2:$O$2413,"<>")
A25: 24 | B25: TINA SHTIBKO | C25: https://www.youtube.com/channel/UCIQbb4FNm2BhP5GfSTbrQ4w | D25: =COUNTIF(全転載一覧!$B$2:$B$2413,B25) | E25: 2 年前 | F25: 朗読/同形式 | G25: =COUNTIFS(全転載一覧!$B$2:$B$2413,B25,全転載一覧!$N$2:$N$2413,"<>") | H25: =COUNTIFS(全転載一覧!$B$2:$B$2413,B25,全転載一覧!$O$2:$O$2413,"<>")
A26: 25 | B26: フィクション 5634 | C26: https://www.youtube.com/channel/UCtx1aitp-eTJhv2c94bnBZQ | D26: =COUNTIF(全転載一覧!$B$2:$B$2413,B26) | E26: 3 週間前 | F26: 朗読/同形式 | G26: =COUNTIFS(全転載一覧!$B$2:$B$2413,B26,全転載一覧!$N$2:$N$2413,"<>") | H26: =COUNTIFS(全転載一覧!$B$2:$B$2413,B26,全転載一覧!$O$2:$O$2413,"<>")
A27: 26 | B27: 泥だらけの絆 5655 | C27: https://www.youtube.com/channel/UCdyvc7k9wPzVO9X62aCvguQ | D27: =COUNTIF(全転載一覧!$B$2:$B$2413,B27) | E27: 13 日前 | F27: 朗読/同形式 | G27: =COUNTIFS(全転載一覧!$B$2:$B$2413,B27,全転載一覧!$N$2:$N$2413,"<>") | H27: =COUNTIFS(全転載一覧!$B$2:$B$2413,B27,全転載一覧!$O$2:$O$2413,"<>")
A28: 27 | B28: Bonnie Denver | C28: https://www.youtube.com/channel/UCsdndA886timZqWK6_b0d0Q | D28: =COUNTIF(全転載一覧!$B$2:$B$2413,B28) | E28: 1 年前 | F28: 朗読/同形式 | G28: =COUNTIFS(全転載一覧!$B$2:$B$2413,B28,全転載一覧!$N$2:$N$2413,"<>") | H28: =COUNTIFS(全転載一覧!$B$2:$B$2413,B28,全転載一覧!$O$2:$O$2413,"<>")
A29: 28 | B29: 心温まるストーリー 4989 | C29: https://www.youtube.com/channel/UCS-VuYFB_DXsDhPHAzUS0JA | D29: =COUNTIF(全転載一覧!$B$2:$B$2413,B29) | E29: 1 か月前 | F29: 朗読/同形式 | G29: =COUNTIFS(全転載一覧!$B$2:$B$2413,B29,全転載一覧!$N$2:$N$2413,"<>") | H29: =COUNTIFS(全転載一覧!$B$2:$B$2413,B29,全転載一覧!$O$2:$O$2413,"<>")
A30: 29 | B30: Jamison Abraham | C30: https://www.youtube.com/channel/UCcUsK23eqHw3ZQA5HjspM9Q | D30: =COUNTIF(全転載一覧!$B$2:$B$2413,B30) | E30: 1 年前 | F30: 朗読/同形式 | G30: =COUNTIFS(全転載一覧!$B$2:$B$2413,B30,全転載一覧!$N$2:$N$2413,"<>") | H30: =COUNTIFS(全転載一覧!$B$2:$B$2413,B30,全転載一覧!$O$2:$O$2413,"<>")
A31: 30 | B31: サヨナラの選択4848 | C31: https://www.youtube.com/channel/UCiDg2Vs1LHy6qIiV6ilje1A | D31: =COUNTIF(全転載一覧!$B$2:$B$2413,B31) | E31: 3 週間前 | F31: 朗読/同形式 | G31: =COUNTIFS(全転載一覧!$B$2:$B$2413,B31,全転載一覧!$N$2:$N$2413,"<>") | H31: =COUNTIFS(全転載一覧!$B$2:$B$2413,B31,全転載一覧!$O$2:$O$2413,"<>")
... A38: 37 | B38: 痛快!!怒りのスカッとチャンネル【スカッと朗読】 | C38: https://www.youtube.com/channel/UC96mO8pXAaiP70V7KUjVHqg | D38: =COUNTIF(全転載一覧!$B$2:$B$2413,B38) | E38: 1 年前 | F38: 朗読/同形式 | G38: =COUNTIFS(全転載一覧!$B$2:$B$2413,B38,全転載一覧!$N$2:$N$2413,"<>") | H38: =COUNTIFS(全転載一覧!$B$2:$B$2413,B38,全転載一覧!$O$2:$O$2413,"<>")
A39: 38 | B39: 雨の中の記憶、雨の中の記憶 | D39: =COUNTIF(全転載一覧!$B$2:$B$2413,B39) | E39: 3 週間前 | F39: 朗読/同形式 | G39: =COUNTIFS(全転載一覧!$B$2:$B$2413,B39,全転載一覧!$N$2:$N$2413,"<>") | H39: =COUNTIFS(全転載一覧!$B$2:$B$2413,B39,全転載一覧!$O$2:$O$2413,"<>")
A40: 39 | B40: スカっとゼミ!! | C40: https://www.youtube.com/channel/UC9Hd679L2faWD0aJQHeAlrA | D40: =COUNTIF(全転載一覧!$B$2:$B$2413,B40) | E40: 1 年前 | F40: 朗読/同形式 | G40: =COUNTIFS(全転載一覧!$B$2:$B$2413,B40,全転載一覧!$N$2:$N$2413,"<>") | H40: =COUNTIFS(全転載一覧!$B$2:$B$2413,B40,全転載一覧!$O$2:$O$2413,"<>")
A41: 40 | B41: スカッと成敗ストーリー | C41: https://www.youtube.com/channel/UC1iIGo491nSYyJ_AsgmPzyw | D41: =COUNTIF(全転載一覧!$B$2:$B$2413,B41) | E41: 2 か月前 | F41: 朗読/同形式 | G41: =COUNTIFS(全転載一覧!$B$2:$B$2413,B41,全転載一覧!$N$2:$N$2413,"<>") | H41: =COUNTIFS(全転載一覧!$B$2:$B$2413,B41,全転載一覧!$O$2:$O$2413,"<>")
A42: 41 | B42: 時を越える話 | C42: https://www.youtube.com/channel/UC_n9gc1na-2QpFv6TPInL3w | D42: =COUNTIF(全転載一覧!$B$2:$B$2413,B42) | E42: 3 週間前 | F42: 朗読/同形式 | G42: =COUNTIFS(全転載一覧!$B$2:$B$2413,B42,全転載一覧!$N$2:$N$2413,"<>") | H42: =COUNTIFS(全転載一覧!$B$2:$B$2413,B42,全転載一覧!$O$2:$O$2413,"<>")
A43: 42 | B43: 涙の向こう側 | C43: https://www.youtube.com/channel/UCOXAYjsxUMpublA1yS1ATIA | D43: =COUNTIF(全転載一覧!$B$2:$B$2413,B43) | E43: 8 日前 | F43: 朗読/同形式 | G43: =COUNTIFS(全転載一覧!$B$2:$B$2413,B43,全転載一覧!$N$2:$N$2413,"<>") | H43: =COUNTIFS(全転載一覧!$B$2:$B$2413,B43,全転載一覧!$O$2:$O$2413,"<>")
A44: 43 | B44: 老いの詩 | C44: https://www.youtube.com/channel/UClKj-HO63gh7qxtT7M0czEQ | D44: =COUNTIF(全転載一覧!$B$2:$B$2413,B44) | E44: 1 か月前 | F44: 朗読/同形式 | G44: =COUNTIFS(全転載一覧!$B$2:$B$2413,B44,全転載一覧!$N$2:$N$2413,"<>") | H44: =COUNTIFS(全転載一覧!$B$2:$B$2413,B44,全転載一覧!$O$2:$O$2413,"<>")
A45: 44 | B45: Ivan Ilencow | C45: https://www.youtube.com/channel/UC6IzQHpKzqIt1DgjPouEefQ | D45: =COUNTIF(全転載一覧!$B$2:$B$2413,B45) | E45: 2 年前 | F45: 朗読/同形式 | G45: =COUNTIFS(全転載一覧!$B$2:$B$2413,B45,全転載一覧!$N$2:$N$2413,"<>") | H45: =COUNTIFS(全転載一覧!$B$2:$B$2413,B45,全転載一覧!$O$2:$O$2413,"<>")
A46: 45 | B46: Legacy Apollo | C46: https://www.youtube.com/channel/UC2YwIXq-utTkNLQgcRVloyQ | D46: =COUNTIF(全転載一覧!$B$2:$B$2413,B46) | E46: 2 年前 | F46: 朗読/同形式 | G46: =COUNTIFS(全転載一覧!$B$2:$B$2413,B46,全転載一覧!$N$2:$N$2413,"<>") | H46: =COUNTIFS(全転載一覧!$B$2:$B$2413,B46,全転載一覧!$O$2:$O$2413,"<>")
A47: 46 | B47: Pendelton Gideon | C47: https://www.youtube.com/channel/UCIRVjzjmTHwXA3X81dpyNeQ | D47: =COUNTIF(全転載一覧!$B$2:$B$2413,B47) | E47: 1 年前 | F47: 朗読/同形式 | G47: =COUNTIFS(全転載一覧!$B$2:$B$2413,B47,全転載一覧!$N$2:$N$2413,"<>") | H47: =COUNTIFS(全転載一覧!$B$2:$B$2413,B47,全転載一覧!$O$2:$O$2413,"<>")
A48: 47 | B48: Павел **** | C48: https://www.youtube.com/channel/UCSPg9ALk7YwnsqACClpErGg | D48: =COUNTIF(全転載一覧!$B$2:$B$2413,B48) | E48: 2 年前 | F48: 朗読/同形式 | G48: =COUNTIFS(全転載一覧!$B$2:$B$2413,B48,全転載一覧!$N$2:$N$2413,"<>") | H48: =COUNTIFS(全転載一覧!$B$2:$B$2413,B48,全転載一覧!$O$2:$O$2413,"<>")
A49: 48 | B49: 人生スカッと朗読館 | C49: https://www.youtube.com/channel/UChTkZ7g3oCCQG3XSqe69LWQ | D49: =COUNTIF(全転載一覧!$B$2:$B$2413,B49) | E49: 5 日前 | F49: 朗読/同形式 | G49: =COUNTIFS(全転載一覧!$B$2:$B$2413,B49,全転載一覧!$N$2:$N$2413,"<>") | H49: =COUNTIFS(全転載一覧!$B$2:$B$2413,B49,全転載一覧!$O$2:$O$2413,"<>")
A50: 49 | B50: 夜の語り部5056 | C50: https://www.youtube.com/channel/UCEvaB4r-6y7tj3UAoMEdqXA | D50: =COUNTIF(全転載一覧!$B$2:$B$2413,B50) | E50: 1 か月前 | F50: 朗読/同形式 | G50: =COUNTIFS(全転載一覧!$B$2:$B$2413,B50,全転載一覧!$N$2:$N$2413,"<>") | H50: =COUNTIFS(全転載一覧!$B$2:$B$2413,B50,全転載一覧!$O$2:$O$2413,"<>")
A51: 50 | B51: 妻の復讐 5649 | C51: https://www.youtube.com/channel/UC_-FBuCpoEW8RPG4j-oCbkg | D51: =COUNTIF(全転載一覧!$B$2:$B$2413,B51) | E51: 2 週間前 | F51: 朗読/同形式 | G51: =COUNTIFS(全転載一覧!$B$2:$B$2413,B51,全転載一覧!$N$2:$N$2413,"<>") | H51: =COUNTIFS(全転載一覧!$B$2:$B$2413,B51,全転載一覧!$O$2:$O$2413,"<>")
... A90: 89 | B90: 雨の中の記憶 | C90: https://www.youtube.com/channel/UCJ_Zte-T_DYEEvf5DqPciGg | D90: =COUNTIF(全転載一覧!$B$2:$B$2413,B90) | E90: 1 か月前 | F90: 朗読/同形式 | G90: =COUNTIFS(全転載一覧!$B$2:$B$2413,B90,全転載一覧!$N$2:$N$2413,"<>") | H90: =COUNTIFS(全転載一覧!$B$2:$B$2413,B90,全転載一覧!$O$2:$O$2413,"<>")
A91: 90 | B91: 雨の中の記憶、静かな心の記録 | D91: =COUNTIF(全転載一覧!$B$2:$B$2413,B91) | E91: 10 日前 | F91: 朗読/同形式 | G91: =COUNTIFS(全転載一覧!$B$2:$B$2413,B91,全転載一覧!$N$2:$N$2413,"<>") | H91: =COUNTIFS(全転載一覧!$B$2:$B$2413,B91,全転載一覧!$O$2:$O$2413,"<>")
A92: 91 | B92: 雨の中の記憶、静かな終わり | D92: =COUNTIF(全転載一覧!$B$2:$B$2413,B92) | E92: 1 か月前 | F92: 朗読/同形式 | G92: =COUNTIFS(全転載一覧!$B$2:$B$2413,B92,全転載一覧!$N$2:$N$2413,"<>") | H92: =COUNTIFS(全転載一覧!$B$2:$B$2413,B92,全転載一覧!$O$2:$O$2413,"<>")
A93: 92 | B93: 静かな夜の物語、お話の部屋 | D93: =COUNTIF(全転載一覧!$B$2:$B$2413,B93) | E93: 4 週間前 | F93: 朗読/同形式 | G93: =COUNTIFS(全転載一覧!$B$2:$B$2413,B93,全転載一覧!$N$2:$N$2413,"<>") | H93: =COUNTIFS(全転載一覧!$B$2:$B$2413,B93,全転載一覧!$O$2:$O$2413,"<>")
A94: 93 | B94: Avalynn Roderick | C94: https://www.youtube.com/channel/UC2ALeyYaaWwXZhLpaAxCjDA | D94: =COUNTIF(全転載一覧!$B$2:$B$2413,B94) | E94: 2 年前 | F94: 朗読/同形式 | G94: =COUNTIFS(全転載一覧!$B$2:$B$2413,B94,全転載一覧!$N$2:$N$2413,"<>") | H94: =COUNTIFS(全転載一覧!$B$2:$B$2413,B94,全転載一覧!$O$2:$O$2413,"<>")
A95: 94 | B95: Chi Tông | C95: https://www.youtube.com/channel/UCQZmlpJ03rsGpabdpOyYt5g | D95: =COUNTIF(全転載一覧!$B$2:$B$2413,B95) | E95: 1 年前 | F95: 朗読/同形式 | G95: =COUNTIFS(全転載一覧!$B$2:$B$2413,B95,全転載一覧!$N$2:$N$2413,"<>") | H95: =COUNTIFS(全転載一覧!$B$2:$B$2413,B95,全転載一覧!$O$2:$O$2413,"<>")
A96: 95 | B96: Malani Darren | C96: https://www.youtube.com/channel/UCGjfIdDymNvLcybwzheXAnQ | D96: =COUNTIF(全転載一覧!$B$2:$B$2413,B96) | E96: 1 年前 | F96: 朗読/同形式 | G96: =COUNTIFS(全転載一覧!$B$2:$B$2413,B96,全転載一覧!$N$2:$N$2413,"<>") | H96: =COUNTIFS(全転載一覧!$B$2:$B$2413,B96,全転載一覧!$O$2:$O$2413,"<>")
A97: 96 | B97: Thuong Le | C97: https://www.youtube.com/channel/UCxXjwf3LJAKSZP_9Thu5meA | D97: =COUNTIF(全転載一覧!$B$2:$B$2413,B97) | E97: 1 年前 | F97: 朗読/同形式 | G97: =COUNTIFS(全転載一覧!$B$2:$B$2413,B97,全転載一覧!$N$2:$N$2413,"<>") | H97: =COUNTIFS(全転載一覧!$B$2:$B$2413,B97,全転載一覧!$O$2:$O$2413,"<>")
A98: 97 | B98: anh le | C98: https://www.youtube.com/channel/UCarxn6vtJCi169Mjzrmzo4A | D98: =COUNTIF(全転載一覧!$B$2:$B$2413,B98) | E98: 1 年前 | F98: 朗読/同形式 | G98: =COUNTIFS(全転載一覧!$B$2:$B$2413,B98,全転載一覧!$N$2:$N$2413,"<>") | H98: =COUNTIFS(全転載一覧!$B$2:$B$2413,B98,全転載一覧!$O$2:$O$2413,"<>")
A99: 98 | B99: ezebo chiamaka | C99: https://www.youtube.com/channel/UCE-qld23FOqFEVR1e-zZk_g | D99: =COUNTIF(全転載一覧!$B$2:$B$2413,B99) | E99: 1 年前 | F99: 朗読/同形式 | G99: =COUNTIFS(全転載一覧!$B$2:$B$2413,B99,全転載一覧!$N$2:$N$2413,"<>") | H99: =COUNTIFS(全転載一覧!$B$2:$B$2413,B99,全転載一覧!$O$2:$O$2413,"<>")
A100: 99 | B100: faustino karisa | C100: https://www.youtube.com/channel/UCh1wgkzk9PVxPJshc_EWlIA | D100: =COUNTIF(全転載一覧!$B$2:$B$2413,B100) | E100: 2 年前 | F100: 朗読/同形式 | G100: =COUNTIFS(全転載一覧!$B$2:$B$2413,B100,全転載一覧!$N$2:$N$2413,"<>") | H100: =COUNTIFS(全転載一覧!$B$2:$B$2413,B100,全転載一覧!$O$2:$O$2413,"<>")
A101: 100 | B101: 【経済的処刑】マウント成金の一文無し計画 | C101: https://www.youtube.com/channel/UCFrczgjtItoUn5iNZnathKA | D101: =COUNTIF(全転載一覧!$B$2:$B$2413,B101) | E101: 3 か月前 | F101: 朗読/同形式 | G101: =COUNTIFS(全転載一覧!$B$2:$B$2413,B101,全転載一覧!$N$2:$N$2413,"<>") | H101: =COUNTIFS(全転載一覧!$B$2:$B$2413,B101,全転載一覧!$O$2:$O$2413,"<>")
A102: 101 | B102: 【鑑定書の告発】科学が暴く「ざまぁ」の真相 | C102: https://www.youtube.com/channel/UCQilFCU3Eok7gFShbP8i38w | D102: =COUNTIF(全転載一覧!$B$2:$B$2413,B102) | E102: 3 か月前 | F102: 朗読/同形式 | G102: =COUNTIFS(全転載一覧!$B$2:$B$2413,B102,全転載一覧!$N$2:$N$2413,"<>") | H102: =COUNTIFS(全転載一覧!$B$2:$B$2413,B102,全転載一覧!$O$2:$O$2413,"<>")
A103: 102 | B103: アヒルの子 | C103: https://www.youtube.com/channel/UCW4prcGFf0yqLylWHc8zRLQ | D103: =COUNTIF(全転載一覧!$B$2:$B$2413,B103) | E103: 3 か月前 | F103: 朗読/同形式 | G103: =COUNTIFS(全転載一覧!$B$2:$B$2413,B103,全転載一覧!$N$2:$N$2413,"<>") | H103: =COUNTIFS(全転載一覧!$B$2:$B$2413,B103,全転載一覧!$O$2:$O$2413,"<>")
A104: 103 | B104: スカッと感動 !02 | C104: https://www.youtube.com/channel/UC245xKv3oOdbX57tRsuWmQg | D104: =COUNTIF(全転載一覧!$B$2:$B$2413,B104) | E104: 2 年前 | F104: 朗読/同形式 | G104: =COUNTIFS(全転載一覧!$B$2:$B$2413,B104,全転載一覧!$N$2:$N$2413,"<>") | H104: =COUNTIFS(全転載一覧!$B$2:$B$2413,B104,全転載一覧!$O$2:$O$2413,"<>")
A105: 104 | B105: 人生の一頁 5631 | C105: https://www.youtube.com/channel/UC342_Tf8mM_bScq2p9d7lcg | D105: =COUNTIF(全転載一覧!$B$2:$B$2413,B105) | E105: 3 週間前 | F105: 朗読/同形式 | G105: =COUNTIFS(全転載一覧!$B$2:$B$2413,B105,全転載一覧!$N$2:$N$2413,"<>") | H105: =COUNTIFS(全転載一覧!$B$2:$B$2413,B105,全転載一覧!$O$2:$O$2413,"<>")
... A141: 140 | B141: 街の物語 5687 | C141: https://www.youtube.com/channel/UCxterQPS0akz9_edy6xAiDw | D141: =COUNTIF(全転載一覧!$B$2:$B$2413,B141) | E141: 3 週間前 | F141: 朗読/同形式 | G141: =COUNTIFS(全転載一覧!$B$2:$B$2413,B141,全転載一覧!$N$2:$N$2413,"<>") | H141: =COUNTIFS(全転載一覧!$B$2:$B$2413,B141,全転載一覧!$O$2:$O$2413,"<>")
A142: 141 | B142: 雨の中の記憶、お話の部屋 | D142: =COUNTIF(全転載一覧!$B$2:$B$2413,B142) | E142: 3 週間前 | F142: 朗読/同形式 | G142: =COUNTIFS(全転載一覧!$B$2:$B$2413,B142,全転載一覧!$N$2:$N$2413,"<>") | H142: =COUNTIFS(全転載一覧!$B$2:$B$2413,B142,全転載一覧!$O$2:$O$2413,"<>")
A143: 142 | B143: 静かな夜の物語、静かな心の記録 | D143: =COUNTIF(全転載一覧!$B$2:$B$2413,B143) | E143: 4 週間前 | F143: 朗読/同形式 | G143: =COUNTIFS(全転載一覧!$B$2:$B$2413,B143,全転載一覧!$N$2:$N$2413,"<>") | H143: =COUNTIFS(全転載一覧!$B$2:$B$2413,B143,全転載一覧!$O$2:$O$2413,"<>")
A144: 143 | B144: Catherine Mack | C144: https://www.youtube.com/channel/UChYk58s7t8r6sD1nV1Ua6PQ | D144: =COUNTIF(全転載一覧!$B$2:$B$2413,B144) | E144: 1 年前 | F144: 朗読/同形式 | G144: =COUNTIFS(全転載一覧!$B$2:$B$2413,B144,全転載一覧!$N$2:$N$2413,"<>") | H144: =COUNTIFS(全転載一覧!$B$2:$B$2413,B144,全転載一覧!$O$2:$O$2413,"<>")
A145: 144 | B145: Dorothy Jessika | C145: https://www.youtube.com/channel/UCjIFYuek6gc0gbT5TNn1sCQ | D145: =COUNTIF(全転載一覧!$B$2:$B$2413,B145) | E145: 1 年前 | F145: 朗読/同形式 | G145: =COUNTIFS(全転載一覧!$B$2:$B$2413,B145,全転載一覧!$N$2:$N$2413,"<>") | H145: =COUNTIFS(全転載一覧!$B$2:$B$2413,B145,全転載一覧!$O$2:$O$2413,"<>")
A146: 145 | B146: Elliot Perry | C146: https://www.youtube.com/channel/UCu6sSOVx4IweXf0aPxIradQ | D146: =COUNTIF(全転載一覧!$B$2:$B$2413,B146) | E146: 1 年前 | F146: 朗読/同形式 | G146: =COUNTIFS(全転載一覧!$B$2:$B$2413,B146,全転載一覧!$N$2:$N$2413,"<>") | H146: =COUNTIFS(全転載一覧!$B$2:$B$2413,B146,全転載一覧!$O$2:$O$2413,"<>")
A147: 146 | B147: FutureLens | C147: https://www.youtube.com/channel/UC1l4HieEbZPmgNoaCJdgHdw | D147: =COUNTIF(全転載一覧!$B$2:$B$2413,B147) | E147: 4 週間前 | F147: 朗読/同形式 | G147: =COUNTIFS(全転載一覧!$B$2:$B$2413,B147,全転載一覧!$N$2:$N$2413,"<>") | H147: =COUNTIFS(全転載一覧!$B$2:$B$2413,B147,全転載一覧!$O$2:$O$2413,"<>")
A148: 147 | B148: ItsDabestTV | C148: https://www.youtube.com/channel/UC7MuHVZzBSqOMtfuirZ-_Bw | D148: =COUNTIF(全転載一覧!$B$2:$B$2413,B148) | E148: 1 年前 | F148: 朗読/同形式 | G148: =COUNTIFS(全転載一覧!$B$2:$B$2413,B148,全転載一覧!$N$2:$N$2413,"<>") | H148: =COUNTIFS(全転載一覧!$B$2:$B$2413,B148,全転載一覧!$O$2:$O$2413,"<>")
A149: 148 | B149: Jay Connor | C149: https://www.youtube.com/channel/UCy819L_3O_Dd0-bKp9dHsSw | D149: =COUNTIF(全転載一覧!$B$2:$B$2413,B149) | E149: 2 年前 | F149: 朗読/同形式 | G149: =COUNTIFS(全転載一覧!$B$2:$B$2413,B149,全転載一覧!$N$2:$N$2413,"<>") | H149: =COUNTIFS(全転載一覧!$B$2:$B$2413,B149,全転載一覧!$O$2:$O$2413,"<>")
A150: 149 | B150: Michela Foti | C150: https://www.youtube.com/channel/UCVvLCeJwdpBQ4Aw1Ym-w7dg | D150: =COUNTIF(全転載一覧!$B$2:$B$2413,B150) | E150: 5 か月前 | F150: 朗読/同形式 | G150: =COUNTIFS(全転載一覧!$B$2:$B$2413,B150,全転載一覧!$N$2:$N$2413,"<>") | H150: =COUNTIFS(全転載一覧!$B$2:$B$2413,B150,全転載一覧!$O$2:$O$2413,"<>")
A151: 150 | B151: MrOrilsp | C151: https://www.youtube.com/channel/UC3AWBIaP0jDKtLkWHdHem2A | D151: =COUNTIF(全転載一覧!$B$2:$B$2413,B151) | E151: 1 年前 | F151: 朗読/同形式 | G151: =COUNTIFS(全転載一覧!$B$2:$B$2413,B151,全転載一覧!$N$2:$N$2413,"<>") | H151: =COUNTIFS(全転載一覧!$B$2:$B$2413,B151,全転載一覧!$O$2:$O$2413,"<>")
A152: 151 | B152: NGUYEN Tran | C152: https://www.youtube.com/channel/UCT9dD8tTpHu2pj3jcPsrGFw | D152: =COUNTIF(全転載一覧!$B$2:$B$2413,B152) | E152: 7 か月前 | F152: 朗読/同形式 | G152: =COUNTIFS(全転載一覧!$B$2:$B$2413,B152,全転載一覧!$N$2:$N$2413,"<>") | H152: =COUNTIFS(全転載一覧!$B$2:$B$2413,B152,全転載一覧!$O$2:$O$2413,"<>")
A153: 152 | B153: Reapin365 | C153: https://www.youtube.com/channel/UCQZrGKEGPVP0gJ8OV05LNoA | D153: =COUNTIF(全転載一覧!$B$2:$B$2413,B153) | E153: 2 年前 | F153: 朗読/同形式 | G153: =COUNTIFS(全転載一覧!$B$2:$B$2413,B153,全転載一覧!$N$2:$N$2413,"<>") | H153: =COUNTIFS(全転載一覧!$B$2:$B$2413,B153,全転載一覧!$O$2:$O$2413,"<>")
A154: 153 | B154: Smtih Landry | C154: https://www.youtube.com/channel/UCnpwEpHYgkmbLhk3PZecjNw | D154: =COUNTIF(全転載一覧!$B$2:$B$2413,B154) | E154: 1 年前 | F154: 朗読/同形式 | G154: =COUNTIFS(全転載一覧!$B$2:$B$2413,B154,全転載一覧!$N$2:$N$2413,"<>") | H154: =COUNTIFS(全転載一覧!$B$2:$B$2413,B154,全転載一覧!$O$2:$O$2413,"<>")
A155: 154 | B155: TEL人生相談 | C155: https://www.youtube.com/channel/UC8h96aFQ0J8wvyM6y-koWYg | D155: =COUNTIF(全転載一覧!$B$2:$B$2413,B155) | E155: 2 年前 | F155: 朗読/同形式 | G155: =COUNTIFS(全転載一覧!$B$2:$B$2413,B155,全転載一覧!$N$2:$N$2413,"<>") | H155: =COUNTIFS(全転載一覧!$B$2:$B$2413,B155,全転載一覧!$O$2:$O$2413,"<>")
... A183: 182 | B183: 陽咲 | C183: https://www.youtube.com/channel/UCkWQ3TuNHjERVg8BInHuS-Q | D183: =COUNTIF(全転載一覧!$B$2:$B$2413,B183) | E183: 3 か月前 | F183: 朗読/同形式 | G183: =COUNTIFS(全転載一覧!$B$2:$B$2413,B183,全転載一覧!$N$2:$N$2413,"<>") | H183: =COUNTIFS(全転載一覧!$B$2:$B$2413,B183,全転載一覧!$O$2:$O$2413,"<>")
A184: 183 | B184: 雨の中の記憶、静かな夜の物語 | D184: =COUNTIF(全転載一覧!$B$2:$B$2413,B184) | E184: 4 日前 | F184: 朗読/同形式 | G184: =COUNTIFS(全転載一覧!$B$2:$B$2413,B184,全転載一覧!$N$2:$N$2413,"<>") | H184: =COUNTIFS(全転載一覧!$B$2:$B$2413,B184,全転載一覧!$O$2:$O$2413,"<>")
A185: 184 | B185: 黒猫は見ていました【スカッと】 | C185: https://www.youtube.com/channel/UCOW4cd0N3rxrb7Um2iz126g | D185: =COUNTIF(全転載一覧!$B$2:$B$2413,B185) | E185: 3 年前 | F185: 朗読/同形式 | G185: =COUNTIFS(全転載一覧!$B$2:$B$2413,B185,全転載一覧!$N$2:$N$2413,"<>") | H185: =COUNTIFS(全転載一覧!$B$2:$B$2413,B185,全転載一覧!$O$2:$O$2413,"<>")
A186: 185 | B186: minh vương | C186: https://www.youtube.com/channel/UCdm2C4XwcbiPrnEtGAg00EQ | D186: =COUNTIF(全転載一覧!$B$2:$B$2413,B186) | E186: 2 年前 | F186: 朗読/同形式 | G186: =COUNTIFS(全転載一覧!$B$2:$B$2413,B186,全転載一覧!$N$2:$N$2413,"<>") | H186: =COUNTIFS(全転載一覧!$B$2:$B$2413,B186,全転載一覧!$O$2:$O$2413,"<>")
A187: 186 | B187: スカッとする話 | C187: https://www.youtube.com/channel/UCE4ScoaaEmRsXAijXOWNgPw | D187: =COUNTIF(全転載一覧!$B$2:$B$2413,B187) | E187: 2 年前 | F187: 朗読/同形式 | G187: =COUNTIFS(全転載一覧!$B$2:$B$2413,B187,全転載一覧!$N$2:$N$2413,"<>") | H187: =COUNTIFS(全転載一覧!$B$2:$B$2413,B187,全転載一覧!$O$2:$O$2413,"<>")
A188: 187 | B188: 374 Chocontham | C188: https://www.youtube.com/channel/UC3G5yZkOnkxx0y2IYkWi4tQ | D188: =COUNTIF(全転載一覧!$B$2:$B$2413,B188) | E188: 2 年前 | F188: 朗読/同形式 | G188: =COUNTIFS(全転載一覧!$B$2:$B$2413,B188,全転載一覧!$N$2:$N$2413,"<>") | H188: =COUNTIFS(全転載一覧!$B$2:$B$2413,B188,全転載一覧!$O$2:$O$2413,"<>")
A189: 188 | B189: 468 Ungthuphoi | C189: https://www.youtube.com/channel/UChMTaakDMyRJ8dYWT6dyj6A | D189: =COUNTIF(全転載一覧!$B$2:$B$2413,B189) | E189: 1 年前 | F189: 朗読/同形式 | G189: =COUNTIFS(全転載一覧!$B$2:$B$2413,B189,全転載一覧!$N$2:$N$2413,"<>") | H189: =COUNTIFS(全転載一覧!$B$2:$B$2413,B189,全転載一覧!$O$2:$O$2413,"<>")
A190: 189 | B190: 568 Nhièudodu | C190: https://www.youtube.com/channel/UCaEoz8eqqUVi21dauWEQjYg | D190: =COUNTIF(全転載一覧!$B$2:$B$2413,B190) | E190: 1 年前 | F190: 朗読/同形式 | G190: =COUNTIFS(全転載一覧!$B$2:$B$2413,B190,全転載一覧!$N$2:$N$2413,"<>") | H190: =COUNTIFS(全転載一覧!$B$2:$B$2413,B190,全転載一覧!$O$2:$O$2413,"<>")
A191: 190 | B191: 579 Bitoxao | C191: https://www.youtube.com/channel/UCaPaxAG2UObG776NJHpdwbw | D191: =COUNTIF(全転載一覧!$B$2:$B$2413,B191) | E191: 1 年前 | F191: 朗読/同形式 | G191: =COUNTIFS(全転載一覧!$B$2:$B$2413,B191,全転載一覧!$N$2:$N$2413,"<>") | H191: =COUNTIFS(全転載一覧!$B$2:$B$2413,B191,全転載一覧!$O$2:$O$2413,"<>")
A192: 191 | B192: Abigail Zev | C192: https://www.youtube.com/channel/UCY6UyFBIk69QFXhMHmo9dWw | D192: =COUNTIF(全転載一覧!$B$2:$B$2413,B192) | E192: 1 年前 | F192: 朗読/同形式 | G192: =COUNTIFS(全転載一覧!$B$2:$B$2413,B192,全転載一覧!$N$2:$N$2413,"<>") | H192: =COUNTIFS(全転載一覧!$B$2:$B$2413,B192,全転載一覧!$O$2:$O$2413,"<>")
A193: 192 | B193: Alexis Dax | C193: https://www.youtube.com/channel/UCcxJzIDFT60xAOJXAQWTnCA | D193: =COUNTIF(全転載一覧!$B$2:$B$2413,B193) | E193: 1 年前 | F193: 朗読/同形式 | G193: =COUNTIFS(全転載一覧!$B$2:$B$2413,B193,全転載一覧!$N$2:$N$2413,"<>") | H193: =COUNTIFS(全転載一覧!$B$2:$B$2413,B193,全転載一覧!$O$2:$O$2413,"<>")
A194: 193 | B194: COLORS DECEIVE | C194: https://www.youtube.com/channel/UCytiIFYh1eDwUeCeeUdLqZQ | D194: =COUNTIF(全転載一覧!$B$2:$B$2413,B194) | E194: 2 年前 | F194: 朗読/同形式 | G194: =COUNTIFS(全転載一覧!$B$2:$B$2413,B194,全転載一覧!$N$2:$N$2413,"<>") | H194: =COUNTIFS(全転載一覧!$B$2:$B$2413,B194,全転載一覧!$O$2:$O$2413,"<>")
A195: 194 | B195: Deadpool Lool | C195: https://www.youtube.com/channel/UCCDbYtkLVK6W2f4MG5hSuBQ | D195: =COUNTIF(全転載一覧!$B$2:$B$2413,B195) | E195: 2 年前 | F195: 朗読/同形式 | G195: =COUNTIFS(全転載一覧!$B$2:$B$2413,B195,全転載一覧!$N$2:$N$2413,"<>") | H195: =COUNTIFS(全転載一覧!$B$2:$B$2413,B195,全転載一覧!$O$2:$O$2413,"<>")
A196: 195 | B196: Heidi Judge | C196: https://www.youtube.com/channel/UCUinF1LRXZ039lhfwhchH-A | D196: =COUNTIF(全転載一覧!$B$2:$B$2413,B196) | E196: 2 年前 | F196: 朗読/同形式 | G196: =COUNTIFS(全転載一覧!$B$2:$B$2413,B196,全転載一覧!$N$2:$N$2413,"<>") | H196: =COUNTIFS(全転載一覧!$B$2:$B$2413,B196,全転載一覧!$O$2:$O$2413,"<>")
... A225: 224 | B225: 人生の分かれ道4716 | C225: https://www.youtube.com/channel/UCeICrgMl03_lHG8LvJYPU_A | D225: =COUNTIF(全転載一覧!$B$2:$B$2413,B225) | E225: 3 週間前 | F225: 朗読/同形式 | G225: =COUNTIFS(全転載一覧!$B$2:$B$2413,B225,全転載一覧!$N$2:$N$2413,"<>") | H225: =COUNTIFS(全転載一覧!$B$2:$B$2413,B225,全転載一覧!$O$2:$O$2413,"<>")
A226: 225 | B226: 人生の物語箱、他 2 チャンネル | D226: =COUNTIF(全転載一覧!$B$2:$B$2413,B226) | E226: 1 か月前 | F226: 朗読/同形式 | G226: =COUNTIFS(全転載一覧!$B$2:$B$2413,B226,全転載一覧!$N$2:$N$2413,"<>") | H226: =COUNTIFS(全転載一覧!$B$2:$B$2413,B226,全転載一覧!$O$2:$O$2413,"<>")
A227: 226 | B227: 人間模様の記録4926 | C227: https://www.youtube.com/channel/UCnD_7fuQhUby4AEJmhWasaQ | D227: =COUNTIF(全転載一覧!$B$2:$B$2413,B227) | E227: 1 か月前 | F227: 朗読/同形式 | G227: =COUNTIFS(全転載一覧!$B$2:$B$2413,B227,全転載一覧!$N$2:$N$2413,"<>") | H227: =COUNTIFS(全転載一覧!$B$2:$B$2413,B227,全転載一覧!$O$2:$O$2413,"<>")
A228: 227 | B228: 小さな幸せ便り | C228: https://www.youtube.com/channel/UCHM9oCUXlsh9yYe3EfDijuA | D228: =COUNTIF(全転載一覧!$B$2:$B$2413,B228) | E228: 3 週間前 | F228: 朗読/同形式 | G228: =COUNTIFS(全転載一覧!$B$2:$B$2413,B228,全転載一覧!$N$2:$N$2413,"<>") | H228: =COUNTIFS(全転載一覧!$B$2:$B$2413,B228,全転載一覧!$O$2:$O$2413,"<>")
A229: 228 | B229: 小刘同学 | C229: https://www.youtube.com/channel/UCVU7qdhT7ffUFt9LherXxwA | D229: =COUNTIF(全転載一覧!$B$2:$B$2413,B229) | E229: 4 週間前 | F229: 朗読/同形式 | G229: =COUNTIFS(全転載一覧!$B$2:$B$2413,B229,全転載一覧!$N$2:$N$2413,"<>") | H229: =COUNTIFS(全転載一覧!$B$2:$B$2413,B229,全転載一覧!$O$2:$O$2413,"<>")
A230: 229 | B230: 山口 るみ | C230: https://www.youtube.com/channel/UCUP10Hi7XrqedvibsczRs1A | D230: =COUNTIF(全転載一覧!$B$2:$B$2413,B230) | E230: 2 年前 | F230: 朗読/同形式 | G230: =COUNTIFS(全転載一覧!$B$2:$B$2413,B230,全転載一覧!$N$2:$N$2413,"<>") | H230: =COUNTIFS(全転載一覧!$B$2:$B$2413,B230,全転載一覧!$O$2:$O$2413,"<>")
A231: 230 | B231: 巡る人生4577 | C231: https://www.youtube.com/channel/UCwN0AryGOqjMHNrKy1XUitQ | D231: =COUNTIF(全転載一覧!$B$2:$B$2413,B231) | E231: 1 か月前 | F231: 朗読/同形式 | G231: =COUNTIFS(全転載一覧!$B$2:$B$2413,B231,全転載一覧!$N$2:$N$2413,"<>") | H231: =COUNTIFS(全転載一覧!$B$2:$B$2413,B231,全転載一覧!$O$2:$O$2413,"<>")
A232: 231 | B232: 平成ストーリー 5691 | C232: https://www.youtube.com/channel/UCmQV3SMY6qKoiJW2Zy5j0Tg | D232: =COUNTIF(全転載一覧!$B$2:$B$2413,B232) | E232: 3 週間前 | F232: 朗読/同形式 | G232: =COUNTIFS(全転載一覧!$B$2:$B$2413,B232,全転載一覧!$N$2:$N$2413,"<>") | H232: =COUNTIFS(全転載一覧!$B$2:$B$2413,B232,全転載一覧!$O$2:$O$2413,"<>")
A233: 232 | B233: 影の告白 5438 | C233: https://www.youtube.com/channel/UComuFUgBo6gXsBacU3_GUmA | D233: =COUNTIF(全転載一覧!$B$2:$B$2413,B233) | E233: 3 週間前 | F233: 朗読/同形式 | G233: =COUNTIFS(全転載一覧!$B$2:$B$2413,B233,全転載一覧!$N$2:$N$2413,"<>") | H233: =COUNTIFS(全転載一覧!$B$2:$B$2413,B233,全転載一覧!$O$2:$O$2413,"<>")
A234: 233 | B234: 心の琴線 5726 | C234: https://www.youtube.com/channel/UCeX0ohQDly_ouo2i6HwylXQ | D234: =COUNTIF(全転載一覧!$B$2:$B$2413,B234) | E234: 2 週間前 | F234: 朗読/同形式 | G234: =COUNTIFS(全転載一覧!$B$2:$B$2413,B234,全転載一覧!$N$2:$N$2413,"<>") | H234: =COUNTIFS(全転載一覧!$B$2:$B$2413,B234,全転載一覧!$O$2:$O$2413,"<>")
A235: 234 | B235: 悪人の末路 | C235: https://www.youtube.com/channel/UCKDr_34u3Plr5f--TCifU7g | D235: =COUNTIF(全転載一覧!$B$2:$B$2413,B235) | E235: 1 か月前 | F235: 朗読/同形式 | G235: =COUNTIFS(全転載一覧!$B$2:$B$2413,B235,全転載一覧!$N$2:$N$2413,"<>") | H235: =COUNTIFS(全転載一覧!$B$2:$B$2413,B235,全転載一覧!$O$2:$O$2413,"<>")
A236: 235 | B236: 感動する話 4991 | C236: https://www.youtube.com/channel/UC2oqyzI78dKFGeqeWSaPWug | D236: =COUNTIF(全転載一覧!$B$2:$B$2413,B236) | E236: 1 か月前 | F236: 朗読/同形式 | G236: =COUNTIFS(全転載一覧!$B$2:$B$2413,B236,全転載一覧!$N$2:$N$2413,"<>") | H236: =COUNTIFS(全転載一覧!$B$2:$B$2413,B236,全転載一覧!$O$2:$O$2413,"<>")
A237: 236 | B237: 感動する話 5014 | C237: https://www.youtube.com/channel/UCqsgQ2Pbd6YQUW4IX3F034w | D237: =COUNTIF(全転載一覧!$B$2:$B$2413,B237) | E237: 1 か月前 | F237: 朗読/同形式 | G237: =COUNTIFS(全転載一覧!$B$2:$B$2413,B237,全転載一覧!$N$2:$N$2413,"<>") | H237: =COUNTIFS(全転載一覧!$B$2:$B$2413,B237,全転載一覧!$O$2:$O$2413,"<>")
A238: 237 | B238: 感動する話 5708 | C238: https://www.youtube.com/channel/UCiez4FwoYHRgWrHDnDR91pw | D238: =COUNTIF(全転載一覧!$B$2:$B$2413,B238) | E238: 2 週間前 | F238: 朗読/同形式 | G238: =COUNTIFS(全転載一覧!$B$2:$B$2413,B238,全転載一覧!$N$2:$N$2413,"<>") | H238: =COUNTIFS(全転載一覧!$B$2:$B$2413,B238,全転載一覧!$O$2:$O$2413,"<>")
...

Sheet ラウンド0_検索上位の転載
A1: No. | B1: 申請日 | C1: 削除確認 | D1: チャンネル名 | E1: チャンネルURL | F1: 転載動画URL | G1: 転載の検索順位 | H1: 本家の検索順位 | I1: 転載の投稿 | J1: 転載の再生数 | K1: 元動画URL | L1: 元動画の再生数 | M1: 元タイトル | N1: メモ
A2: 1 | D2: 実話感動チャンネル | E2: https://www.youtube.com/channel/UCekQO8WQ0udVSYSfX4Pymgw | F2: https://www.youtube.com/watch?v=jv_tPg2W6KU | G2: 1 | H2: 2 | I2: 2 か月前 | J2: 27912 | K2: https://www.youtube.com/watch?v=p4pyD9SD1Tk | L2: 81000 | M2: 【スカッとする話】義両親に蹴られ骨折した私に夫「寝かせとけば治るw」翌日、病室に嘲笑いに来た義家族「あれ、嫁は？w」医師「警察署です」義家族「え？」【朗読】【スカッと】
A3: 2 | D3: 実話感動チャンネル | E3: https://www.youtube.com/channel/UCekQO8WQ0udVSYSfX4Pymgw | F3: https://www.youtube.com/watch?v=qFlVMlu5W_s | G3: 1 | H3: 2 | I3: 3 か月前 | J3: 13613 | K3: https://www.youtube.com/watch?v=nlS5u4pCtI0 | L3: 38000 | M3: 【スカッとする話】警察官の弟の結婚式に出席した私。義母「中卒の姉は一族の恥ねw」直後、慌てた弟が義母に私の正体を伝えると、義母は顔面蒼白に…【朗読】【スカッと】
A4: 3 | D4: 実話感動チャンネル | E4: https://www.youtube.com/channel/UCekQO8WQ0udVSYSfX4Pymgw | F4: https://www.youtube.com/watch?v=3Y0kz4vBXE4 | G4: 1 | H4: 2 | I4: 3 か月前 | J4: 11882 | K4: https://www.youtube.com/watch?v=Tpbu9uHiFPg | L4: 110000 | M4: 【スカッとする話】結婚10年目に銀行員の夫が突然の暴露「お前の親友と結婚するw籍入れてないし財産分与は無しw」私「あれ？あんた知らないの？」夫「何がだよw」実は…
A5: 4 | D5: 実話感動チャンネル | E5: https://www.youtube.com/channel/UCekQO8WQ0udVSYSfX4Pymgw | F5: https://www.youtube.com/watch?v=wC808VvKID0 | G5: 1 | H5: 2 | I5: 2 か月前 | J5: 5598 | K5: https://www.youtube.com/watch?v=9kcEIi88egw | L5: 230000 | M5: 【スカッとする話】自ら命を絶った夫が亡くなり1週間後、私宛に夫から手紙が届いた...手紙「両親に見つからず読んでくれ」そこに記された場所に行き同封の鍵でコインロッカーを開けると...
A6: 5 | D6: 家族の修羅場 | E6: https://www.youtube.com/channel/UCBh3ipHGoPZMTeNkEWdf5kQ | F6: https://www.youtube.com/watch?v=TgQ5XyInIK4 | G6: 1 | H6: 2 | I6: 7 か月前 | J6: 3 | K6: https://www.youtube.com/watch?v=RAvd6Tel5z0 | L6: 27000 | M6: 【スカッとする話】初孫の初節句のお祝いで料亭に行くと私だけ料理がない…長男嫁「家族の分しかないですよw」私「じゃあ他人は帰りますね。仕送り30万もやめるから」
A7: 6 | D7: 家族の修羅場 | E7: https://www.youtube.com/channel/UCBh3ipHGoPZMTeNkEWdf5kQ | F7: https://www.youtube.com/watch?v=73K4XYt9xrc | G7: 1 | H7: 2 | I7: 7 か月前 | J7: 0 | K7: https://www.youtube.com/watch?v=XKULaOclsHw | L7: 19000 | M7: 【スカッとする話】母が危篤になり病院へ急ぐ私に夫「他人のババァとか興味ないwてか出張中は連絡するなw」2週間後、満面の笑みで夫が帰ると→私「お義母さんの葬儀、終わったよ」
A8: 7 | D8: 家族の修羅場 | E8: https://www.youtube.com/channel/UCBh3ipHGoPZMTeNkEWdf5kQ | F8: https://www.youtube.com/watch?v=Dw56BW6dv8A | G8: 1 | H8: 2 | I8: 7 か月前 | J8: 0 | K8: https://www.youtube.com/watch?v=Hf2l_WByhX8 | L8: 15000 | M8: 【スカッとする話】私「ボーナスとミニバンが消えた！」夫「還暦祝いで母さんに譲ったw文句あるなら離婚するぞw」3日後、半狂乱の義母から鬼電→私「あんた誰？」【スカッと】【朗読】
A9: 8 | D9: 家族の修羅場 | E9: https://www.youtube.com/channel/UCBh3ipHGoPZMTeNkEWdf5kQ | F9: https://www.youtube.com/watch?v=hU_nHDJY2IQ | G9: 1 | H9: 2 | I9: 7 か月前 | J9: 0 | K9: https://www.youtube.com/watch?v=AkFPFwnz6fs | L9: 55000 | M9: 【スカッとする話】1億の一軒家に住む金持ち自慢の婚約者の実家へ結婚挨拶に行くと、義父「なんだ？不細工な嫁だなw」義母「親の顔が見てみたいわねw」→母「どうも、不細工の母です」義両親「え？あなたは…」
A10: 9 | D10: Văn Sơn Lã | E10: https://www.youtube.com/channel/UCnSrambnfB2Nc_4BliQ4Aug | F10: https://www.youtube.com/watch?v=hDurNSA0XVU | G10: 1 | H10: 2 | I10: 1 年前 | J10: 0 | K10: https://www.youtube.com/watch?v=a207sJNOihM | L10: 87000 | M10: 【スカッとする話】浮気中の夫が意識不明で運ばれ、救急隊員「意識不明の重体です！」私「旦那じゃありません」無視して夫の人生終了させた結果w
A11: 10 | D11: Văn Sơn Lã | E11: https://www.youtube.com/channel/UCnSrambnfB2Nc_4BliQ4Aug | F11: https://www.youtube.com/watch?v=x6IaaxpWj6s | G11: 1 | H11: 2 | I11: 1 年前 | J11: 0 | K11: https://www.youtube.com/watch?v=urrn4wk835o | L11: 100000 | M11: 【スカッとする話】事故で半身不随の夫の見舞いに来た8歳の姪「この手紙ばぁばから預かったの。夫さんに隠れて読んでって」手紙を確認した私は慌てて夫のズボンを脱がし...
A12: 11 | D12: Văn Sơn Lã | E12: https://www.youtube.com/channel/UCnSrambnfB2Nc_4BliQ4Aug | F12: https://www.youtube.com/watch?v=xOwGZi2Qd64 | G12: 1 | H12: 2 | I12: 1 年前 | J12: 1 | K12: https://www.youtube.com/watch?v=14YEbx6YYwk | L12: 42000 | M12: 【スカッとする話】家事に疲れて休憩していると妊娠9ヶ月の私を蹴ってきた夫「妊婦だからは甘え！家事サボるな！」無視した私に夫がビール瓶を投げるも当たって血まみれになったのは...
A13: 12 | D13: 人生スカッと朗読館 | E13: https://www.youtube.com/channel/UChTkZ7g3oCCQG3XSqe69LWQ | F13: https://www.youtube.com/watch?v=qsjIpApuEeQ | G13: 1 | H13: 2 | I13: 6 日前 | J13: 0 | K13: https://www.youtube.com/watch?v=hi2PAohyTkU | L13: 20000 | M13: 【スカッとする話】夫の出張中、オウムを任された私。何気なくオウムに話しかけると、オウム「嫁にはバレてないよ」不審に思い夫の部屋を開けた。→直後、私は顔面蒼白に…【朗読ドラマ】【朗読】【スカッと】
... A64: 63 | D64: 話題のLINE | E64: https://www.youtube.com/channel/UCPUjukg0U7MOqNIw_4l5hkA | F64: https://www.youtube.com/watch?v=ljV5pcl0_Uw | G64: 1 | H64: 3 | I64: 2 年前 | J64: 526913 | K64: https://www.youtube.com/watch?v=iT0GjRHrB6w | L64: 260000 | M64: 【スカッとする話】年末年始の親族の集まりで20人分のおせちをゴミ箱にぶちまけたエリート夫「親戚にマズイ飯を作るな！」私「私は何も作ってないよ？」夫「え？」実は...
A65: 64 | D65: 静かな夜の物語、雨の中の記憶 | F65: https://www.youtube.com/watch?v=ze9iOqJewBo | G65: 1 | H65: 2 | I65: 2 週間前 | J65: 0 | K65: https://www.youtube.com/watch?v=T40Q2m3NnVw | L65: 60000 | M65: 【スカッとする話】私の里帰り中に医者の婚約者を略奪した姉から連絡「彼の赤ちゃん妊娠したwアンタは帰ってくるなw」私「いいの？有り難う！」そのまま新居に引越した結果w
A66: 65 | D66: 静かな夜の物語、雨の中の記憶 | F66: https://www.youtube.com/watch?v=o0udygfbu2Y | G66: 1 | H66: 圏外 | I66: 10 日前 | J66: 2 | K66: https://www.youtube.com/watch?v=cF4ti4NhgGU | L66: 170000 | M66: 【スカッとする話】地下室に隠れ夫と親友が真っ最中だった...母「嫁子、戸締りしておいたわよ！」ど天然の母が気づかず鍵を閉めたので永遠に放置し新居に引越した結果w
A67: 66 | D67: 静かな夜の物語、静かな心の記録 | F67: https://www.youtube.com/watch?v=GzdH1HjwK5s | G67: 1 | H67: 2 | I67: 1 か月前 | J67: 0 | K67: https://www.youtube.com/watch?v=Eh0FIn_sub0 | L67: 56000 | M67: 【スカッとする話】8歳の姪「1日だけ泊めて下さい...」大雪の中、赤ちゃんを抱き抱えボロボロの姿で現れた姪...。夫「え？それは無理だよ？」姪「そんな…涙」→結果
A68: 67 | D68: 静かな夜の物語、静かな心の記録 | F68: https://www.youtube.com/watch?v=zcVtcsNhvSU | G68: 1 | H68: 2 | I68: 23 時間前 | J68: 0 | K68: https://www.youtube.com/watch?v=-EQHZjnhA9w | L68: 28000 | M68: 【スカッとする話】一人暮らしの私のことを気遣う娘に私「いつも仕送りありがとう。月1000円でも気持ちが嬉しいわよ」娘「え？毎月13万送金してるよ？」私「えっ？」直後、娘が私の銀行口座を止めると...
A69: 68 | D69: 読書室【スカッとする話】 | E69: https://www.youtube.com/channel/UCjQd7ZVm5BPbGpB_V9B6kgQ | F69: https://www.youtube.com/watch?v=ItiHHN9nAoE | G69: 2 | H69: 3 | I69: 1 年前 | J69: 0 | K69: https://www.youtube.com/watch?v=KMhlovvuqDg | L69: 28000 | M69: 【スカッとする話】13億の資産を築いた夫の葬儀後、通帳と印鑑を盗んだ義両親「3000万の家買っちゃったw」それを聞いてお腹を抱えて大爆笑→私「御愁傷さまw」実は...【スカッと】【朗読】
A70: 69 | D70: 468 Ungthuphoi | E70: https://www.youtube.com/channel/UChMTaakDMyRJ8dYWT6dyj6A | F70: https://www.youtube.com/watch?v=KXFghHJtNeI | G70: 1 | H70: 2 | I70: 1 年前 | J70: 47 | K70: https://www.youtube.com/watch?v=wjCku8hnE4A | L70: 21000 | M70: 【スカッとする話】母に誘われ高級料亭へ行くと女性にプロポーズする夫「亡き妻の分まで君を幸せにする！」直後、普段温厚な母が立ち上がり、母「お隣いいですか？」結果w
A71: 70 | D71: 578 Nhumotbong | E71: https://www.youtube.com/channel/UC0biqKicwkA9gYrdBBgU1-w | F71: https://www.youtube.com/watch?v=ZMKLsP9ebxU | G71: 1 | H71: 3 | I71: 1 年前 | J71: 1 | K71: https://www.youtube.com/watch?v=McNVTi5SXBU | L71: 95000 | M71: 【スカッとする話】姑との同居を勝手に決めた夫「引越しは済んだか？」私「うん！私の荷物も全部実家に送り終わったとこ」夫「え？実家？」結果w【修羅場】
A72: 71 | D72: 679 Moicaitay | E72: https://www.youtube.com/channel/UCbS2i6mY4rmoSoHWGu7uiYA | F72: https://www.youtube.com/watch?v=XM51nQV3pRg | G72: 1 | H72: 2 | I72: 1 年前 | J72: 0 | K72: https://www.youtube.com/watch?v=2ytRePzCVrE | L72: 60000 | M72: 【スカッとする話】私の出張中に勝手に姉と姪の引越し荷物を我が家に運び入れた夫「お前はずっと仕事してろw」私「はーい、こっちも勝手にするね」ハワイの豪邸に引越した結果w
A73: 72 | D73: Bonnie Denver | E73: https://www.youtube.com/channel/UCsdndA886timZqWK6_b0d0Q | F73: https://www.youtube.com/watch?v=mNNqKsGw3zk | G73: 1 | H73: 3 | I73: 1 年前 | J73: 0 | K73: https://www.youtube.com/watch?v=k6GWqtIXUlQ | L73: 42000 | M73: 【スカッとする話】台風の夜、5歳の孫からSOS「ママに家を追い出された！助けて」私「パパは？」孫「知らない女の人と出て行った」私「え？」キレた私は...
A74: 73 | D74: COLORS DECEIVE | E74: https://www.youtube.com/channel/UCytiIFYh1eDwUeCeeUdLqZQ | F74: https://www.youtube.com/watch?v=-y-Wocuo5FY | G74: 1 | H74: 2 | I74: 2 年前 | J74: 4734 | K74: https://www.youtube.com/watch?v=U9HQWEyzPVc | L74: 64000 | M74: 【スカッとする話】11億の資産を築いた父の葬儀後に夫が突然「父さんの遺産いくらあるんだ？w」私「3億通帳に入れてるよ」翌朝、離婚届けを置き通帳と印鑑を盗んだ夫が家に来て「あ、あの通帳って」
A75: 74 | D75: Dau Conhoen | E75: https://www.youtube.com/channel/UCbc3JRrwmaDW2_mYXitLGCg | F75: https://www.youtube.com/watch?v=gRDlO_YWtwA | G75: 1 | H75: 2 | I75: 2 年前 | J75: 353 | K75: https://www.youtube.com/watch?v=8Tm2R7t4MCc | L75: 140000 | M75: 【スカッとする話】家事、育児、介護、パートをこなし10年。ある日、出張後に夫が突然の土下座「お前の親友を妊娠させた！」親友「旦那は貰うから出てけw」私「喜んで！」3日後、血相変えた親友から鬼電がw
A76: 75 | D76: Deadpool Lool | E76: https://www.youtube.com/channel/UCCDbYtkLVK6W2f4MG5hSuBQ | F76: https://www.youtube.com/watch?v=gKvYOjL-TSQ | G76: 1 | H76: 2 | I76: 2 年前 | J76: 1 | K76: https://www.youtube.com/watch?v=jA4TTTeqo-M | L76: 120000 | M76: 【スカッとする話】私が年商500億の社長と知らない夫「時給941円の底辺は出てけw」連れ子「役立たずの母親バイバイw」私「じゃあ出ていきます」１ヶ月後、涙を流した夫から鬼電がw
A77: 76 | D77: Elliot Perry | E77: https://www.youtube.com/channel/UCu6sSOVx4IweXf0aPxIradQ | F77: https://www.youtube.com/watch?v=YI-bX_pqL4E | G77: 1 | H77: 2 | I77: 1 年前 | J77: 0 | K77: https://www.youtube.com/watch?v=N9NwywjCXnU | L77: 67000 | M77: 【スカッとする話】大学から10年付き合った婚約者「10代の嫁が良い！そろそろ婚活するからもう別れよ！」捨てられ3年後に婚約者から鬼電→私「あんた誰だっけ？」
A78: 77 | D78: FutureLens | E78: https://www.youtube.com/channel/UC1l4HieEbZPmgNoaCJdgHdw | F78: https://www.youtube.com/watch?v=CRlkbIQAxQk | G78: 1 | H78: 2 | I78: 4 週間前 | J78: 74 | K78: https://www.youtube.com/watch?v=6wF7ONOegQ0 | L78: 30000 | M78: 【スカッとする話】38歳で第一子を出産した私を捨て、19歳年下の不倫相手を優先した夫「可愛い子供が欲しかったな。お前との子はブスだから離婚で」18年後、娘と再会した夫が青ざめw【朗読】【スカッと】
A79: 78 | D79: Helen Chaney | E79: https://www.youtube.com/channel/UCknZc7rOLWhfFlVN8PKKzGQ | F79: https://www.youtube.com/watch?v=VN4pcX92erg | G79: 2 | H79: 3 | I79: 2 年前 | J79: 62 | K79: https://www.youtube.com/watch?v=9x2mRPOpvjQ | L79: 70000 | M79: 【スカッとする話】娘の結婚式当日に夫がいない…私「何してるの？式始まってるよ！」夫「悪い、緊急の仕事が入って！」私「…OK」1時間後、ある人物から電話を受けた夫が半狂乱にw
A80: 79 | D80: Hidalgo Jesus | E80: https://www.youtube.com/channel/UCmHPxolrDN4OJyWrR31soAA | F80: https://www.youtube.com/watch?v=jFXlACv0pLg | G80: 2 | H80: 3 | I80: 2 年前 | J80: 0 | K80: https://www.youtube.com/watch?v=2bkFoDUO1Qo | L80: 150000 | M80: 【スカッとする話】長男夫婦に初孫が生まれ出産祝いに行くと私だけカップ麺...長男嫁「家族の分しか無いですw」夫「...帰りますか」私「はい」直後、長男嫁に大惨事がw
... A106: 105 | D106: 人生の光と影 | E106: https://www.youtube.com/channel/UCYX4tsWpykTmtfNq_i36C_w | F106: https://www.youtube.com/watch?v=cYepYy4CPGU | G106: 1 | H106: 2 | I106: 5 日前 | J106: 87 | K106: https://www.youtube.com/watch?v=Ru27si_54MQ | L106: 300000 | M106: 【スカッとする話】結婚し幸せな日常を送る息子が急逝し13日後、私宛に亡き息子から手紙が届いた。手紙「俺の代わりに嫁に復讐を...」手紙で指定された場所に行った私は恐怖で震えだし...
A107: 106 | D107: 人生の小径、Love in later life | F107: https://www.youtube.com/watch?v=XdEKWgjOb-I | G107: 1 | H107: 2 | I107: 1 か月前 | J107: 9 | K107: https://www.youtube.com/watch?v=q3GnEwyCGbE | L107: 18000 | M107: 【スカッとする話】夫の手帳から愛人と隠し子との家族写真、更に離婚届が…。私「離婚したいから出せってことか！」即提出して夫の荷物を全て処分→黙って永久に姿を消した結果w
A108: 107 | D108: 人生の感動物語 | E108: https://www.youtube.com/channel/UCLq7Bngo0s5xFWKcyKaJHWA | F108: https://www.youtube.com/watch?v=2bnA0iWe1fM | G108: 6 | H108: 7 | I108: 2 か月前 | J108: 2 | K108: https://www.youtube.com/watch?v=NTuf2k99EWQ | L108: 270000 | M108: 【スカッとする話】体調不良でパートを早退し家に帰ると夫が親友と真っ最中...コッソリ二人の動画を撮影し親友の夫に送ってやった結果w
A109: 108 | D109: 人生の教訓 5696 | E109: https://www.youtube.com/channel/UChL0a6zTE7nHEavxEB0mGtQ | F109: https://www.youtube.com/watch?v=pE7R3YQKIW0 | G109: 1 | H109: 2 | I109: 3 週間前 | J109: 1 | K109: https://www.youtube.com/watch?v=39BPJNaibmM | L109: 75000 | M109: 【スカッとする話】父の会社を手伝って25年の私に夫「俺、来月引退することにした…会社は東京にいる長男に任せる」私「勝手にどうぞ。私今日でここ辞めるので」直後、父が半狂乱にw【朗読】【スカッと】
A110: 109 | D110: 人生の晩年5045 | E110: https://www.youtube.com/channel/UCRajns3nAnfDW1XFNGE8mjg | F110: https://www.youtube.com/watch?v=tH1-lLCCL1I | G110: 2 | H110: 4 | I110: 1 か月前 | J110: 6 | K110: https://www.youtube.com/watch?v=n-_5T-nb0dg | L110: 37000 | M110: 【スカッと】起業した夫を支えてきた私を裏切った夫「21歳のバイトを妊娠させた！離婚しで！」私「はーい、仕事も辞めるね！」夫「は？仕事は続けてくれよ」私「嫌よ。だってあのバイト...」
A111: 110 | D111: 人生逆転劇 | E111: https://www.youtube.com/channel/UChQ1QPCoCPRXlD5aqltcP2Q | F111: https://www.youtube.com/watch?v=iDMUfsZ73Bo | G111: 1 | H111: 2 | I111: 1 か月前 | J111: 27 | K111: https://www.youtube.com/watch?v=zb8EIRbjwZc | L111: 29000 | M111: 【スカッと総集編】妊娠した私を捨て21歳の浮気相手と再婚した社長の夫「彼女が妊娠したから離婚w」20年後、公園で元夫と再会すると…【スカッと】【スカッとする話】【修羅場】
A112: 111 | D112: 人生逆転噺5074 | E112: https://www.youtube.com/channel/UCSE8UrVc2WuisTfaKPVRjGA | F112: https://www.youtube.com/watch?v=nPSLaGnDiuQ | G112: 1 | H112: 2 | I112: 1 か月前 | J112: 1 | K112: https://www.youtube.com/watch?v=xZkf_P7X0BY | L112: 98000 | M112: 【スカッとする話】兄夫婦の出産祝いで父親と家を訪ねると父「今すぐ帰る！車を出せ！」慌てる父に理由を訪ねると、父「バックミラー見てみろ」私「え？」【朗読】【スカッと】
A113: 112 | D113: 今日の物語 | E113: https://www.youtube.com/channel/UCPXh5v9VEouZRWDFnMm2RNg | F113: https://www.youtube.com/watch?v=41IKF-y9FF4 | G113: 1 | H113: 2 | I113: 3 か月前 | J113: 150 | K113: https://www.youtube.com/watch?v=Mpi2bhYFSsQ | L113: 140000 | M113: 【スカッとする話】私が毎日12時間、義父の介護をしていると知らない夫「離婚しよう…お前と一緒はもう限界…」私「本当にいいの？」夫「当然w」→介護負担を伝えず即離婚して姿を消すと…w【朗読】【スカッと】
A114: 113 | D114: 午後の茶室5033 | E114: https://www.youtube.com/channel/UCAY-Kr81JdEZjsie9IiR_bw | F114: https://www.youtube.com/watch?v=c5j-gRh8bBE | G114: 1 | H114: 2 | I114: 3 週間前 | J114: 136 | K114: https://www.youtube.com/watch?v=bDw-dlei5Gk | L114: 46000 | M114: 【スカッと総集編】私が夫の入院費を払ってると知らず新居に引越した夫の連れ子「いつまで寄生虫するの？w」私「じゃ出てく」連れ子だけ残し1億の豪邸に引越した結果w
A115: 114 | D115: 嘘と温もり 5646 | E115: https://www.youtube.com/channel/UCxtvYnyBSRQBeUoKt9cvsmw | F115: https://www.youtube.com/watch?v=VGZ8u9KN8Vs | G115: 1 | H115: 2 | I115: 3 週間前 | J115: 0 | K115: https://www.youtube.com/watch?v=xyoQNySkFhc | L115: 100000 | M115: 【スカッとする話】私の事が大嫌いな長男嫁「ウチの冠婚葬祭に義両親は絶対来ないで。嫌なら離婚する」私「いいけど、アナタ本当に大丈夫？後悔するよ？」長男嫁「しねぇよw二度と連絡してくんなw」→数ヶ月後w
A116: 115 | D116: 堀田 あやか | E116: https://www.youtube.com/channel/UCA_Jou4B-xo7nsjrqftqHJQ | F116: https://www.youtube.com/watch?v=UVuBeZfUQlk | G116: 1 | H116: 2 | I116: 2 年前 | J116: 0 | K116: https://www.youtube.com/watch?v=0AsFooilZ4k | L116: 120000 | M116: 【スカッとする話】長男嫁から突然怒りの電話「お義父の介護費用、ちょっとはお義母さんも払ってください！」私「え？私に夫はいませんが」長男嫁「え？」実は…【修羅場】【スカッと】
A117: 116 | D117: 壊れかけた巣 5653 | E117: https://www.youtube.com/channel/UCCxdsvXDsa6Fg4zEu_0fDoA | F117: https://www.youtube.com/watch?v=gykK75sSLwQ | G117: 2 | H117: 3 | I117: 3 週間前 | J117: 3 | K117: https://www.youtube.com/watch?v=McNVTi5SXBU | L117: 95000 | M117: 【スカッとする話】姑との同居を勝手に決めた夫「引越しは済んだか？」私「うん！私の荷物も全部実家に送り終わったとこ」夫「え？実家？」結果w【修羅場】
A118: 117 | D118: 大人のスカッと物語 | E118: https://www.youtube.com/channel/UC3_22iiSJgBR1aGvyoWj1gg | F118: https://www.youtube.com/watch?v=1USAusebSpE | G118: 1 | H118: 2 | I118: 3 か月前 | J118: 1 | K118: https://www.youtube.com/watch?v=mgV03N2miWM | L118: 43000 | M118: 【スカッとする話】私が総資産11億の主婦と知らずに夫「仕事もしない役立たずは出てけw」連れ子「寄生虫は今すぐ母親辞めろw」私「承知しました」1年後、夫と連れ子から鬼電がw
A119: 118 | D119: 姑の裏の顔 5668 | E119: https://www.youtube.com/channel/UCAUkwErZzfdQ5NFOS49O-rw | F119: https://www.youtube.com/watch?v=HpCgM5Pwq-Q | G119: 2 | H119: 3 | I119: 2 日前 | J119: 0 | K119: https://www.youtube.com/watch?v=5GO3xM_YnnI | L119: 83000 | M119: 【スカッと総集編】私が家族9人を養ってると知らず荷物を全て捨てた義母「いつまで我が家に寄生するの？w」私「では引っ越しますね」義母だけ残し豪邸に引越した結果w
... A121: 120 | D121: 孤独な心 | E121: https://www.youtube.com/channel/UCSNdJwT8r-r8xVDRxs6utlw | F121: https://www.youtube.com/watch?v=u1GSjSJh3R0 | G121: 1 | H121: 2 | I121: 1 年前 | J121: 17 | K121: https://www.youtube.com/watch?v=g4FVXeIsDTQ | L121: 140000 | M121: 【スカッとする話】夫を略奪した姉から結婚式の招待状が届くと、父「母さんと2人で行くよ」母「地獄を見せてくるわね」普段温厚な両親がこの後...w
A122: 121 | D122: 実話感動チャンネル、他 2 チャンネル | F122: https://www.youtube.com/watch?v=kxUtH92Mc5Q | G122: 2 | H122: 3 | I122: 1 か月前 | J122: 4379 | K122: https://www.youtube.com/watch?v=cJTBStbKuvI | L122: 29000 | M122: 【スカッとする話】里帰り出産から帰ると、浮気夫「すまん、離婚してくれ…」愛人「金目当ての女は消えてw」私「OK（大丈夫かな？w借金1億あるけどw）」【朗読】【スカッと】
A123: 122 | D123: 家庭の奇妙な話 5500 | E123: https://www.youtube.com/channel/UCyECOcLVBmrEH9eCxnZtzEg | F123: https://www.youtube.com/watch?v=H1qwUEBaWy0 | G123: 2 | H123: 3 | I123: 3 週間前 | J123: 3 | K123: https://www.youtube.com/watch?v=nmxjuOeyqQ8 | L123: 23000 | M123: 【スカッとする話】娘の寝室に入り5時間出てこない義父。不審に思った私と夫が静かに扉を開けた瞬間、私たちは顔面蒼白に…【朗読】【スカッと】
A124: 123 | D124: 小刘同学 | E124: https://www.youtube.com/channel/UCVU7qdhT7ffUFt9LherXxwA | F124: https://www.youtube.com/watch?v=Ih_wpUdxcEo | G124: 1 | H124: 3 | I124: 3 週間前 | J124: 0 | K124: https://www.youtube.com/watch?v=4cntzQ0KsAA | L124: 130000 | M124: 【スカッとする話】妹の出産祝いに義両親と行くと、夫「俺も自分の子供欲しいな」私「え？何言ってるの？目の前にいるじゃない」義母と義父「は？」二人がブチギレ
A125: 124 | D125: 小川 まりこ | E125: https://www.youtube.com/channel/UC53MBRQyKkDsuQiIxcBTGUQ | F125: https://www.youtube.com/watch?v=ZutqMgKZErI | G125: 2 | H125: 3 | I125: 2 年前 | J125: 0 | K125: https://www.youtube.com/watch?v=NAEwCqwiBcg | L125: 67000 | M125: 【スカッとする話】私名義の4LDKマンションと知らず、強引に私を追い出す姑と義姉「家は貰う！寄生虫は出て行け！」稼ぎ頭の私「わかりました…」→私物を全て回収し、家賃30万の家だけ残した結果w【修羅場】
A126: 125 | D126: 尴尬笑场团 | E126: https://www.youtube.com/channel/UCzUkBP4kXovWWNL8PmpEDbg | F126: https://www.youtube.com/watch?v=h6_FVKQ7C9U | G126: 1 | H126: 2 | I126: 1 日前 | J126: 0 | K126: https://www.youtube.com/watch?v=hRCh_bWpcgg | L126: 100000 | M126: 【スカッとする話】私が義母の入院費を払ってると知らず新居に引っ越した夫「寄生虫は施設でもいけw」1億の高級施設に引越し入院費の支払も止めた結果w
A127: 126 | D127: 山口 るみ | E127: https://www.youtube.com/channel/UCUP10Hi7XrqedvibsczRs1A | F127: https://www.youtube.com/watch?v=dKeZrvZkH6c | G127: 1 | H127: 2 | I127: 2 年前 | J127: 0 | K127: https://www.youtube.com/watch?v=8k24mctnXF4 | L127: 42000 | M127: 【スカッとする話】夫が結婚式へ行くと娘が突然「パパが乗る飛行機が燃えてる...」私「え？一体どうしたの？」直後、不思議な力を持つ娘がある物を指差し、娘「あれが証拠だよ」実は...【修羅場】
A128: 127 | D128: 心のラジオ 5704 | E128: https://www.youtube.com/channel/UCTYL3zm2mHCTixzhSZRtx0w | F128: https://www.youtube.com/watch?v=Rwh6U-NjqG4 | G128: 1 | H128: 2 | I128: 2 週間前 | J128: 1 | K128: https://www.youtube.com/watch?v=-rCnVoxQEpM | L128: 62000 | M128: 【スカッとする話】病院から突然の電話で看護師「夫さん倒れて緊急入院です！病院代支払いに来て下さい！」私「もう支払い済ですよ？」看護師「え？」実は…【朗読】【スカッと】
A129: 128 | D129: 心温まるストーリー 4989 | E129: https://www.youtube.com/channel/UCS-VuYFB_DXsDhPHAzUS0JA | F129: https://www.youtube.com/watch?v=2pKVUEdoXJI | G129: 1 | H129: 3 | I129: 3 週間前 | J129: 19 | K129: https://www.youtube.com/watch?v=vQdhdcwgO20 | L129: 21000 | M129: 【スカッとする話】父が急逝し女社長になった私。副社長「これ退職届80人分wコネだけの女は皆無理ってw」翌日、新聞を見た元部下が土下座→全員を無視してあげた結果w【朗読】【スカッと】
A130: 129 | D130: 心温まる物語 5715 | E130: https://www.youtube.com/channel/UCp5XuGGZyQWEBrJpOq-DHdw | F130: https://www.youtube.com/watch?v=BDesDtjgN10 | G130: 1 | H130: 3 | I130: 3 週間前 | J130: 60 | K130: https://www.youtube.com/watch?v=-4yhJ5v7T4s | L130: 17000 | M130: 【スカッとする話】大手銀行で5時間待たされた。私「30億おろします」銀行員「残高300円じゃねーか底辺ババァw」私「貸金庫のお金30億他に移すわ」
A131: 130 | D131: 悠久の日本物語、Love in later life | F131: https://www.youtube.com/watch?v=VdMoB4jLY94 | G131: 1 | H131: 2 | I131: 1 か月前 | J131: 37 | K131: https://www.youtube.com/watch?v=wdxUcG1tem8 | L131: 200000 | M131: 【スカッとする話】母の葬儀中に夫から電話「親戚の集まりなのにサボるな！親の葬儀とか知るか今すぐ来い」私「分かりました」喪服のまま駆け付けた結果ｗ
A132: 131 | D132: 愛憎の交差点 5648 | E132: https://www.youtube.com/channel/UCZ27s-bExyb-zcqGkYvoicQ | F132: https://www.youtube.com/watch?v=KBXbnqmHN3c | G132: 1 | H132: 2 | I132: 3 週間前 | J132: 0 | K132: https://www.youtube.com/watch?v=F74TRQPted4 | L132: 230000 | M132: 【スカッとする話】体調不良でパートを早退し家に帰ると夫が義母と真っ最中...私「お義父さん、大変です！」義父をその場に凸させた結果w
A133: 132 | D133: 感動する話 026 | E133: https://www.youtube.com/channel/UCqHEaSgEBh5CGxnv61bbyvQ | F133: https://www.youtube.com/watch?v=i287iWPogAM | G133: 2 | H133: 3 | I133: 3 年前 | J133: 2 | K133: https://www.youtube.com/watch?v=luo2hcOOZik | L133: 140000 | M133: 【スカッとする話】私と夫の事が大嫌いな長男夫婦「俺達の結婚式は欠席しろ。嫌なら絶縁する」私「いいけど、アナタ達本当に大丈夫？後悔するよ？」長男「しねぇよw二度と連絡してくんなw」数ヶ月後w【修羅場】
A134: 133 | D134: 感動のストーリー 5718 | E134: https://www.youtube.com/channel/UChJXskMmVDbiJsbH0jjVRUg | F134: https://www.youtube.com/watch?v=PhzawcLuby0 | G134: 1 | H134: 2 | I134: 4 週間前 | J134: 3 | K134: https://www.youtube.com/watch?v=292Mju-11jU | L134: 42000 | M134: 【スカッとする話】余命半年と宣告された私に夫「保険金3000万楽しみだ！仕事も辞めちゃおうかなw」私（受け取れるわけないのにw）半年後、夫が半狂乱にw【朗読】【スカッと】
A135: 134 | D135: 感動の話 | E135: https://www.youtube.com/channel/UCZE_yArcdxL_mMeMGYBVO8A | F135: https://www.youtube.com/watch?v=msusD7MaUzo | G135: 2 | H135: 3 | I135: 6 か月前 | J135: 354 | K135: https://www.youtube.com/watch?v=tfbycPtFjbg | L135: 170000 | M135: 【スカッとする話】義母を10年介護している私に夫「離婚してくれ…老後もお前と一緒は無理…」私「じゃあ介護と嫁辞めるね」即離婚して沖縄に引越すと夫から鬼電→携帯解約し永久に無視した結果w【朗読】
A136: 135 | D136: 感動サプライズ朗読 | E136: https://www.youtube.com/channel/UCVwHsLnY-oFWKcwz_e3OiTw | F136: https://www.youtube.com/watch?v=mqxqoDxdiEI | G136: 1 | H136: 2 | I136: 2 年前 | J136: 42 | K136: https://www.youtube.com/watch?v=0U4B813ccGQ | L136: 37000 | M136: 【スカッとする話】私が癌で入院になった途端に夫「通帳と印鑑はどこにあるんだ？俺が管理してやるから任せろw」私「5000万あるから宜しく」→1ヶ月後、通帳と印鑑と共に離婚届けだけを残し夫が消えた...
A137: 136 | D137: 感動スカッ | E137: https://www.youtube.com/channel/UC_AlxSO8zevgbkHYbk8WFzA | F137: https://www.youtube.com/watch?v=ED3hBxqLxrQ | G137: 1 | H137: 2 | I137: 1 年前 | J137: 1 | K137: https://www.youtube.com/watch?v=yefpSXnGZOg | L137: 150000 | M137: 【スカッとする話】私名義の新築戸建と知らず里帰り出産で我が家に来た娘「母さんの部屋は私が使うw」夫「お前は車で寝てろw」私「わかりました...」→キレた私が家を売り払うと...w
A138: 137 | D138: 日常の物語 5630 | E138: https://www.youtube.com/channel/UCrhCCeFTpz-DPK7whyTKW8A | F138: https://www.youtube.com/watch?v=1qrlGonnGX0 | G138: 1 | H138: 2 | I138: 3 週間前 | J138: 80 | K138: https://www.youtube.com/watch?v=F8aYLPS1MQo | L138: 230000 | M138: 【スカッと総集編】長男夫婦からの仕送りがなぜか毎回5010円。不審に思い長男に尋ねると「俺は振り込んで無いけど？」私「はい？」実は…【修羅場】【スカッと】【スカッとする話】
A139: 138 | D139: 日料寿司料理 | E139: https://www.youtube.com/channel/UC8w8D_s25Z0LGR34gpcn2JQ | F139: https://www.youtube.com/watch?v=alZdxZpSk_k | G139: 1 | H139: 2 | I139: 2 週間前 | J139: 2 | K139: https://www.youtube.com/watch?v=jcLkESG2h5U | L139: 47000 | M139: 【スカッと】単身赴任の夫の家へサプライズで行くと記入済みの離婚届が...私「お望み通り提出するか」速攻で提出して携帯解約し家を売却して海外移住した結果w
A140: 139 | D140: 日本の物語 〜老後の人生〜 | E140: https://www.youtube.com/channel/UCEZOpLWYD1o09D4aS_BZmbA | F140: https://www.youtube.com/watch?v=AH8CnLKGWQM | G140: 1 | H140: 4 | I140: 1 か月前 | J140: 28 | K140: https://www.youtube.com/watch?v=n-_5T-nb0dg | L140: 37000 | M140: 【スカッと】起業した夫を支えてきた私を裏切った夫「21歳のバイトを妊娠させた！離婚しで！」私「はーい、仕事も辞めるね！」夫「は？仕事は続けてくれよ」私「嫌よ。だってあのバイト...」
A141: 140 | D141: 昭和の記憶、感動する話 | F141: https://www.youtube.com/watch?v=gEeA_My_hRM | G141: 1 | H141: 2 | I141: 5 か月前 | J141: 46 | K141: https://www.youtube.com/watch?v=ZRMhr32Ws-4 | L141: 64000 | M141: 【スカッとする話】実家へ向かう電車に乗る直前、見知らぬ老人に服を引っ張られ、老人「行っちゃダメ、信じてくれ」老人の言う通りにすると、半狂乱の義家族から鬼電がw【朗読】【スカッと】
A142: 141 | D142: 柚子茶と回想 | E142: https://www.youtube.com/channel/UCsSsbPhLxU5hpXwmCpIG6og | F142: https://www.youtube.com/watch?v=74VND3JY1KM | G142: 1 | H142: 3 | I142: 5 か月前 | J142: 541 | K142: https://www.youtube.com/watch?v=tfbycPtFjbg | L142: 170000 | M142: 【スカッとする話】義母を10年介護している私に夫「離婚してくれ…老後もお前と一緒は無理…」私「じゃあ介護と嫁辞めるね」即離婚して沖縄に引越すと夫から鬼電→携帯解約し永久に無視した結果w【朗読】
A143: 142 | D143: 段小段 | E143: https://www.youtube.com/channel/UC73C1p_AtHaQAjc8wiv54mw | F143: https://www.youtube.com/watch?v=hl0tnMTRcoE | G143: 1 | H143: 2 | I143: 5 日前 | J143: 0 | K143: https://www.youtube.com/watch?v=7BkfeUd5plU | L143: 76000 | M143: 【スカッとする話】私が役員報酬で家計を支えていると知らず夫を略奪し引越した愛人。愛人「家政婦で良いなら住所教えるよw」私「じゃ時給780円の夫とは離婚で」愛人「寝言は寝て言えw」結果w
A144: 143 | D144: 毎日が喜び | E144: https://www.youtube.com/channel/UCms4kBFMhD7L74TA7J7ikaQ | F144: https://www.youtube.com/watch?v=pAkI99M8o5I | G144: 1 | H144: 2 | I144: 3 か月前 | J144: 3 | K144: https://www.youtube.com/watch?v=ULpnjx45zHg | L144: 31000 | M144: 【スカッとする話】医者の婚約者を奪った妹「高収入の彼は私が貰うｗブサイクは庶民と合コンしてろw」直後、お腹を抱え大爆笑した私→私「病院の院長は私だけど？」
A145: 144 | D145: 毎日新しい物語 | E145: https://www.youtube.com/channel/UCPQauCR7i_WSrZhft4ORBbg | F145: https://www.youtube.com/watch?v=kcvkSGcWDwM | G145: 1 | H145: 2 | I145: 2 年前 | J145: 227 | K145: https://www.youtube.com/watch?v=nN0MMqPfpd0 | L145: 40000 | M145: 【スカッとする話】私の両親が亡くなった途端、実家を勝手に建て替えた夫「愛人と隠し子と住む家建てるw」私「アンタら終わったね」3日後、夫と愛人が半狂乱にw
A146: 145 | D146: 涙が止まらない本当の話 | E146: https://www.youtube.com/channel/UC-rAVI-jHz59_dhCmwgr3wg | F146: https://www.youtube.com/watch?v=QEp7k6Cqlxc | G146: 2 | H146: 3 | I146: 4 か月前 | J146: 589 | K146: https://www.youtube.com/watch?v=ZSMzLBZN4z0 | L146: 12000 | M146: 【スカッとする話】手術当日、怯える私を見捨て、平然と飲み会へ向かった夫。1年後、夫の癌が発覚すると夫「怖いから来てくれ、頼む」私「飲み会だから無理w」結果w【朗読】【スカッと】
A147: 146 | D147: 涙が止まらない本当の話、心に響く感動ストーリー | F147: https://www.youtube.com/watch?v=qhhzp0sGBag | G147: 1 | H147: 7 | I147: 4 か月前 | J147: 889 | K147: https://www.youtube.com/watch?v=NTuf2k99EWQ | L147: 270000 | M147: 【スカッとする話】体調不良でパートを早退し家に帰ると夫が親友と真っ最中...コッソリ二人の動画を撮影し親友の夫に送ってやった結果w
A148: 147 | D148: 涙の数だけ 5716 | E148: https://www.youtube.com/channel/UCw2xsZd4GSJowgB3QGFuxLQ | F148: https://www.youtube.com/watch?v=Sztz4XKNtGk | G148: 2 | H148: 3 | I148: 3 週間前 | J148: 65 | K148: https://www.youtube.com/watch?v=nb_aRD_6UTg | L148: 27000 | M148: 【スカッとする話】親友が急逝し女手一つで引き取り育てた娘の結婚式で私の席にだけ盛り塩が置かれていた。医者の新郎母「母子家庭の母は一族の恥w」娘「…母さん帰ろう」私「…うん」翌日、新郎一家は全てを失い…
A149: 148 | D149: 涙の食卓 5651 | E149: https://www.youtube.com/channel/UCDts-8SRBGNQEaBIhxtE0tw | F149: https://www.youtube.com/watch?v=gq_ltzd-xGY | G149: 1 | H149: 圏外 | I149: 3 週間前 | J149: 0 | K149: https://www.youtube.com/watch?v=4HBdhL1n_XU | L149: 280000 | M149: 【スカッと総集編】新築4LDKを購入した途端、夫「明日から長男夫婦と同居する！」長男嫁「逆らったら介護しませんよw」私「は？私は独身ですけど？」夫・長男夫婦「は？」結果w
A150: 149 | D150: 潮汕鱼小庄 | E150: https://www.youtube.com/channel/UC8raI5CKlVfy9JxZhQb2gGA | F150: https://www.youtube.com/watch?v=paLwWEepddQ | G150: 1 | H150: 2 | I150: 2 日前 | J150: 42 | K150: https://www.youtube.com/watch?v=Y2GawdK7Q9E | L150: 100000 | M150: 【スカッとする話】長男夫婦に初孫が生まれ出産祝いに行くと長男嫁「二人は汚いので床でいいですか？w」長男「ジジババは段ボールの上でw」夫「...帰るか」私「うん」速帰宅し→永久に無視した結果w
A151: 150 | D151: 略奪女を成敗する | E151: https://www.youtube.com/channel/UCJp73l8_hVv3B87urdWKPQA | F151: https://www.youtube.com/watch?v=5HXJqNSX7Ds | G151: 1 | H151: 2 | I151: 1 か月前 | J151: 2 | K151: https://www.youtube.com/watch?v=JaGjTAkTfxQ | L151: 300000 | M151: 【スカッとする話】私が夫の入院費を払ってると知らず私の荷物を全て捨てた夫の連れ子「もうパパに寄生するなw」連れ子を残し1億のタワマンに引越し入院費の支払いも止めた結果w
A152: 151 | D152: 秘密と嘘の家 5436 | E152: https://www.youtube.com/channel/UCFu4mcOSv2LuCDSSbnFcMXw | F152: https://www.youtube.com/watch?v=QrVr4xYpFIs | G152: 1 | H152: 3 | I152: 4 週間前 | J152: 1 | K152: https://www.youtube.com/watch?v=nmxjuOeyqQ8 | L152: 23000 | M152: 【スカッとする話】娘の寝室に入り5時間出てこない義父。不審に思った私と夫が静かに扉を開けた瞬間、私たちは顔面蒼白に…【朗読】【スカッと】
A153: 152 | D153: 秘密の重さ 5647 | E153: https://www.youtube.com/channel/UCRxTgybyclgid9aIBdIXUVA | F153: https://www.youtube.com/watch?v=fgGZTp2-9So | G153: 1 | H153: 2 | I153: 2 週間前 | J153: 2 | K153: https://www.youtube.com/watch?v=da0XdCuaRR4 | L153: 130000 | M153: 【スカッとする話】私がフルタイムで働き家計を支えていると知らず夫と引っ越した義両親「同居するなら月給80万の息子の新居教えるわw」私「では手取り8万の旦那とは離婚で」義両親「嘘つくなw」結果w
A154: 153 | D154: 結婚後の生活 | E154: https://www.youtube.com/channel/UC9Nq5Tyz6qzWqrXjucfmm_A | F154: https://www.youtube.com/watch?v=F8fUGxI65ic | G154: 5 | H154: 7 | I154: 4 か月前 | J154: 22 | K154: https://www.youtube.com/watch?v=NTuf2k99EWQ | L154: 270000 | M154: 【スカッとする話】体調不良でパートを早退し家に帰ると夫が親友と真っ最中...コッソリ二人の動画を撮影し親友の夫に送ってやった結果w
A155: 154 | D155: 美しい木 | E155: https://www.youtube.com/channel/UCKDhvWl0boDNeo65NQzjbOg | F155: https://www.youtube.com/watch?v=xAHW3dG1V5M | G155: 1 | H155: 2 | I155: 3 か月前 | J155: 0 | K155: https://www.youtube.com/watch?v=3WJaWicyrhk | L155: 25000 | M155: 【スカッとする話】長男夫婦の結婚式の帰宅中、突然激怒する夫「犯罪者のクズとは離婚！毎月の仕送り5万盗んでただろ！」 私「承知しました...」 即離婚して仕送り辞めた結果w【スカッと】
A156: 155 | D156: 近藤 智 | E156: https://www.youtube.com/channel/UCGrrWOm-FX7EsUB4uGVtxCA | F156: https://www.youtube.com/watch?v=FGbjMRQItrA | G156: 2 | H156: 3 | I156: 1 か月前 | J156: 178 | K156: https://www.youtube.com/watch?v=iT0GjRHrB6w | L156: 260000 | M156: 【スカッとする話】年末年始の親族の集まりで20人分のおせちをゴミ箱にぶちまけたエリート夫「親戚にマズイ飯を作るな！」私「私は何も作ってないよ？」夫「え？」実は...
A157: 156 | D157: 逆転ストーリー 5008 | E157: https://www.youtube.com/channel/UCriVTHI8ZSlCtGVvqIqnMSw | F157: https://www.youtube.com/watch?v=oOG4kNeC0o8 | G157: 1 | H157: 2 | I157: 1 か月前 | J157: 117 | K157: https://www.youtube.com/watch?v=sd51TvGQSo0 | L157: 49000 | M157: 【スカッとする話】夫と作業着で株主総会へ行くと総務部長「小汚い貧乏人は帰れw」夫「俺、大株主なんだけど…」部長「じゃあ全株売ってみろよw」私「もしもし？全株（999億）売却で」結果w【朗読】
A158: 157 | D158: 都会の孤独5052 | E158: https://www.youtube.com/channel/UCTWwkNBKuUw8iJZaqGYyivA | F158: https://www.youtube.com/watch?v=GFc6HQj6EGQ | G158: 1 | H158: 2 | I158: 1 か月前 | J158: 0 | K158: https://www.youtube.com/watch?v=Yfo6v4-ZtHc | L158: 220000 | M158: 【スカッとする話】私が義父の入院費を払ってると知らず私の荷物を全て捨てた夫「もう俺に寄生するな穀潰しがw」夫を残し1億の豪邸に引越し入院費の支払いも止めた結果w
A159: 158 | D159: 陽咲 | E159: https://www.youtube.com/channel/UCkWQ3TuNHjERVg8BInHuS-Q | F159: https://www.youtube.com/watch?v=6RRRd0Fql0c | G159: 1 | H159: 2 | I159: 2 か月前 | J159: 0 | K159: https://www.youtube.com/watch?v=Rw2iIdnpgQY | L159: 39000 | M159: 【スカッとする話】私を低収入扱いする長男夫婦。長男嫁「低収入の義母は出てけw」長男「俺もこんな母親いらないw」お望み通り口座を0円にして、1年間家を出た結果w
A160: 159 | D160: 隠された才能 5633 | E160: https://www.youtube.com/channel/UCxSupAhazSWDXBtwag7MUbA | F160: https://www.youtube.com/watch?v=cnKO3QZMVLk | G160: 1 | H160: 2 | I160: 3 週間前 | J160: 113 | K160: https://www.youtube.com/watch?v=L6kEKzkIxIU | L160: 43000 | M160: 【スカッとする話】同窓会でいじめられた私。同級生「乞食は残飯食ってろw」1時間後、息子が現れた途端、同級生の態度が急変し…w【朗読】【スカッと】
A161: 160 | D161: 雨の中の記憶、静かな終わり | F161: https://www.youtube.com/watch?v=WJocrLwyLiM | G161: 1 | H161: 2 | I161: 4 週間前 | J161: 2 | K161: https://www.youtube.com/watch?v=cOi4yMZgKgk | L161: 37000 | M161: 【スカッとする話】70歳記念の夫婦旅行に財布を持たず便乗する長男夫婦。長男嫁「今日もごちになりますw」長男「今回は嫁の両親も呼んだよw」私「別にいいわよ。今日で最後だし」長男嫁「え？」
A162: 161 | D162: 静かな夜の物語、お話の部屋 | F162: https://www.youtube.com/watch?v=Tfysps_BXAs | G162: 1 | H162: 2 | I162: 4 週間前 | J162: 6 | K162: https://www.youtube.com/watch?v=2HkpvXHVMuM | L162: 86000 | M162: 【スカッとする話】息子夫婦の家へ行くと8歳の孫が地下室で鎖に繋がれ寝ていた...私「一体どうしたの？」孫「いつもの事だけど？」私「は？」キレた私は家を売却し更地にし...
A163: 162 | D163: 静かな夜の物語、静かな終わり | F163: https://www.youtube.com/watch?v=TNvNxxjv3I8 | G163: 1 | H163: 2 | I163: 1 か月前 | J163: 0 | K163: https://www.youtube.com/watch?v=QYxlZ4M3Tcs | L163: 81000 | M163: 【スカッとする話】注文した料理に一切手をつけない夫。私「食べないの？」夫「...」会計時、店員の手の動きを見た瞬間、私はガクガク震えだし...
A164: 163 | D164: 静かな話 5629 | E164: https://www.youtube.com/channel/UC0d7olDuujDBFI3bhVL4fPg | F164: https://www.youtube.com/watch?v=h9V7FM7lV-U | G164: 1 | H164: 2 | I164: 3 週間前 | J164: 54 | K164: https://www.youtube.com/watch?v=3Zu1EEzUQkY | L164: 31000 | M164: 【スカッとする話】雪山に生き埋めにされ天才孤児に救われた財閥会長の私。救急車で運ばれ病院で子供と再会。孤児「ここは危ないから逃げて！」衝撃の真実を知り私は顔面蒼白に…【朗読】【スカッと】
A165: 164 | D165: 高山美津世【感動★総集編】 | E165: https://www.youtube.com/channel/UC5H2HIMfOu-JA_xGcjAf5xA | F165: https://www.youtube.com/watch?v=LaQSOyXPwTY | G165: 1 | H165: 2 | I165: 3 年前 | J165: 21728 | K165: https://www.youtube.com/watch?v=i8zqcOBxHyo | L165: 37000 | M165: 【スカッとする話】長男の海外主張中、癌で余命半年の私を奴隷扱いする長男嫁「家事も役立たずは出てけ！」私「はい...」泣きながら出て行くと長男とある人物がやってきて…【修羅場】【スカッと】

Sheet ラウンド1
A1: No. | B1: 申請日 | C1: 削除確認 | D1: 順位 | E1: チャンネル名 | F1: チャンネルURL | G1: 転載動画URL | H1: 一致率 | I1: 転載の投稿 | J1: 転載の再生数 | K1: 元動画URL | L1: 元動画の再生数 | M1: 元タイトル | N1: メモ
A2: 1 | D2: 1 | E2: 藤田 七海 | F2: https://www.youtube.com/channel/UCe0KTxGVR84qUjkAHQb-wGg | G2: https://www.youtube.com/watch?v=H3NTQ4PrQQY | H2: 1 | I2: 2 週間前 | J2: 54 | K2: https://www.youtube.com/watch?v=dOy6I1JE_yY | L2: 30000 | M2: 【スカッとする話】私の退職金をやたら気にする夫「いくら貰ったの？」私「口座に2000万入った！」翌日、カードを手に夫が失踪。私（計画通りw）実は【朗読】【スカッと】
A3: 2 | D3: 2 | E3: スカッと物語 | F3: https://www.youtube.com/channel/UCLz5UoQMIAja9LyZIOCYmQg | G3: https://www.youtube.com/watch?v=od3pGdQwxPk | H3: 1 | I3: 8 日前 | J3: 0 | K3: https://www.youtube.com/watch?v=IsPanDg1vH0 | L3: 28000 | M3: 【スカッとする話】娘の葬儀に愛人を連れてきた婿「最期に間に合わなくて残念w」愛人「遺産2億は私達が相続ねw」私「…ですってw」夫「助かるなw」愛人「え？」実はw【朗読ドラマ】【朗読】【スカッと】
A4: 3 | D4: 3 | E4: 出る杭は打たれる | F4: https://www.youtube.com/channel/UCAmIDIbiOxKA9YSVK0aYSZQ | G4: https://www.youtube.com/watch?v=eO55IR5xYH8 | H4: 1 | I4: 2 か月前 | J4: 0 | K4: https://www.youtube.com/watch?v=OJkzN_P6Tys | L4: 43000 | M4: 【スカッとする話】義母の私にだけ引越し先を教えない長男嫁「他人に住所は教えませんw今後一切関わらないでくださいw」1ヶ月後、長男嫁が病気で緊急手術→他人なので執刀医を辞退した結果w
A5: 4 | D5: 4 | E5: 良い話 | F5: https://www.youtube.com/channel/UCSrk1OzKlw4sCvRbksLDgcQ | G5: https://www.youtube.com/watch?v=BgwIu7GjpsA | H5: 1 | I5: 5 日前 | J5: 0 | K5: https://www.youtube.com/watch?v=p9EJ4XSEiOU | L5: 33000 | M5: 【スカッとする話】夫を略奪した美人同級生から結婚式の招待状が届くと、祖父「バァさんと2人で行く」祖母「地獄を見せてくるわ」普段温厚な祖父母がこの後...w【スカッと】【朗読】【修羅場】
A6: 5 | D6: 5 | E6: 家庭の真実 5497 | F6: https://www.youtube.com/channel/UCqzVZHS7_AHD3WczZdnOkwg | G6: https://www.youtube.com/watch?v=DBMjSadqY8E | H6: 1 | I6: 3 週間前 | J6: 30 | K6: https://www.youtube.com/watch?v=lRIrN83xkSc | L6: 62000 | M6: 【スカッとする話】私の車のアクセルにこっそり手を加える夫。私（知らないふりしよw）翌日、車を義両親に貸し出すと、夫「ま、待ってくれ…」実はw【朗読】【スカッと】
A7: 6 | D7: 6 | E7: スカッとストーリー 5006 | F7: https://www.youtube.com/channel/UC1x3I0LM2SzXkpn57uaFuQA | G7: https://www.youtube.com/watch?v=7UfS_a8A8SY | H7: 1 | I7: 1 か月前 | J7: 66 | K7: https://www.youtube.com/watch?v=YYnTTQ_3WI8 | L7: 59000 | M7: 【スカッとする話】妹の代わりに田舎の猟師に嫁いだ私「今日の夕飯は鹿肉？」夫「いや、これで好きな物食べて」10万円を手渡された私…→夫の正体を知った妹が半狂乱にw【朗読】【スカッと】
A8: 7 | D8: 7 | E8: 嫁ゴコロ逆転朗読館 | F8: https://www.youtube.com/channel/UCQDSjWHn0tvkuVZav4jZnXQ | G8: https://www.youtube.com/watch?v=sn9gV9SEkus | H8: 1 | I8: 6 日前 | J8: 0 | K8: https://www.youtube.com/watch?v=00HSG0Knh3I | L8: 17000 | M8: 【スカッとする話】70歳を過ぎ夫と別居中の私。40年もの間、夫は冷酷だった。ある日、夫の手帳を開いた瞬間、全てを理解し涙が溢れ…【朗読】【スカッと】
A9: 8 | D9: 8 | E9: 読書室【スカッとする話】 | F9: https://www.youtube.com/channel/UCjQd7ZVm5BPbGpB_V9B6kgQ | G9: https://www.youtube.com/watch?v=ykrbCE8A45A | H9: 1 | I9: 1 年前 | J9: 2 | K9: https://www.youtube.com/watch?v=RNWUvpjXeTw | L9: 22000 | M9: 【スカッと】私の子供が夫の上司と瓜二つ。夫「浮気してたな！離婚だ！」義母「アバズレは今すぐ出てけw」13年後、夫と義母と再会すると二人は半狂乱。だって娘は…
A10: 9 | D10: 9 | E10: 憂鬱よりスカッと | F10: https://www.youtube.com/channel/UC8bvniIkSPPf_5ELr1VNZCQ | G10: https://www.youtube.com/watch?v=EbCFdI1mcDA | H10: 1 | I10: 2 年前 | J10: 100 | K10: https://www.youtube.com/watch?v=VyoXxeYV0Ag | L10: 37000 | M10: 【スカッとする話】家事、育児、仕事をこなし夫と30年間連れ添った私に夫が突然の土下座「愛人が妊娠したから再婚する。離婚してくれ」私「はーい、ではさようなら」1週間後、半狂乱の夫から39件の鬼電がw
A11: 10 | D11: 10 | E11: とする話 | F11: https://www.youtube.com/channel/UC-1KoQRWd1ijwgKpAmRTQ7A | G11: https://www.youtube.com/watch?v=E9MMt25o2Es | H11: 1 | I11: 1 年前 | J11: 73 | K11: https://www.youtube.com/watch?v=w3t-NBVK2CU | L11: 31000 | M11: 【スカッとする話】結婚式当日に夫から突然の電話。夫「みんな集まってるぞ！早く来い！」私「え？なに言ってるの？」たった今終わったと伝えると…
A12: 11 | D12: 11 | E12: Dima Tomashevich | F12: https://www.youtube.com/channel/UCkfiH3lPVPodePE4eNSDpWg | G12: https://www.youtube.com/watch?v=SRmU4BFmMfU | H12: 1 | I12: 2 年前 | J12: 0 | K12: https://www.youtube.com/watch?v=xGHuS24cdnQ | L12: 16000 | M12: 【スカッとする話】夫が亡くなり葬式後、更に最愛の長男と孫まで亡くした私に長男嫁「遺産は私が貰うからババァも逝けw」と深夜に家を追い出された。公園で号泣してると、懐かしい声が聞こえ振り返ると...
A13: 12 | D13: 12 | E13: さあ、どうぞ | F13: https://www.youtube.com/channel/UCG-XF2tttCtNESz__p6GQ7w | G13: https://www.youtube.com/watch?v=EoPGSTdsArk | H13: 1 | I13: 2 か月前 | J13: 1 | K13: https://www.youtube.com/watch?v=jtzUWcGh5y8 | L13: 11000 | M13: 【スカッとする話】私の夫を奪ったママ友「医者の旦那さん奪っちゃったｗ赤ちゃんできたし豪華挙式するねｗ」私「結婚したことないですけど？」ママ友「え？」結果ｗ
... A18: 17 | D18: 17 | E18: 義家族スカッと物語帳 | F18: https://www.youtube.com/channel/UCIZ41RBpQd7wBp_oOTGv1zw | G18: https://www.youtube.com/watch?v=CLwUPWOMYZM | H18: 1 | I18: 6 日前 | J18: 0 | K18: https://www.youtube.com/watch?v=KVKExhX2jn4 | L18: 33000 | M18: 【スカッとする話】財布を届けにきた私に気づかない夫「嫁は何も疑ってないよw今夜もまた会えるねw」夫の正体を知り私の愛は消滅しw【朗読】【スカッと】
A19: 18 | D19: 18 | E19: 静かな夜の物語、雨の中の記憶 | G19: https://www.youtube.com/watch?v=hKi2-HjQLs0 | H19: 1 | I19: 2 週間前 | J19: 0 | K19: https://www.youtube.com/watch?v=Yrtj6pTpQ5A | L19: 100000 | M19: 【スカッと総集編】家事、育児、介護、パートをこなし15年。私「もう限界。実家に帰ります」夫「はぁ？ガキの面倒は？飯は？帰るなら離婚届書いてけ！」→速提出して両親に離婚報告すると涙を流した夫が家に来て…
A20: 19 | D20: 19 | E20: Noah Qumi | F20: https://www.youtube.com/channel/UCH4l3-r5NgR2RlKdoRwfzAw | G20: https://www.youtube.com/watch?v=MHsVbMKecBY | H20: 1 | I20: 7 日前 | J20: 0 | K20: https://www.youtube.com/watch?v=blo_a56_T1U | L20: 370000 | M20: 【スカッとする話】愛人に夫を奪われた私。2人「すまん、離婚してくれ…」離婚届が置かれた瞬間、即サインし夫を譲ると、相手弁護士がガタガタ震え出しw【朗読】【スカッと】
A21: 20 | D21: 20 | E21: Shinji Datの人生物語 | F21: https://www.youtube.com/channel/UCpdX_bFCePsYvPWZAMQoaeg | G21: https://www.youtube.com/watch?v=FiGEQo_QLoY | H21: 1 | I21: 2 か月前 | J21: 11 | K21: https://www.youtube.com/watch?v=gqjIGgB7rlA | L21: 40000 | M21: 【スカッとする話】夫「俺の年金は1円もやらん」40年間夫を支えてきたのに、他人のように突き放された私（もう我慢しなくていっかw）→翌日、なぜか夫が泣き叫びw【朗読】【スカッと】
A22: 21 | D22: 21 | E22: スカッとする話 5020 | F22: https://www.youtube.com/channel/UCAG5eZR0aJpGuShtjtimSEg | G22: https://www.youtube.com/watch?v=-FQjdMNh2gM | H22: 1 | I22: 4 週間前 | J22: 43 | K22: https://www.youtube.com/watch?v=gVrVwssbXow | L22: 28000 | M22: 【感動する話】親に捨てられた中1の私に弁当屋の夫婦「これお食べ」空腹の私を助けてくれた老夫婦。20年後、社長になった私が再訪問→張り紙の一文で泣き崩れ…【朗読】
A23: 22 | D23: 22 | E23: 人生の光と影 | F23: https://www.youtube.com/channel/UCYX4tsWpykTmtfNq_i36C_w | G23: https://www.youtube.com/watch?v=8AmSKMrlaRQ | H23: 1 | I23: 8 日前 | J23: 161 | K23: https://www.youtube.com/watch?v=ZTng_6NCKl8 | L23: 60000 | M23: 【スカッとする話】親代わりに育てた弟の結婚式でタキシードを着た弟が1人ポツン。弟「結婚は嘘でドッキリって…」直後、普段温厚な夫が新婦一族に電話。夫「出資1億はキャンセルで」新婦一族「え？」【朗読】
A24: 23 | D24: 23 | E24: 美しい木 | F24: https://www.youtube.com/channel/UCKDhvWl0boDNeo65NQzjbOg | G24: https://www.youtube.com/watch?v=xAHW3dG1V5M | H24: 1 | I24: 3 か月前 | J24: 0 | K24: https://www.youtube.com/watch?v=3WJaWicyrhk | L24: 25000 | M24: 【スカッとする話】長男夫婦の結婚式の帰宅中、突然激怒する夫「犯罪者のクズとは離婚！毎月の仕送り5万盗んでただろ！」 私「承知しました...」 即離婚して仕送り辞めた結果w【スカッと】
A25: 24 | D25: 24 | E25: TINA SHTIBKO | F25: https://www.youtube.com/channel/UCIQbb4FNm2BhP5GfSTbrQ4w | G25: https://www.youtube.com/watch?v=LFh5HyZqSaY | H25: 1 | I25: 2 年前 | J25: 0 | K25: https://www.youtube.com/watch?v=4XaTm2Lo-tc | L25: 51000 | M25: 【スカッとする話】長男が結婚し実家で同居すると、長男嫁「狭いので出てって下さいw」我が家を追い出され1ヶ月後、私の新居を見にきた長男嫁「こ、この家って」
A26: 25 | D26: 25 | E26: フィクション 5634 | F26: https://www.youtube.com/channel/UCtx1aitp-eTJhv2c94bnBZQ | G26: https://www.youtube.com/watch?v=1dPUOOQoIgw | H26: 1 | I26: 3 週間前 | J26: 211 | K26: https://www.youtube.com/watch?v=K7QGPSQED7o | L26: 30000 | M26: 【感動する話】離婚前夜、夫との最後の晩餐。料亭で夫を待ち続けたが、メールの返信もなく現れない。その時、突然私に声をかけた店主「実は、ご主人が…」【朗読】
A27: 26 | D27: 26 | E27: 泥だらけの絆 5655 | F27: https://www.youtube.com/channel/UCdyvc7k9wPzVO9X62aCvguQ | G27: https://www.youtube.com/watch?v=AXXpmLXnPFo | H27: 1 | I27: 13 日前 | J27: 1 | K27: https://www.youtube.com/watch?v=qNSSnNaMxrs | L27: 80000 | M27: 【スカッとする話】私1人で育てた息子の顔合わせで、なぜか私たちだけお茶漬け…義家族「貧乏人は好きだろ？w」直後、私の存在に気づいた義兄「俺たちの人生終了だ…」【朗読】【スカッと】
A28: 27 | D28: 27 | E28: Bonnie Denver | F28: https://www.youtube.com/channel/UCsdndA886timZqWK6_b0d0Q | G28: https://www.youtube.com/watch?v=gw_bZgF_vcw | H28: 1 | I28: 1 年前 | J28: 4 | K28: https://www.youtube.com/watch?v=tOHZbuZysA4 | L28: 74000 | M28: 【スカッとする話】医者一族の婚約者と結婚挨拶に行くと私達の席だけない。義母「片親の貧乏人とは婚約破棄w」母「ではおたくの病院潰すわ」義家族「え？」
A29: 28 | D29: 28 | E29: 心温まるストーリー 4989 | F29: https://www.youtube.com/channel/UCS-VuYFB_DXsDhPHAzUS0JA | G29: https://www.youtube.com/watch?v=qJ8No7XGqYQ | H29: 1 | I29: 1 か月前 | J29: 98 | K29: https://www.youtube.com/watch?v=qNSSnNaMxrs | L29: 80000 | M29: 【スカッとする話】私1人で育てた息子の顔合わせで、なぜか私たちだけお茶漬け…義家族「貧乏人は好きだろ？w」直後、私の存在に気づいた義兄「俺たちの人生終了だ…」【朗読】【スカッと】
A30: 29 | D30: 29 | E30: Jamison Abraham | F30: https://www.youtube.com/channel/UCcUsK23eqHw3ZQA5HjspM9Q | G30: https://www.youtube.com/watch?v=Nududo1BLfA | H30: 1 | I30: 1 年前 | J30: 0 | K30: https://www.youtube.com/watch?v=Mi69PEXjWFc | L30: 35000 | M30: 【スカッと】365日間、私を無視し続けた年収1000万の夫「誰のおかげで生きてると思ってる！文句あるなら離婚して出てけw」私「後悔しない？」夫「しねぇよw」3日後、夫は会社をクビにw
A31: 30 | D31: 30 | E31: サヨナラの選択4848 | F31: https://www.youtube.com/channel/UCiDg2Vs1LHy6qIiV6ilje1A | G31: https://www.youtube.com/watch?v=ks7lwFCnjLM | H31: 1 | I31: 3 週間前 | J31: 0 | K31: https://www.youtube.com/watch?v=Y4k29xHFHUY | L31: 33000 | M31: 【スカッとする話】デパートでバイトする私に会長夫人「私を誰だと思ってるの？ここの会長の夫人様よ！」私「で？」夫人「もういいお前クビ！」直後、会長夫人は全てを失い…w【朗読】【スカッと】
... A38: 37 | D38: 37 | E38: 痛快!!怒りのスカッとチャンネル【スカッと朗読】 | F38: https://www.youtube.com/channel/UC96mO8pXAaiP70V7KUjVHqg | G38: https://www.youtube.com/watch?v=4_x4CtcujZ0 | H38: 1 | I38: 1 年前 | J38: 39 | K38: https://www.youtube.com/watch?v=bI91wh-7IMg | L38: 190000 | M38: 【スカッとする話】孫の七五三のお祝いに親戚一同と行くと私だけ席がない...長男嫁「他人の席は無いから立ってればw」私「じゃ帰るか」親戚一同「うん」全員で帰宅した結果w
A39: 38 | D39: 38 | E39: 雨の中の記憶、雨の中の記憶 | G39: https://www.youtube.com/watch?v=D7M2p9ALM9c | H39: 1 | I39: 3 週間前 | J39: 19 | K39: https://www.youtube.com/watch?v=KKEWop4fNrk | L39: 66000 | M39: 【スカッと総集編】私が総資産が28億の社長令嬢と知らず私を裏切り職場の美人同僚と再婚した夫「美人同僚と再婚するから離婚w」同僚「子供は1人で頑張れｗ」私「はーい」1ヶ月後、夫達から鬼電がw
A40: 39 | D40: 39 | E40: スカっとゼミ!! | F40: https://www.youtube.com/channel/UC9Hd679L2faWD0aJQHeAlrA | G40: https://www.youtube.com/watch?v=tc-9FGKPWTs | H40: 0.96 | I40: 1 年前 | J40: 7509 | K40: https://www.youtube.com/watch?v=VrctjOjY0Ts | L40: 88000 | M40: 【スカッとする話】単身赴任中の私に夫から速達で離婚届…夫「息子も離婚して欲しいってw」私（やっと自由になれるw）大喜びして離婚届を提出し家を売り払い更地にするとw
A41: 40 | D41: 40 | E41: スカッと成敗ストーリー | F41: https://www.youtube.com/channel/UC1iIGo491nSYyJ_AsgmPzyw | G41: https://www.youtube.com/watch?v=cmr_Wm_l0r0 | H41: 1 | I41: 2 か月前 | J41: 0 | K41: https://www.youtube.com/watch?v=NskvXTGiyMY | L41: 34000 | M41: 【スカッとする話】私がグループ13社の社長と知らず、母の葬儀後に銀行員の夫「相続少ねぇなw離婚でw」即離婚届を提出し夫の銀行へ→私「700億の法人口座は解約で」
A42: 41 | D42: 41 | E42: 時を越える話 | F42: https://www.youtube.com/channel/UC_n9gc1na-2QpFv6TPInL3w | G42: https://www.youtube.com/watch?v=ISJkWfnE524 | H42: 1 | I42: 3 週間前 | J42: 3159 | K42: https://www.youtube.com/watch?v=ZobJWKrmIzQ | L42: 77000 | M42: 【スカッとする話】娘の結婚式に愛人と共に現れた夫「彼女にも座らせてあげて」私は黙って愛人に席を譲った直後、グループ10社を束ねる新郎父「会長、お久しぶりです」【朗読】【スカッと】
A43: 42 | D43: 42 | E43: 涙の向こう側 | F43: https://www.youtube.com/channel/UCOXAYjsxUMpublA1yS1ATIA | G43: https://www.youtube.com/watch?v=SwLud5WJ-9Q | H43: 1 | I43: 8 日前 | J43: 673 | K43: https://www.youtube.com/watch?v=7b4pVxD6-XQ | L43: 18000 | M43: 【スカッとする話】私「もう限界…出ていきます」夫「家事と介護は嫁の仕事！責任果たせないなら離婚！」お望み通り離婚届を置いて姿を消すと→半狂乱の夫から鬼電がw【朗読】【スカッと】
A44: 43 | D44: 43 | E44: 老いの詩 | F44: https://www.youtube.com/channel/UClKj-HO63gh7qxtT7M0czEQ | G44: https://www.youtube.com/watch?v=pQKMo5JuRYs | H44: 1 | I44: 1 か月前 | J44: 5 | K44: https://www.youtube.com/watch?v=YYnTTQ_3WI8 | L44: 59000 | M44: 【スカッとする話】妹の代わりに田舎の猟師に嫁いだ私「今日の夕飯は鹿肉？」夫「いや、これで好きな物食べて」10万円を手渡された私…→夫の正体を知った妹が半狂乱にw【朗読】【スカッと】
A45: 44 | D45: 44 | E45: Ivan Ilencow | F45: https://www.youtube.com/channel/UC6IzQHpKzqIt1DgjPouEefQ | G45: https://www.youtube.com/watch?v=9GauLOUX3QM | H45: 1 | I45: 2 年前 | J45: 2 | K45: https://www.youtube.com/watch?v=CTeggEwk2Nc | L45: 28000 | M45: 【スカッとする話】妊婦の私が倒れて入院するとワインをぶっかけ海外旅行に行く夫「帰るまでに産んでおけよ！」無視した私に夫がワインを投げるも当たって失神したのは...【修羅場】【スカッと】
A46: 45 | D46: 45 | E46: Legacy Apollo | F46: https://www.youtube.com/channel/UC2YwIXq-utTkNLQgcRVloyQ | G46: https://www.youtube.com/watch?v=c0b7OwI4zCw | H46: 1 | I46: 2 年前 | J46: 175 | K46: https://www.youtube.com/watch?v=-WjRVa4jNLk | L46: 59000 | M46: 【スカッとする話】73歳の誕生日に長男夫婦がくれた10万円の時計をゴミ箱に捨てた私に夫「長男と長男嫁さんに土下座して謝れ！」私「これ見ても同じこと言える？」夫「え？」実は…【修羅場】
A47: 46 | D47: 46 | E47: Pendelton Gideon | F47: https://www.youtube.com/channel/UCIRVjzjmTHwXA3X81dpyNeQ | G47: https://www.youtube.com/watch?v=yAg-ur38iSY | H47: 1 | I47: 1 年前 | J47: 2 | K47: https://www.youtube.com/watch?v=tOHZbuZysA4 | L47: 74000 | M47: 【スカッとする話】医者一族の婚約者と結婚挨拶に行くと私達の席だけない。義母「片親の貧乏人とは婚約破棄w」母「ではおたくの病院潰すわ」義家族「え？」
A48: 47 | D48: 47 | E48: Павел **** | F48: https://www.youtube.com/channel/UCSPg9ALk7YwnsqACClpErGg | G48: https://www.youtube.com/watch?v=iKlAkSZVtcE | H48: 1 | I48: 2 年前 | J48: 0 | K48: https://www.youtube.com/watch?v=EIrAyCZzwiI | L48: 34000 | M48: 【スカッとする話】40度の高熱の私から財布とクレカを奪った長男嫁「はい、氷水w帰るまでに治して下さいねｗ」バケツで氷水をかけられ気絶した…3日後、私はご機嫌に帰宅した長男嫁に...
A49: 48 | D49: 48 | E49: 人生スカッと朗読館 | F49: https://www.youtube.com/channel/UChTkZ7g3oCCQG3XSqe69LWQ | G49: https://www.youtube.com/watch?v=qsjIpApuEeQ | H49: 1 | I49: 5 日前 | J49: 0 | K49: https://www.youtube.com/watch?v=hi2PAohyTkU | L49: 20000 | M49: 【スカッとする話】夫の出張中、オウムを任された私。何気なくオウムに話しかけると、オウム「嫁にはバレてないよ」不審に思い夫の部屋を開けた。→直後、私は顔面蒼白に…【朗読ドラマ】【朗読】【スカッと】
A50: 49 | D50: 49 | E50: 夜の語り部5056 | F50: https://www.youtube.com/channel/UCEvaB4r-6y7tj3UAoMEdqXA | G50: https://www.youtube.com/watch?v=bQ7ZCEsAHqU | H50: 1 | I50: 1 か月前 | J50: 1 | K50: https://www.youtube.com/watch?v=t9x4VmiCRI4 | L50: 43000 | M50: 【スカッとする話】親代わりで育てた妹の結婚式で、着物姿の妹が式場に1人ポツン…義家族「嘘に決まってるじゃんw」私「なら契約も嘘か！了解」義家族「え？」実はw【朗読】【スカッと】
A51: 50 | D51: 50 | E51: 妻の復讐 5649 | F51: https://www.youtube.com/channel/UC_-FBuCpoEW8RPG4j-oCbkg | G51: https://www.youtube.com/watch?v=RsEXpU8hnpQ | H51: 1 | I51: 2 週間前 | J51: 1 | K51: https://www.youtube.com/watch?v=wxIjPqUT7oA | L51: 100000 | M51: 【スカッとする話】パートから帰ると突然私を殴ってきた義母「息子の金盗んだな！金返せ！」夫と義母に泥棒扱いされた私「じゃあ警察呼びますね」→即通報すると2人が半狂乱にw【朗読】【スカッと】【シニア】
... A88: 87 | D88: 87 | E88: 逆転ストーリー 5008 | F88: https://www.youtube.com/channel/UCriVTHI8ZSlCtGVvqIqnMSw | G88: https://www.youtube.com/watch?v=5h3oP6uheYc | H88: 1 | I88: 4 週間前 | J88: 11048 | K88: https://www.youtube.com/watch?v=sTmob2uIaqg | L88: 72000 | M88: 【スカッとする話】結婚挨拶から帰宅した息子「片親の貧乏人とは白紙って…」息子の頬にはビンタの痕が…キレた私は義家族に即電話→義家族全員が号泣の展開にw【朗読】【スカッと】
A89: 88 | D89: 88 | E89: 雨の中の記憶、静かな心の記録 | G89: https://www.youtube.com/watch?v=WfmGCr48Es4 | H89: 1 | I89: 10 日前 | J89: 0 | K89: https://www.youtube.com/watch?v=29F5nZ8UXYQ | L89: 96000 | M89: 【スカッと総集編】私が家族全員を養ってたと知らず新築に引越す義母「アンタの全てが気に入らないw家族だけで暮らすから消えろw」 即離婚して全名義を夫に変更→半狂乱の義母から鬼電がw
A90: 89 | D90: 89 | E90: 雨の中の記憶、静かな終わり | G90: https://www.youtube.com/watch?v=fz0_OTDIvpQ | H90: 0.99 | I90: 1 か月前 | J90: 6 | K90: https://www.youtube.com/watch?v=Bz-9j9l6enc | L90: 16000 | M90: 【スカッとする話】新婚旅行中に私を雪山に置き去りにした夫「俺に意見するバカは帰ってくるなw反省するまでそこにいろw」私「さむい…置いてかないで…」翌日、夫がありえない姿で発見され…
A91: 90 | D91: 90 | E91: 静かな夜の物語、お話の部屋 | G91: https://www.youtube.com/watch?v=ndorpzHpT74 | H91: 1 | I91: 4 週間前 | J91: 0 | K91: https://www.youtube.com/watch?v=LBUgCfVXgYM | L91: 98000 | M91: 【スカッと】妊娠10ヶ月の私を地下室に閉じこめ夫とハワイ旅行に行った義両親「クズ嫁はそこで反省してなw」1週間後、帰宅した義母が腐敗臭に気づき慌てて地下室の扉を開けると...
A92: 91 | D92: 91 | E92: Avalynn Roderick | F92: https://www.youtube.com/channel/UC2ALeyYaaWwXZhLpaAxCjDA | G92: https://www.youtube.com/watch?v=Rzltaxpy2-U | H92: 1 | I92: 2 年前 | J92: 2 | K92: https://www.youtube.com/watch?v=14YEbx6YYwk | L92: 42000 | M92: 【スカッとする話】家事に疲れて休憩していると妊娠9ヶ月の私を蹴ってきた夫「妊婦だからは甘え！家事サボるな！」無視した私に夫がビール瓶を投げるも当たって血まみれになったのは...
A93: 92 | D93: 92 | E93: Chi Tông | F93: https://www.youtube.com/channel/UCQZmlpJ03rsGpabdpOyYt5g | G93: https://www.youtube.com/watch?v=YyHW5siTvnw | H93: 1 | I93: 1 年前 | J93: 2 | K93: https://www.youtube.com/watch?v=U2N_1lBpoWY | L93: 56000 | M93: 【スカッとする話】自ら命を絶った夫の葬儀後、墓参りに行くと１通の手紙が…手紙「俺の代わりに母さんに復讐を…」手紙の中身を読み進めると→私はガクガク震え始め…
A94: 93 | D94: 93 | E94: Malani Darren | F94: https://www.youtube.com/channel/UCGjfIdDymNvLcybwzheXAnQ | G94: https://www.youtube.com/watch?v=nk--vBe6ElI | H94: 1 | I94: 1 年前 | J94: 0 | K94: https://www.youtube.com/watch?v=xGHuS24cdnQ | L94: 16000 | M94: 【スカッとする話】夫が亡くなり葬式後、更に最愛の長男と孫まで亡くした私に長男嫁「遺産は私が貰うからババァも逝けw」と深夜に家を追い出された。公園で号泣してると、懐かしい声が聞こえ振り返ると...
A95: 94 | D95: 94 | E95: Thuong Le | F95: https://www.youtube.com/channel/UCxXjwf3LJAKSZP_9Thu5meA | G95: https://www.youtube.com/watch?v=Lnu9yYMStWM | H95: 1 | I95: 1 年前 | J95: 0 | K95: https://www.youtube.com/watch?v=A5CUcQsHdDg | L95: 69000 | M95: 【スカッとする話】事故で昏睡状態の夫を見舞いに来た愛人「この手紙、娘さんから預かったの。夫さんに隠れて見てって」手紙を確認した私は慌てて夫のシャツを脱がせると...
A96: 95 | D96: 95 | E96: anh le | F96: https://www.youtube.com/channel/UCarxn6vtJCi169Mjzrmzo4A | G96: https://www.youtube.com/watch?v=tETIUjJQ8Xg | H96: 1 | I96: 1 年前 | J96: 0 | K96: https://www.youtube.com/watch?v=ochYsslDkKg | L96: 98000 | M96: 【スカッとする話】親族の集まりで夫の実家へ行くと、記入済みの離婚届が机に...私「出せって事だし提出しよ」速攻で提出し姿を消した結果w
A97: 96 | D97: 96 | E97: ezebo chiamaka | F97: https://www.youtube.com/channel/UCE-qld23FOqFEVR1e-zZk_g | G97: https://www.youtube.com/watch?v=sUvK3bUzoT8 | H97: 0.98 | I97: 1 年前 | J97: 0 | K97: https://www.youtube.com/watch?v=hsj8uitT6I4 | L97: 44000 | M97: 【スカッとする話】5LDKの新築祝いに親族で集まると、夫「来年から両親と同居するw嫁は両親の介護宜しくｗ」私「え？介護はしないよ？嫁は1週間前にやめたので」夫「はい？」実は…w
A98: 97 | D98: 97 | E98: faustino karisa | F98: https://www.youtube.com/channel/UCh1wgkzk9PVxPJshc_EWlIA | G98: https://www.youtube.com/watch?v=cuby2mvuIs4 | H98: 1 | I98: 2 年前 | J98: 0 | K98: https://www.youtube.com/watch?v=zoLRHo5Z1wA | L98: 56000 | M98: 【スカッとする話】13億を築いた父の遺産を相続した途端、夫「お前の金は全部俺の金だw逆らったら離婚だからな」義両親「嫁の金は私の金w」私「え？私は独身ですけど？」夫・義両親「え？」
A99: 98 | D99: 98 | E99: 【経済的処刑】マウント成金の一文無し計画 | F99: https://www.youtube.com/channel/UCFrczgjtItoUn5iNZnathKA | G99: https://www.youtube.com/watch?v=BWVbpoIQ6xw | H99: 1 | I99: 3 か月前 | J99: 0 | K99: https://www.youtube.com/watch?v=Bnt4k5MNq9Y | L99: 38000 | M99: 【スカッとする話】500名参列の兄の結婚式で非常識な花嫁「車椅子の席は無いから帰れw」夫「じゃあ帰ろっか」私「うん」直後、招待客500名が立ち上がり…
A100: 99 | D100: 99 | E100: 【鑑定書の告発】科学が暴く「ざまぁ」の真相 | F100: https://www.youtube.com/channel/UCQilFCU3Eok7gFShbP8i38w | G100: https://www.youtube.com/watch?v=FBqCDXKN3d8 | H100: 1 | I100: 3 か月前 | J100: 0 | K100: https://www.youtube.com/watch?v=H_NZ8XCvi6M | L100: 29000 | M100: 【スカッとする話】夜勤から帰った私に気づかない長男嫁「お義母さんなんか一生いなくて良いのにw」長男「遺産貰うまでの辛抱だw」長男嫁と長男の会話が聞こえ私は無言で家を立ち去り…
A101: 100 | D101: 100 | E101: アヒルの子 | F101: https://www.youtube.com/channel/UCW4prcGFf0yqLylWHc8zRLQ | G101: https://www.youtube.com/watch?v=_U0dbAh0Ar0 | H101: 1 | I101: 3 か月前 | J101: 0 | K101: https://www.youtube.com/watch?v=7RO_1nL2V5U | L101: 79000 | M101: 【スカッとする話】10億の資産を築いた父の葬儀後に母と高級料亭へ行くと、なぜか欠席してた夫と姑の姿が…。声をかけようとすると夫と姑のとんでもない会話が聞こえたのでこっそり先手を打った結果w
A102: 101 | D102: 101 | E102: スカッと感動 !02 | F102: https://www.youtube.com/channel/UC245xKv3oOdbX57tRsuWmQg | G102: https://www.youtube.com/watch?v=ouFYMpFMg6E | H102: 1 | I102: 2 年前 | J102: 369 | K102: https://www.youtube.com/watch?v=bI91wh-7IMg | L102: 190000 | M102: 【スカッとする話】孫の七五三のお祝いに親戚一同と行くと私だけ席がない...長男嫁「他人の席は無いから立ってればw」私「じゃ帰るか」親戚一同「うん」全員で帰宅した結果w
A103: 102 | D103: 101 | E103: スカッと感動 !02 | F103: https://www.youtube.com/channel/UC245xKv3oOdbX57tRsuWmQg | G103: https://www.youtube.com/watch?v=dSdjJtEhgx8 | H103: 1 | I103: 2 年前 | J103: 1 | K103: https://www.youtube.com/watch?v=hRCh_bWpcgg | L103: 100000 | M103: 【スカッとする話】私が義母の入院費を払ってると知らず新居に引っ越した夫「寄生虫は施設でもいけw」1億の高級施設に引越し入院費の支払も止めた結果w
... A305: 304 | D305: 138 | E305: 街の物語 5687 | F305: https://www.youtube.com/channel/UCxterQPS0akz9_edy6xAiDw | G305: https://www.youtube.com/watch?v=zXDp7Lbl-9g | H305: 1 | I305: 3 週間前 | J305: 1336 | K305: https://www.youtube.com/watch?v=IkjrifvTA_A | L305: 180000 | M305: 【スカッと総集編】長男の葬儀中にペットカメラを確認すると、家の風呂場で夫と長男嫁が真っ最中 私「うわ…気持ち悪い」音量を最大にし浴室に閉じ込め、家族全員呼んでみた結果ｗ【修羅場】【スカッと】
A306: 305 | D306: 139 | E306: 雨の中の記憶、お話の部屋 | G306: https://www.youtube.com/watch?v=mAz5AIyyMYs | H306: 1 | I306: 3 週間前 | J306: 2 | K306: https://www.youtube.com/watch?v=rSLi31Fw8tI | L306: 14000 | M306: 【スカッとする話】新築一軒家の我が家が全焼し現場確認に行くと夫と幼馴染が何か探している…。2人に声をかけようとすると恐ろしい会話を聞いてしまい慌てて警察に駆け込むと…
A307: 306 | D307: 139 | E307: 雨の中の記憶、お話の部屋 | G307: https://www.youtube.com/watch?v=FrxyFWxugt8 | H307: 1 | I307: 8 日前 | J307: 27 | K307: https://www.youtube.com/watch?v=rYAfWQF1W-0 | L307: 66000 | M307: 【スカッとする話】娘と義実家の大掃除をしてると突然、娘「母さん帰るよ！」慌てた様子で車を急発進させた。私「どうしたの？」娘「見なかった？」私「え？」帰宅すると…
A308: 307 | D308: 139 | E308: 雨の中の記憶、お話の部屋 | G308: https://www.youtube.com/watch?v=NGczH5b9BE0 | H308: 0.99 | I308: 2 週間前 | J308: 1 | K308: https://www.youtube.com/watch?v=CjxJ0f62VMM | L308: 26000 | M308: 【スカッとする話】実家で母の同居介護中に娘が記入済みの離婚届を持ってきた…娘「パパが私とママはいらないって…」私「やったね！」即提出し家を売り払い更地にすると…w
A309: 308 | D309: 139 | E309: 雨の中の記憶、お話の部屋 | G309: https://www.youtube.com/watch?v=CIJOaOhk7ZI | H309: 0.99 | I309: 1 時間前 | J309: 0 | K309: https://www.youtube.com/watch?v=Fiv9d71jhj4 | L309: 21000 | M309: 【スカッとする話】38歳で妊娠した私を捨て19歳の浮気相手と再婚した警察官の夫「若い女が良いから離婚でw」20年後、警察で元夫と再会→直後、息子を見た元夫が震えだし…w
A310: 309 | D310: 139 | E310: 雨の中の記憶、お話の部屋 | G310: https://www.youtube.com/watch?v=qpUGtsvPtRY | H310: 0.97 | I310: 2 週間前 | J310: 10 | K310: https://www.youtube.com/watch?v=ixDA5L4ob04 | L310: 58000 | M310: 【スカッとする話】夫の葬儀中、涙を流す私に義母「遺産は私たちが貰うわねw」義父「これで高級老人ホーム入れるw」私「え？あなたらは1円も相続できないよ？」義両親「え？」
A311: 310 | D311: 140 | E311: 静かな夜の物語、静かな心の記録 | G311: https://www.youtube.com/watch?v=GzdH1HjwK5s | H311: 1 | I311: 4 週間前 | J311: 0 | K311: https://www.youtube.com/watch?v=Eh0FIn_sub0 | L311: 56000 | M311: 【スカッとする話】8歳の姪「1日だけ泊めて下さい...」大雪の中、赤ちゃんを抱き抱えボロボロの姿で現れた姪...。夫「え？それは無理だよ？」姪「そんな…涙」→結果
A312: 311 | D312: 140 | E312: 静かな夜の物語、静かな心の記録 | G312: https://www.youtube.com/watch?v=BGTCsj16a2I | H312: 1 | I312: 3 週間前 | J312: 0 | K312: https://www.youtube.com/watch?v=Y2GawdK7Q9E | L312: 100000 | M312: 【スカッとする話】長男夫婦に初孫が生まれ出産祝いに行くと長男嫁「二人は汚いので床でいいですか？w」長男「ジジババは段ボールの上でw」夫「...帰るか」私「うん」速帰宅し→永久に無視した結果w
A313: 312 | D313: 140 | E313: 静かな夜の物語、静かな心の記録 | G313: https://www.youtube.com/watch?v=JHUnHhyu7AU | H313: 1 | I313: 3 週間前 | J313: 2 | K313: https://www.youtube.com/watch?v=xCscEAOYwvs | L313: 35000 | M313: 【スカッとする話】なぜか夫の連れ子が湯船に入った後、必ず茶色の液体が浮いている...後日、高熱が出て病院に行くと医師「今すぐ離婚して下さい」私「え？」実は...
A314: 313 | D314: 140 | E314: 静かな夜の物語、静かな心の記録 | G314: https://www.youtube.com/watch?v=p_7Pbr4_LJQ | H314: 1 | I314: 4 日前 | J314: 0 | K314: https://www.youtube.com/watch?v=cYm3AWOE2Yc | L314: 57000 | M314: 【スカッとする話】長男夫婦の家へ孫に会いに行くと、孫娘が真っ暗な物置で食事し軒下で寝ていた。私「一体どうしたの！？」孫「１年間ずっとここで...」私「は？」直後、キレた私は...
A315: 314 | D315: 140 | E315: 静かな夜の物語、静かな心の記録 | G315: https://www.youtube.com/watch?v=aK06k2dCG3Q | H315: 1 | I315: 5 日前 | J315: 0 | K315: https://www.youtube.com/watch?v=Hdd6qR2k6_Q | L315: 40000 | M315: 【スカッとする話】K察「お宅の旦那がﾀﾋにそうです！至急現場に来て下さい！」私「え？」親族全員を呼び現場に駆けつけた結果w
A316: 315 | D316: 141 | E316: 雨の中の記憶 | F316: https://www.youtube.com/channel/UCJ_Zte-T_DYEEvf5DqPciGg | G316: https://www.youtube.com/watch?v=DvvC6Oqv0Lc | H316: 1 | I316: 1 か月前 | J316: 1 | K316: https://www.youtube.com/watch?v=WEXOfp8SBz0 | L316: 24000 | M316: 【スカッとする話】私も夫も身長160cm以下なのになぜか息子の身長が190cm超えに...。夫「浮気してたなこの裏切り者！」息子「父さん、何も知らないの？」夫「え？」実は…
A317: 316 | D317: 141 | E317: 雨の中の記憶 | F317: https://www.youtube.com/channel/UCJ_Zte-T_DYEEvf5DqPciGg | G317: https://www.youtube.com/watch?v=k3aogZE__qY | H317: 0.98 | I317: 1 か月前 | J317: 0 | K317: https://www.youtube.com/watch?v=uja6sG8362w | L317: 24000 | M317: 【スカッとする話】11年育てた連れ子の息子が医大に合格すると、連れ子「他人のくせに母親ぶるなw」私「は？お前こそ息子ぶるなよ…」入学費と仕送りを即停止し永久に他人扱いした結果w
A318: 317 | D318: 141 | E318: 雨の中の記憶 | F318: https://www.youtube.com/channel/UCJ_Zte-T_DYEEvf5DqPciGg | G318: https://www.youtube.com/watch?v=zviUeQjEC-4 | H318: 0.98 | I318: 1 か月前 | J318: 2 | K318: https://www.youtube.com/watch?v=GpzX3kYhSRk | L318: 28000 | M318: 【スカッとする話】出産で義兄の結婚式を欠席すると、義父「出産ごときで欠席？離婚だ！」義父にキレられ縁を切り式当日…義兄「父さん、状況わかってる？」義父「は？」結果w
A319: 318 | D319: 141 | E319: 雨の中の記憶 | F319: https://www.youtube.com/channel/UCJ_Zte-T_DYEEvf5DqPciGg | G319: https://www.youtube.com/watch?v=-olARGeQJ6Y | H319: 0.94 | I319: 1 か月前 | J319: 4 | K319: https://www.youtube.com/watch?v=nShlR1YbtJs | L319: 55000 | M319: 【スカッとする話】母子家庭で育てた息子の結婚挨拶へ行くと私たちだけ納豆ご飯…義父「貧乏人はそれ好きだろw」3秒後、婚約者が私を見て震え出し…義家族は全てを失う結果にw
A320: 319 | D320: 142 | E320: Catherine Mack | F320: https://www.youtube.com/channel/UChYk58s7t8r6sD1nV1Ua6PQ | G320: https://www.youtube.com/watch?v=LhX3_YMvCuQ | H320: 1 | I320: 1 年前 | J320: 2 | K320: https://www.youtube.com/watch?v=k6Uv2NHfBM0 | L320: 55000 | M320: 【スカッとする話】私が年商300億の社長だと知らず婚約者を奪った姉｢社長の旦那の子妊娠しちゃったw慰謝料はいくらでも請求してw｣→弁護士｢え？社長は妹さんの方ですよ？｣姉「はい？」
A321: 320 | D321: 142 | E321: Catherine Mack | F321: https://www.youtube.com/channel/UChYk58s7t8r6sD1nV1Ua6PQ | G321: https://www.youtube.com/watch?v=zuGycTrE4Vk | H321: 1 | I321: 1 年前 | J321: 0 | K321: https://www.youtube.com/watch?v=S46f35JhiWk | L321: 62000 | M321: 【スカッとする話】元夫の新郎に招待された結婚式に行くと私の席だけがない...元夫「俺を振った罰だwクズは帰れw」私「じゃあ今すぐ帰ります」 3分後、血相を変えた元夫から鬼電がw
A322: 321 | D322: 142 | E322: Catherine Mack | F322: https://www.youtube.com/channel/UChYk58s7t8r6sD1nV1Ua6PQ | G322: https://www.youtube.com/watch?v=V2aH3jQboDM | H322: 1 | I322: 1 年前 | J322: 0 | K322: https://www.youtube.com/watch?v=SA1PcWksbus | L322: 38000 | M322: 【スカッとする話】5歳の娘の病気が判明した途端、私と娘を捨て愛人と消えた夫。9年後、娘のある秘密を知ると夫「迎えに来たぞ！パパと帰ろう」娘「え？誰このおじさん」夫「え？」
A323: 322 | D323: 142 | E323: Catherine Mack | F323: https://www.youtube.com/channel/UChYk58s7t8r6sD1nV1Ua6PQ | G323: https://www.youtube.com/watch?v=xLhH6yee8ZE | H323: 1 | I323: 1 年前 | J323: 1 | K323: https://www.youtube.com/watch?v=f5r1JGa0gr8 | L323: 140000 | M323: 【スカッとする話】ハワイへの家族旅行当日、空港に無一文で置き去りにされた私...夫「家族だけで楽しんでくるw」義両親「アンタは野宿でもしてなw」私「はーい」→ホテルで夫と義両親が顔面蒼白にw
A324: 323 | D324: 143 | E324: Dorothy Jessika | F324: https://www.youtube.com/channel/UCjIFYuek6gc0gbT5TNn1sCQ | G324: https://www.youtube.com/watch?v=3MALgzgYIi4 | H324: 1 | I324: 1 年前 | J324: 1 | K324: https://www.youtube.com/watch?v=VXr2EWwrnTg | L324: 170000 | M324: 【スカッとする話】結婚5年目の夫を霊感のある兄に紹介…その3秒後、兄の衝撃の一言で夫がガクガク震え出し…
A325: 324 | D325: 143 | E325: Dorothy Jessika | F325: https://www.youtube.com/channel/UCjIFYuek6gc0gbT5TNn1sCQ | G325: https://www.youtube.com/watch?v=lX6KQ0Iiyuc | H325: 1 | I325: 1 年前 | J325: 0 | K325: https://www.youtube.com/watch?v=T40Q2m3NnVw | L325: 60000 | M325: 【スカッとする話】私の里帰り中に医者の婚約者を略奪した姉から連絡「彼の赤ちゃん妊娠したwアンタは帰ってくるなw」私「いいの？有り難う！」そのまま新居に引越した結果w
A326: 325 | D326: 143 | E326: Dorothy Jessika | F326: https://www.youtube.com/channel/UCjIFYuek6gc0gbT5TNn1sCQ | G326: https://www.youtube.com/watch?v=aOi6CmDCvZc | H326: 1 | I326: 2 年前 | J326: 0 | K326: https://www.youtube.com/watch?v=yefpSXnGZOg | L326: 150000 | M326: 【スカッとする話】私名義の新築戸建と知らず里帰り出産で我が家に来た娘「母さんの部屋は私が使うw」夫「お前は車で寝てろw」私「わかりました...」→キレた私が家を売り払うと...w
A327: 326 | D327: 143 | E327: Dorothy Jessika | F327: https://www.youtube.com/channel/UCjIFYuek6gc0gbT5TNn1sCQ | G327: https://www.youtube.com/watch?v=SYJmhGpshww | H327: 0.88 | I327: 1 年前 | J327: 0 | K327: https://www.youtube.com/watch?v=G4O12jIGPfg | L327: 87000 | M327: 【スカッとする話】夫が突然大量の荷物を持ってきて、夫「今日から俺の両親と姉を養う！嫌なら離婚だ！」私「え？もう離婚済みだけど？」夫「え？」結果w
... A471: 470 | D471: 179 | E471: 陽咲 | F471: https://www.youtube.com/channel/UCkWQ3TuNHjERVg8BInHuS-Q | G471: https://www.youtube.com/watch?v=n8Kyhg5TRlc | H471: 1 | I471: 2 か月前 | J471: 0 | K471: https://www.youtube.com/watch?v=g6Y6qpQoq3k | L471: 51000 | M471: 【スカッとする話】中卒で年金生活の私を見下す高学歴エリートの長男嫁「年金暮らしの貧乏人とは絶縁でw」直後、それを聞いた長男が顔面蒼白で「お、お前知らないのか？」【スカッと】
A472: 471 | D472: 180 | E472: 雨の中の記憶、静かな夜の物語 | G472: https://www.youtube.com/watch?v=LjV0uFazyvc | H472: 0.99 | I472: 4 日前 | J472: 0 | K472: https://www.youtube.com/watch?v=CjxJ0f62VMM | L472: 26000 | M472: 【スカッとする話】実家で母の同居介護中に娘が記入済みの離婚届を持ってきた…娘「パパが私とママはいらないって…」私「やったね！」即提出し家を売り払い更地にすると…w
A473: 472 | D473: 180 | E473: 雨の中の記憶、静かな夜の物語 | G473: https://www.youtube.com/watch?v=PWzjByIonsM | H473: 0.97 | I473: 9 日前 | J473: 0 | K473: https://www.youtube.com/watch?v=ixDA5L4ob04 | L473: 58000 | M473: 【スカッとする話】夫の葬儀中、涙を流す私に義母「遺産は私たちが貰うわねw」義父「これで高級老人ホーム入れるw」私「え？あなたらは1円も相続できないよ？」義両親「え？」
A474: 473 | D474: 180 | E474: 雨の中の記憶、静かな夜の物語 | G474: https://www.youtube.com/watch?v=L55fzJWf50M | H474: 0.96 | I474: 1 か月前 | J474: 0 | K474: https://www.youtube.com/watch?v=3vh_pcyKmQw | L474: 15000 | M474: 【スカッとする話】私が総資産18億と知らず職場の社長令嬢と浮気した夫「美人令嬢と再婚するからｗ」令嬢「子供は1人で育ててw」私（馬鹿ねw）1ヶ月後、半狂乱の夫たちから鬼電がｗ
A475: 474 | D475: 180 | E475: 雨の中の記憶、静かな夜の物語 | G475: https://www.youtube.com/watch?v=MnDLSd-cIco | H475: 0.95 | I475: 4 週間前 | J475: 0 | K475: https://www.youtube.com/watch?v=3ms4nR14BoM | L475: 20000 | M475: 【スカッとする話】新築タワマン購入直後に妹「夫君の子供できたし譲って」夫「離婚届書いて家から出てけ」私「え？私独身だけど？」妹・夫「え？」結果w【修羅場】【スカッと】
A476: 475 | D476: 181 | E476: 黒猫は見ていました【スカッと】 | F476: https://www.youtube.com/channel/UCOW4cd0N3rxrb7Um2iz126g | G476: https://www.youtube.com/watch?v=N663V83SPvE | H476: 0.94 | I476: 3 年前 | J476: 3523 | K476: https://www.youtube.com/watch?v=WHx8h3F0pU0 | L476: 340000 | M476: 【スカッとする話】長男夫婦との二世帯住宅ローンを月25万全額支払う私に長男嫁「小銭ぐらいで偉そうにｗ」長男「支払い止めてみろｗ」私「喜んで！」支払い止めた結果w【修羅場】【スカッと】
A477: 476 | D477: 181 | E477: 黒猫は見ていました【スカッと】 | F477: https://www.youtube.com/channel/UCOW4cd0N3rxrb7Um2iz126g | G477: https://www.youtube.com/watch?v=NzNdrn1UWdE | H477: 0.82 | I477: 3 年前 | J477: 2068 | K477: https://www.youtube.com/watch?v=GnxC9hbl3M8 | L477: 80000 | M477: 【スカッとする話】年間7億円の家賃収入がある私をATM扱いする長男嫁「ババアは私達の財布！冠婚葬祭の時だけ連絡してｗ」私「わかりました」→次男夫婦に家をあげた結果ｗ【修羅場】【スカッと】
A478: 477 | D478: 181 | E478: 黒猫は見ていました【スカッと】 | F478: https://www.youtube.com/channel/UCOW4cd0N3rxrb7Um2iz126g | G478: https://www.youtube.com/watch?v=6rQUohA7KSk | H478: 0.81 | I478: 3 年前 | J478: 2192 | K478: https://www.youtube.com/watch?v=JL2POxUZfHk | L478: 160000 | M478: 【スカッとする話】私「実家に帰らせて頂きます」夫「じゃあ二度と戻ってくるな！離婚届書いてから行け！」即提出して父に報告すると慌てた夫から鬼電が...w【修羅場】【スカッと】
A479: 478 | D479: 181 | E479: 黒猫は見ていました【スカッと】 | F479: https://www.youtube.com/channel/UCOW4cd0N3rxrb7Um2iz126g | G479: https://www.youtube.com/watch?v=d4a9fG_WjUE | H479: 0.47 | I479: 3 年前 | J479: 823 | K479: https://www.youtube.com/watch?v=yPjcL2pzTm4 | L479: 120000 | M479: 【スカっとする話】夫の浮気が発覚すると息子「パパと新しいママと暮らすから早く離婚して出てって！」3年後、笑顔で再会した息子に私「あなた誰？」息子「えっ？」【修羅場】
A480: 479 | D480: 182 | E480: 雨の中の記憶 | F480: https://www.youtube.com/channel/UC1DCXepcOSRHtwhX694HY1w | G480: https://www.youtube.com/watch?v=5bYvfIWbuGI | H480: 1 | I480: 1 か月前 | J480: 26 | K480: https://www.youtube.com/watch?v=OdNjDlmFQIc | L480: 45000 | M480: 【スカッと総集編】義実家に帰省した私を駅まで迎えに来た義母「息子とデートに行くから歩いて帰れｗ」私「では徒歩5分の新居に行きます」1時間後、ブチギレた義母が現れ…w
A481: 480 | D481: 182 | E481: 雨の中の記憶 | F481: https://www.youtube.com/channel/UC1DCXepcOSRHtwhX694HY1w | G481: https://www.youtube.com/watch?v=L_L0N9TQYEg | H481: 0.96 | I481: 1 か月前 | J481: 56 | K481: https://www.youtube.com/watch?v=3vh_pcyKmQw | L481: 15000 | M481: 【スカッとする話】私が総資産18億と知らず職場の社長令嬢と浮気した夫「美人令嬢と再婚するからｗ」令嬢「子供は1人で育ててw」私（馬鹿ねw）1ヶ月後、半狂乱の夫たちから鬼電がｗ
A482: 481 | D482: 182 | E482: 雨の中の記憶 | F482: https://www.youtube.com/channel/UC1DCXepcOSRHtwhX694HY1w | G482: https://www.youtube.com/watch?v=bA0JcBtj3bA | H482: 0.96 | I482: 1 か月前 | J482: 4 | K482: https://www.youtube.com/watch?v=3ms4nR14BoM | L482: 20000 | M482: 【スカッとする話】新築タワマン購入直後に妹「夫君の子供できたし譲って」夫「離婚届書いて家から出てけ」私「え？私独身だけど？」妹・夫「え？」結果w【修羅場】【スカッと】
A483: 482 | D483: 183 | E483: minh vương | F483: https://www.youtube.com/channel/UCdm2C4XwcbiPrnEtGAg00EQ | G483: https://www.youtube.com/watch?v=BebSddofeds | H483: 1 | I483: 2 年前 | J483: 1 | K483: https://www.youtube.com/watch?v=jA4TTTeqo-M | L483: 120000 | M483: 【スカッとする話】私が年商500億の社長と知らない夫「時給941円の底辺は出てけw」連れ子「役立たずの母親バイバイw」私「じゃあ出ていきます」１ヶ月後、涙を流した夫から鬼電がw
A484: 483 | D484: 183 | E484: minh vương | F484: https://www.youtube.com/channel/UCdm2C4XwcbiPrnEtGAg00EQ | G484: https://www.youtube.com/watch?v=32TQUrPp7rE | H484: 1 | I484: 2 年前 | J484: 0 | K484: https://www.youtube.com/watch?v=vqBTDvaavnA | L484: 78000 | M484: 【スカッとする話】ピアノの天才の姉だけを溺愛する長男嫁「発達障害の妹はお義母さんにあげるw」私「じゃあ私が育てるわね」養子にして10年育てると...
A485: 484 | D485: 183 | E485: minh vương | F485: https://www.youtube.com/channel/UCdm2C4XwcbiPrnEtGAg00EQ | G485: https://www.youtube.com/watch?v=0WEIRqXLZkM | H485: 1 | I485: 2 年前 | J485: 0 | K485: https://www.youtube.com/watch?v=acMaagt7Yv0 | L485: 110000 | M485: 【スカッとする話】夫「妊娠？知らねぇよwお願いだからもうしゃべんな！」私「..」黙って引っ越し永久に無視してやった結果ｗ
A486: 485 | D486: 184 | E486: スカッとする話 | F486: https://www.youtube.com/channel/UCE4ScoaaEmRsXAijXOWNgPw | G486: https://www.youtube.com/watch?v=lrIE3hsN3X0 | H486: 1 | I486: 2 年前 | J486: 1 | K486: https://www.youtube.com/watch?v=vyDCAcHPme8 | L486: 86000 | M486: 【スカッとする話】夫「来月ママが引っ越してくる！お前の部屋片付けておけw」私「はーい、キレイにしておくね」夫の出張中に不動産屋に連絡し家を売り払いキレイに更地にした結果w
A487: 486 | D487: 184 | E487: スカッとする話 | F487: https://www.youtube.com/channel/UCE4ScoaaEmRsXAijXOWNgPw | G487: https://www.youtube.com/watch?v=wyxcjOSAxes | H487: 0.99 | I487: 2 年前 | J487: 7 | K487: https://www.youtube.com/watch?v=BKC9CbFIESk | L487: 52000 | M487: 【スカッとする話】夫の連れ子の娘と暮らし始めて1年。しかし、全くなつく気配がない…夫が海外出張に行った日に娘が初めて話しかけてきた。娘「お母さん、実は...」そう言って差し出された手には...
... A593: 592 | D593: 219 | E593: 人生の分かれ道4716 | F593: https://www.youtube.com/channel/UCeICrgMl03_lHG8LvJYPU_A | G593: https://www.youtube.com/watch?v=_bY99k0dU6o | H593: 0.95 | I593: 2 週間前 | J593: 0 | K593: https://www.youtube.com/watch?v=ScHjrNEgsdw | L593: 73000 | M593: 【スカッとする話】私たち家族を結婚式に招待しない義母。義母「息子の式にお前ら家族は不要w」私「はーい」結婚式当日、黙って家族で沖縄旅行に行くと→義母から大量着信が…w【朗読】【スカッと】
A594: 593 | D594: 220 | E594: 人生の物語箱、他 2 チャンネル | G594: https://www.youtube.com/watch?v=4jj47ldJDS4 | H594: 1 | I594: 1 か月前 | J594: 7900 | K594: https://www.youtube.com/watch?v=blo_a56_T1U | L594: 370000 | M594: 【スカッとする話】愛人に夫を奪われた私。2人「すまん、離婚してくれ…」離婚届が置かれた瞬間、即サインし夫を譲ると、相手弁護士がガタガタ震え出しw【朗読】【スカッと】
A595: 594 | D595: 220 | E595: 人生の物語箱、他 2 チャンネル | G595: https://www.youtube.com/watch?v=Ngu9GUME2YA | H595: 1 | I595: 2 日前 | J595: 629 | K595: https://www.youtube.com/watch?v=Wobm7os3nrw | L595: 29000 | M595: 【スカッとする話】夫と離婚してから8日後、VIP病室に入院した義母から電話。義母「入院費払っておいてね」私「無理です。だって…」直後、義母が暴れ出し…w【朗読】【スカッと】
...

Sheet ラウンド2
A1: No. | B1: 申請日 | C1: 削除確認 | D1: 順位 | E1: チャンネル名 | F1: チャンネルURL | G1: 転載動画URL | H1: 一致率 | I1: 転載の投稿 | J1: 転載の再生数 | K1: 元動画URL | L1: 元動画の再生数 | M1: 元タイトル | N1: メモ
A2: 1 | D2: 1 | E2: 藤田 七海 | F2: https://www.youtube.com/channel/UCe0KTxGVR84qUjkAHQb-wGg | G2: https://www.youtube.com/watch?v=MCdA3DExAwI | H2: 1 | I2: 2 週間前 | J2: 3 | K2: https://www.youtube.com/watch?v=ZobJWKrmIzQ | L2: 77000 | M2: 【スカッとする話】娘の結婚式に愛人と共に現れた夫「彼女にも座らせてあげて」私は黙って愛人に席を譲った直後、グループ10社を束ねる新郎父「会長、お久しぶりです」【朗読】【スカッと】
A3: 2 | D3: 2 | E3: スカッと物語 | F3: https://www.youtube.com/channel/UCLz5UoQMIAja9LyZIOCYmQg | G3: https://www.youtube.com/watch?v=Ef-RDmTY9Jk | H3: 1 | I3: 7 日前 | J3: 0 | K3: https://www.youtube.com/watch?v=DEqKKzP1pB4 | L3: 21000 | M3: 【スカッとする話】通院費1万すら拒絶した息子夫婦「年金から払えば？w」翌日、家の名義を変え姿を消すと、大号泣の2人から大量着信が…w【朗読ドラマ】【朗読】【スカッと】
A4: 3 | D4: 3 | E4: 出る杭は打たれる | F4: https://www.youtube.com/channel/UCAmIDIbiOxKA9YSVK0aYSZQ | G4: https://www.youtube.com/watch?v=1cday0ktFEQ | H4: 1 | I4: 2 か月前 | J4: 0 | K4: https://www.youtube.com/watch?v=DeIUkxQ3Yjg | L4: 10000 | M4: 【スカッとする話】生まれた息子が夫に似てない。夫「浮気してたな？離婚だ！」義父「今すぐ出てけアバズレが」10年後、夫と義父と遭遇すると2人が発狂。だって息子は…
A5: 4 | D5: 4 | E5: 良い話 | F5: https://www.youtube.com/channel/UCSrk1OzKlw4sCvRbksLDgcQ | G5: https://www.youtube.com/watch?v=_NmgMfK7eX0 | H5: 1 | I5: 5 日前 | J5: 0 | K5: https://www.youtube.com/watch?v=s8zl0VxtC2k | L5: 63000 | M5: 【スカッと総集編】離婚から２週間で再婚した元夫「家柄、性格ともに最高の嫁w」夫の新しい嫁を見た瞬間、私は思わず大爆笑www→だってその嫁は…w
A6: 5 | D6: 5 | E6: 家庭の真実 5497 | F6: https://www.youtube.com/channel/UCqzVZHS7_AHD3WczZdnOkwg | G6: https://www.youtube.com/watch?v=RoD3ADzOkEQ | H6: 1 | I6: 4 週間前 | J6: 21 | K6: https://www.youtube.com/watch?v=AW46gN91lmo | L6: 18000 | M6: 【スカッとする話】孫の合格祝いで義実家に行くと私と夫だけわさびのみだった…義兄「もらえるだけ光栄だろw」私「ありがたく頂きますね」帰宅後、悶絶し涙目の義兄が…w【朗読】【スカッと】
A7: 6 | D7: 6 | E7: スカッとストーリー 5006 | F7: https://www.youtube.com/channel/UC1x3I0LM2SzXkpn57uaFuQA | G7: https://www.youtube.com/watch?v=7p73mp_ivBs | H7: 1 | I7: 1 か月前 | J7: 89 | K7: https://www.youtube.com/watch?v=Jrhwc49ujEM | L7: 68000 | M7: 【スカッとする話】貧乏なフリしてお見合いに行くと男性社長「仕事は何してるの？」私「内職です…（フラれたな）」直後、伝票に書いた私の字を見た彼「僕と付き合って」実は…【朗読】【スカッと】
A8: 7 | D8: 7 | E8: 嫁ゴコロ逆転朗読館 | F8: https://www.youtube.com/channel/UCQDSjWHn0tvkuVZav4jZnXQ | G8: https://www.youtube.com/watch?v=JIMx_juz-_s | H8: 1 | I8: 6 日前 | J8: 0 | K8: https://www.youtube.com/watch?v=Lz3rc2N2XhM | L8: 47000 | M8: 【スカッとする話】正月、帰省の新幹線で、妊娠中の私を立ち席にした夫は「腰が痛い」と1人グリーン車へ。愛人の元へ向かったと知った私は、何も告げず新大阪で姿を消すとw【朗読】【スカッと】
A9: 8 | D9: 8 | E9: 読書室【スカッとする話】 | F9: https://www.youtube.com/channel/UCjQd7ZVm5BPbGpB_V9B6kgQ | G9: https://www.youtube.com/watch?v=9zs6le8kFYk | H9: 1 | I9: 1 年前 | J9: 1 | K9: https://www.youtube.com/watch?v=7msH4kMIKYA | L9: 15000 | M9: 【スカッと】夫を略奪した妹の結婚式で妹「今日から私が社長夫人で〜すw社員は全員パシリよろしく〜w」直後、社員一同が大爆笑w→私（社長は私なんだよな…w）
A10: 9 | D10: 9 | E10: 憂鬱よりスカッと | F10: https://www.youtube.com/channel/UC8bvniIkSPPf_5ELr1VNZCQ | G10: https://www.youtube.com/watch?v=WxOpFiBUsKQ | H10: 1 | I10: 2 年前 | J10: 68 | K10: https://www.youtube.com/watch?v=jpA_PiL1qKA | L10: 31000 | M10: 【スカッとする話】私「もう限界！実家に帰ります！」実家帰省した私が家に帰ると私「ただい...ま？」机の上に記入済みの離婚届が...私「出せっていうから提出しよw」大喜びで市役所へ行った結果w
A11: 10 | D11: 10 | E11: とする話 | F11: https://www.youtube.com/channel/UC-1KoQRWd1ijwgKpAmRTQ7A | G11: https://www.youtube.com/watch?v=SBuY8D55Xp8 | H11: 1 | I11: 1 年前 | J11: 0 | K11: https://www.youtube.com/watch?v=H3HkNoT1qF0 | L11: 72000 | M11: 【スカッとする話】母が他界した直後、7歳の私を捨て職場の愛人と再婚した父「お前は目障りだから施設行けw」3か後、半狂乱の父から鬼電→私「私に父はいませんけど？」
A12: 11 | D12: 11 | E12: Dima Tomashevich | F12: https://www.youtube.com/channel/UCkfiH3lPVPodePE4eNSDpWg | G12: https://www.youtube.com/watch?v=JiYO5b0V6pU | H12: 1 | I12: 2 年前 | J12: 0 | K12: https://www.youtube.com/watch?v=3SjNRx445WM | L12: 31000 | M12: 【スカッとする話】家事に疲れて昼寝してた私に花瓶の水をぶっかけてきた長男嫁「私のおかげで暮らせてるのに…ちゃんとメシぐらい作れ！」私「無理。じゃあ出て行くわ」長男嫁「え？」
A13: 12 | D13: 12 | E13: さあ、どうぞ | F13: https://www.youtube.com/channel/UCG-XF2tttCtNESz__p6GQ7w | G13: https://www.youtube.com/watch?v=t74xjdInIKo | H13: 1 | I13: 2 か月前 | J13: 1 | K13: https://www.youtube.com/watch?v=ZJzIfS3DH88 | L13: 18000 | M13: 【スカッとする話】病気で盲目になった夫のため、365日ずっと料理を作る私に夫「味噌汁おいしかった！味噌変えた？」私は空っぽの鍋を見た瞬間、家中の鍵を全て交換し…
... A18: 17 | D18: 17 | E18: 義家族スカッと物語帳 | F18: https://www.youtube.com/channel/UCIZ41RBpQd7wBp_oOTGv1zw | G18: https://www.youtube.com/watch?v=SqxgbTS5sbk | H18: 1 | I18: 7 日前 | J18: 0 | K18: https://www.youtube.com/watch?v=wWt0dqnPt6g | L18: 65000 | M18: 【スカッとする話】38歳で両親に結婚を急かされ「相手はいる」と嘘をつくとイケメン上司「俺が恋人役するよ」1週間後、両親に会わせると父「まさか…こんな所で」実は【朗読】【スカッと】
A19: 18 | D19: 18 | E19: 静かな夜の物語、雨の中の記憶 | G19: https://www.youtube.com/watch?v=4sbyeBKVtv0 | H19: 1 | I19: 2 週間前 | J19: 0 | K19: https://www.youtube.com/watch?v=TKF2Pe7g2bE | L19: 49000 | M19: 【スカッとする話】4人の子供に囲まれ幸せな日常を送る夫が急逝し2週間後、私宛に夫から手紙が届いた「連れ子に隠れて読んでくれ...」手紙に記された場所へ行き同封の鍵で金庫を開けると...
A20: 19 | D20: 19 | E20: Noah Qumi | F20: https://www.youtube.com/channel/UCH4l3-r5NgR2RlKdoRwfzAw | G20: https://www.youtube.com/watch?v=0HyRkakDfNI | H20: 1 | I20: 7 日前 | J20: 1 | K20: https://www.youtube.com/watch?v=2meTtNT2fJ8 | L20: 250000 | M20: 【スカッとする話】母の手術費のためにバケモノ御曹司と婚約した私。父「すまんな…」結婚初日、別人の彼の姿に驚愕し…【朗読】【スカッと】
A21: 20 | D21: 20 | E21: Shinji Datの人生物語 | F21: https://www.youtube.com/channel/UCpdX_bFCePsYvPWZAMQoaeg | G21: https://www.youtube.com/watch?v=5SfD5lmv8GY | H21: 1 | I21: 2 か月前 | J21: 13 | K21: https://www.youtube.com/watch?v=uYt37nxwb0o | L21: 18000 | M21: 【スカッとする話】私の資産が9億あると知らず社長令嬢の愛人と再婚した元夫と再会「生活保護の貧乏人じゃんw元気？w」私「は？誰と勘違いしてるの？」真実を伝えると元夫が半狂乱にw【スカッと】【朗読】
A22: 21 | D22: 21 | E22: スカッとする話 5020 | F22: https://www.youtube.com/channel/UCAG5eZR0aJpGuShtjtimSEg | G22: https://www.youtube.com/watch?v=tiOlfcaKAJE | H22: 1 | I22: 1 か月前 | J22: 64 | K22: https://www.youtube.com/watch?v=gBmPsDEOoUs | L22: 97000 | M22: 【スカッとする話】結婚直前で逃げた姉の代わりに田舎の農家に嫁いだ私。私「私も手伝おうか？」夫「君は家でゆっくりしてて」翌朝、口座に1000万円…実はw【朗読】【スカッと】
A23: 22 | D23: 22 | E23: 人生の光と影 | F23: https://www.youtube.com/channel/UCYX4tsWpykTmtfNq_i36C_w | G23: https://www.youtube.com/watch?v=k8PCprhidvc | H23: 1 | I23: 8 日前 | J23: 111 | K23: https://www.youtube.com/watch?v=LMo-dxLN6Qc | L23: 37000 | M23: 【スカッとする話】12年前、私の夫を略奪し駆け落ちした長男嫁から連絡。長男嫁「旦那と久しぶりに帰るwあんたはトイレに隠れててw」私「はい…」→約束破ってトイレから飛び出すと…w【朗読】【スカッと】
A24: 23 | D24: 23 | E24: 美しい木 | F24: https://www.youtube.com/channel/UCKDhvWl0boDNeo65NQzjbOg | G24: https://www.youtube.com/watch?v=JaHSlsKxqLI | H24: 1 | I24: 3 か月前 | J24: 0 | K24: https://www.youtube.com/watch?v=SA1PcWksbus | L24: 38000 | M24: 【スカッとする話】5歳の娘の病気が判明した途端、私と娘を捨て愛人と消えた夫。9年後、娘のある秘密を知ると夫「迎えに来たぞ！パパと帰ろう」娘「え？誰このおじさん」夫「え？」
A25: 24 | D25: 24 | E25: TINA SHTIBKO | F25: https://www.youtube.com/channel/UCIQbb4FNm2BhP5GfSTbrQ4w | G25: https://www.youtube.com/watch?v=vH2vcM_uFO8 | H25: 1 | I25: 2 年前 | J25: 0 | K25: https://www.youtube.com/watch?v=l5MOnDUec8k | L25: 34000 | M25: 【スカッとする話】祖母と同居の長男夫婦に毎月25万の仕送りをする私が祖母の様子を見に行くと伝えると長男が激怒「何しにくる気だ！？今まで何もしなかったくせに！」私「は？」実は…
A26: 25 | D26: 25 | E26: フィクション 5634 | F26: https://www.youtube.com/channel/UCtx1aitp-eTJhv2c94bnBZQ | G26: https://www.youtube.com/watch?v=zjVmh756GWo | H26: 1 | I26: 3 週間前 | J26: 1324 | K26: https://www.youtube.com/watch?v=2ALPcxU2NE8 | L26: 33000 | M26: 【スカッとする話】自衛官の兄の結婚式に参加すると、義母「中卒の妹は一族の汚点w」直後、兄が義母の元に歩み寄り、兄「まだ妹の正体に気づかない？」義母「え？」【朗読】【スカッと】
A27: 26 | D27: 26 | E27: 泥だらけの絆 5655 | F27: https://www.youtube.com/channel/UCdyvc7k9wPzVO9X62aCvguQ | G27: https://www.youtube.com/watch?v=tk0adRpC7xI | H27: 1 | I27: 11 日前 | J27: 16 | K27: https://www.youtube.com/watch?v=ae1eDwWjrBU | L27: 76000 | M27: 【スカッとする話】親戚の集まりに私たち家族だけ招待しない義両親。義父「お前ら貧乏家族は不要w」私「わかりました…」家族全員で欠席しハワイ旅行行くと→大号泣の義父から鬼電がw【朗読】【スカッと】
A28: 27 | D28: 27 | E28: Bonnie Denver | F28: https://www.youtube.com/channel/UCsdndA886timZqWK6_b0d0Q | G28: https://www.youtube.com/watch?v=Lapb-z9pqnY | H28: 1 | I28: 1 年前 | J28: 1 | K28: https://www.youtube.com/watch?v=Utio_7T1lvM | L28: 54000 | M28: 【スカッとする話】11年介護した義父の葬儀後に義母「家政婦は用済み！出てけw」夫「離婚届書いて失せろw」私「分かった（全て計画通りw）」1ヶ月後、涙を流した夫と義母から鬼電がw
A29: 28 | D29: 28 | E29: 心温まるストーリー 4989 | F29: https://www.youtube.com/channel/UCS-VuYFB_DXsDhPHAzUS0JA | G29: https://www.youtube.com/watch?v=zZK_hwS9jv8 | H29: 1 | I29: 1 か月前 | J29: 72 | K29: https://www.youtube.com/watch?v=cVe3XmXeRuE | L29: 140000 | M29: 【スカッとする話】私が離婚届に署名すると、満面の笑みで大喜びする義家族。新しい嫁を迎えた1週間後、電気・ガス・水道が止まると急に義家族が焦り出しw【朗読】【スカッと】
A30: 29 | D30: 29 | E30: Jamison Abraham | F30: https://www.youtube.com/channel/UCcUsK23eqHw3ZQA5HjspM9Q | G30: https://www.youtube.com/watch?v=y8x7SoRM9mk | H30: 1 | I30: 1 年前 | J30: 0 | K30: https://www.youtube.com/watch?v=CNsn701Em6g | L30: 41000 | M30: 【スカッと】私が総資産19億と知らず子供の産めない私を捨て再婚した夫「欠陥品とは離婚ｗ家と車も俺が貰うｗ」私「いいよ！ 」→翌日、涙を流した夫から鬼電がw
A31: 30 | D31: 30 | E31: サヨナラの選択4848 | F31: https://www.youtube.com/channel/UCiDg2Vs1LHy6qIiV6ilje1A | G31: https://www.youtube.com/watch?v=iOzvYl0FjG0 | H31: 1 | I31: 2 週間前 | J31: 1 | K31: https://www.youtube.com/watch?v=yluothDtfeE | L31: 35000 | M31: 【スカッとする話】私の実家の庭に幼馴染の家を建てる夫。夫「貧乏だから助けてあげたい」私「それ本当に大丈夫？」真実を伝えると夫が震えだしw【朗読】【スカッと】
... A38: 37 | D38: 37 | E38: 痛快!!怒りのスカッとチャンネル【スカッと朗読】 | F38: https://www.youtube.com/channel/UC96mO8pXAaiP70V7KUjVHqg | G38: https://www.youtube.com/watch?v=agja1b2k0kA | H38: 1 | I38: 1 年前 | J38: 23 | K38: https://www.youtube.com/watch?v=hRCh_bWpcgg | L38: 100000 | M38: 【スカッとする話】私が義母の入院費を払ってると知らず新居に引っ越した夫「寄生虫は施設でもいけw」1億の高級施設に引越し入院費の支払も止めた結果w
A39: 38 | D39: 38 | E39: 雨の中の記憶、雨の中の記憶 | G39: https://www.youtube.com/watch?v=jzQ7tWnYBb4 | H39: 1 | I39: 3 週間前 | J39: 9 | K39: https://www.youtube.com/watch?v=c2AdQUXc1Hg | L39: 59000 | M39: 【スカッと総集編】入院した私に大量の塩をぶっかける長男嫁「このままあの世にいけwババァがいなくて最高w」キレた私は長男嫁への仕送りを停止→本当に帰らぬ人となった結果w
A40: 39 | D40: 39 | E40: スカっとゼミ!! | F40: https://www.youtube.com/channel/UC9Hd679L2faWD0aJQHeAlrA | G40: https://www.youtube.com/watch?v=DKzM1r5EGpw | H40: 0.83 | I40: 2 年前 | J40: 112 | K40: https://www.youtube.com/watch?v=6UWe8WooXpM | L40: 100000 | M40: 【スカッとする話】母子家庭で育てた長男の結婚式へ行くと私の席が無い...姑「貧乏人の席はありませんw」長男「帰ろっか..」私「うん...」義家族は全てを失う結果にw
A41: 40 | D41: 40 | E41: スカッと成敗ストーリー | F41: https://www.youtube.com/channel/UC1iIGo491nSYyJ_AsgmPzyw | G41: https://www.youtube.com/watch?v=SrlJ46l-aQs | H41: 1 | I41: 2 か月前 | J41: 0 | K41: https://www.youtube.com/watch?v=3v1qqv9z0yE | L41: 35000 | M41: 【スカッとする話】長男が双子の娘を残して他界。長男嫁「発達障害のガキは中卒の貧乏ババァに譲ってあげるw」私「では私が育てます…」10年後、まさかの展開にw
A42: 41 | D42: 41 | E42: 時を越える話 | F42: https://www.youtube.com/channel/UC_n9gc1na-2QpFv6TPInL3w | G42: https://www.youtube.com/watch?v=yVVWvJEjUsg | H42: 1 | I42: 3 週間前 | J42: 1621 | K42: https://www.youtube.com/watch?v=28rOAUunNPw | L42: 58000 | M42: 【スカッとする話】夫から高級化粧品を貰った私。夫「あれ、もう使った？w」私「お義母さんが試してたよ」直後、なぜか夫が慌て出しw【朗読】【スカッと】
A43: 42 | D43: 42 | E43: 涙の向こう側 | F43: https://www.youtube.com/channel/UCOXAYjsxUMpublA1yS1ATIA | G43: https://www.youtube.com/watch?v=SjEoD7MKz0E | H43: 1 | I43: 6 日前 | J43: 2934 | K43: https://www.youtube.com/watch?v=yqCdgYsZcrQ | L43: 47000 | M43: 【スカッとする話】初孫のお食い初めに行くと私を無視する長男夫婦…私「おめでと！」長男・嫁「…」キレた私は家具家電を黙って捨て家を売払い更地にすると…w【朗読】【スカッと】
A44: 43 | D44: 43 | E44: 老いの詩 | F44: https://www.youtube.com/channel/UClKj-HO63gh7qxtT7M0czEQ | G44: https://www.youtube.com/watch?v=SPvJ4YWDGWU | H44: 1 | I44: 1 か月前 | J44: 7 | K44: https://www.youtube.com/watch?v=qNSSnNaMxrs | L44: 80000 | M44: 【スカッとする話】私1人で育てた息子の顔合わせで、なぜか私たちだけお茶漬け…義家族「貧乏人は好きだろ？w」直後、私の存在に気づいた義兄「俺たちの人生終了だ…」【朗読】【スカッと】
A45: 44 | D45: 44 | E45: Ivan Ilencow | F45: https://www.youtube.com/channel/UC6IzQHpKzqIt1DgjPouEefQ | G45: https://www.youtube.com/watch?v=IZLbdwBj7XA | H45: 1 | I45: 2 年前 | J45: 0 | K45: https://www.youtube.com/watch?v=ik5Oxry7o0g | L45: 31000 | M45: 【スカッとする話】勝手に我が家の庭でバーベキューをする長男嫁「お義母さんの家の庭借りてるよw肉とビール無いから買ってきてw」私「え？私の家そこじゃないわよ？」長男嫁「え？」
A46: 45 | D46: 45 | E46: Legacy Apollo | F46: https://www.youtube.com/channel/UC2YwIXq-utTkNLQgcRVloyQ | G46: https://www.youtube.com/watch?v=Vk35R5f7G2w | H46: 1 | I46: 2 年前 | J46: 0 | K46: https://www.youtube.com/watch?v=uSa9TRN9UTA | L46: 44000 | M46: 【スカッとする話】長男夫婦「ババァは口を開くな！」食事さえ許されずガリガリの私…久々に帰国した次男「母さんは食べないの？」私「いつもの事よ…」次男「は？」その後..【修羅場】
A47: 46 | D47: 46 | E47: Pendelton Gideon | F47: https://www.youtube.com/channel/UCIRVjzjmTHwXA3X81dpyNeQ | G47: https://www.youtube.com/watch?v=bK4E6flKw4g | H47: 0.99 | I47: 1 年前 | J47: 1 | K47: https://www.youtube.com/watch?v=8p7Hl5wjPok | L47: 370000 | M47: 【スカッとする話】大雪の中、赤ちゃんを背負い2時間歩いてきた8歳の姪「3000円貸して下さい...」夫「はぁ？貸すわけないだろ！」次の瞬間、ブチギレた夫は...
A48: 47 | D48: 47 | E48: Павел **** | F48: https://www.youtube.com/channel/UCSPg9ALk7YwnsqACClpErGg | G48: https://www.youtube.com/watch?v=EnUXTdRCsLE | H48: 1 | I48: 2 年前 | J48: 2 | K48: https://www.youtube.com/watch?v=UOK61ieeNvk | L48: 26000 | M48: 【スカッとする話】夫と高級寿司屋へ行くと長男と長男嫁の姿が...長男「来年は保険金で生活するぞｗ」長男嫁「フランスでの生活楽しみ～ｗ」→面白い会話が聞こえたので夫と先手を打った結果ｗ
A49: 48 | D49: 48 | E49: 人生スカッと朗読館 | F49: https://www.youtube.com/channel/UChTkZ7g3oCCQG3XSqe69LWQ | G49: https://www.youtube.com/watch?v=R6VSFZgv9rc | H49: 1 | I49: 4 日前 | J49: 0 | K49: https://www.youtube.com/watch?v=eFu4Ak6nNYo | L49: 28000 | M49: 【スカッとする話】結婚式をドタキャンした妹の代わりに、田舎の大工と結婚させられた私。私「バイトして生活費入れるね」夫「必要ないよ！だって…」翌日、半狂乱の妹が自宅に来てw【朗読ドラマ】【スカッと】
A50: 49 | D50: 49 | E50: 夜の語り部5056 | F50: https://www.youtube.com/channel/UCEvaB4r-6y7tj3UAoMEdqXA | G50: https://www.youtube.com/watch?v=-PbKfh2Ga5A | H50: 1 | I50: 1 か月前 | J50: 28 | K50: https://www.youtube.com/watch?v=DPS_qm8jKlI | L50: 100000 | M50: 【スカッとする話】私の年収が1000万と知らず夫と一緒に出ていった息子「毒親とは絶縁wバイバイw」私「じゃあ夫とも縁切るね」息子「勝手にどうぞw」2日後w【朗読】【スカッと】
A51: 50 | D51: 50 | E51: 妻の復讐 5649 | F51: https://www.youtube.com/channel/UC_-FBuCpoEW8RPG4j-oCbkg | G51: https://www.youtube.com/watch?v=HB8kbxdHmcw | H51: 1 | I51: 2 週間前 | J51: 0 | K51: https://www.youtube.com/watch?v=Suxi8PzXzbk | L51: 85000 | M51: 【スカッとする話】里帰り出産中、私の荷物が全て実家に送られてきた…夫「この家で母と暮らすから離婚でw」義母「役立たずは帰ってこないでねw」私「ありがとう、助かる！」実は…
... A88: 87 | D88: 87 | E88: 逆転ストーリー 5008 | F88: https://www.youtube.com/channel/UCriVTHI8ZSlCtGVvqIqnMSw | G88: https://www.youtube.com/watch?v=REKSObfsXg4 | H88: 1 | I88: 4 週間前 | J88: 124 | K88: https://www.youtube.com/watch?v=p8J-A05WKIc | L88: 15000 | M88: 【スカッとする話】本社に異動になった中卒の私が東大卒の女部長に挨拶すると女部長「あんたが噂の中卒ねw部下はコーヒー淹れてきてw」私（今は泳がせとこw）実はw【朗読】【スカッと】
A89: 88 | D89: 88 | E89: 雨の中の記憶、静かな心の記録 | G89: https://www.youtube.com/watch?v=JFWqw8vLobc | H89: 1 | I89: 11 日前 | J89: 1 | K89: https://www.youtube.com/watch?v=KKEWop4fNrk | L89: 66000 | M89: 【スカッと総集編】私が総資産が28億の社長令嬢と知らず私を裏切り職場の美人同僚と再婚した夫「美人同僚と再婚するから離婚w」同僚「子供は1人で頑張れｗ」私「はーい」1ヶ月後、夫達から鬼電がw
A90: 89 | D90: 89 | E90: 雨の中の記憶、静かな終わり | G90: https://www.youtube.com/watch?v=OQIXO7vA7VU | H90: 0.99 | I90: 1 日前 | J90: 6 | K90: https://www.youtube.com/watch?v=2kqFB_BTrsg | L90: 26000 | M90: 【スカッとする話】医師「奥様と娘さんが退院しました。お迎えお願いいたします」私「え？私に娘はいませんが？」直後、隣で聞いていた霊感のある母→母「その電話、切ったらダメよ！」
A91: 90 | D91: 90 | E91: 静かな夜の物語、お話の部屋 | G91: https://www.youtube.com/watch?v=IpBhmLwfWrM | H91: 1 | I91: 3 週間前 | J91: 2 | K91: https://www.youtube.com/watch?v=0bP_EWes9dM | L91: 98000 | M91: 【スカッとする話】私が義実家の大黒柱と知らず、親戚の集まりでビールをぶっかけた夫「寄生虫は除菌しなきゃｗ」私「じゃあ仕送り止めるわね」夫・義両親「え？」結果ｗ
A92: 91 | D92: 91 | E92: Avalynn Roderick | F92: https://www.youtube.com/channel/UC2ALeyYaaWwXZhLpaAxCjDA | G92: https://www.youtube.com/watch?v=0MrNXOwrCi4 | H92: 1 | I92: 2 年前 | J92: 0 | K92: https://www.youtube.com/watch?v=ZWebgSwWOzY | L92: 27000 | M92: 【スカッとする話】育休を終え職場に出社した私が新しい女部長に挨拶すると「あれ？清掃のおばちゃん？邪魔だから床掃除でもしてろw」直後、全社員がブルブル震え出し...
A93: 92 | D93: 92 | E93: Chi Tông | F93: https://www.youtube.com/channel/UCQZmlpJ03rsGpabdpOyYt5g | G93: https://www.youtube.com/watch?v=i0IlkEaZ0l4 | H93: 1 | I93: 1 年前 | J93: 0 | K93: https://www.youtube.com/watch?v=b8ZAxV1gG_4 | L93: 20000 | M93: 【スカッとする話】夫と姉の出産祝いに行くと5歳の娘「赤ちゃんが言いたい事あるみたい」不思議な力を持つ娘の言葉に戦慄し私は慌てて警察へ駆け込み...
A94: 93 | D94: 93 | E94: Malani Darren | F94: https://www.youtube.com/channel/UCGjfIdDymNvLcybwzheXAnQ | G94: https://www.youtube.com/watch?v=_ZWaNI5zlHg | H94: 1 | I94: 1 年前 | J94: 0 | K94: https://www.youtube.com/watch?v=l5TmQouYi48 | L94: 64000 | M94: 【スカッとする話】家のローンを月15万払っている私に夫「料理が下手な役立たずは出てけ！」私「いいけどホームレスになっても大丈夫？」夫「ならねぇよw」結果w【修羅場】
A95: 94 | D95: 94 | E95: Thuong Le | F95: https://www.youtube.com/channel/UCxXjwf3LJAKSZP_9Thu5meA | G95: https://www.youtube.com/watch?v=WUNQJvfMUC4 | H95: 1 | I95: 1 年前 | J95: 0 | K95: https://www.youtube.com/watch?v=jwP1fK1sfSY | L95: 50000 | M95: 【スカっとする話】夫の浮気が発覚すると夫の連れ子「パパと新しいママと暮らす！偽物は離婚して出てけ！」1年後、笑顔で再会した娘に私「あんた誰？」娘「は？」
A96: 95 | D96: 95 | E96: anh le | F96: https://www.youtube.com/channel/UCarxn6vtJCi169Mjzrmzo4A | G96: https://www.youtube.com/watch?v=9KJurDT1N8M | H96: 0.97 | I96: 1 年前 | J96: 0 | K96: https://www.youtube.com/watch?v=X-4klsI7p0M | L96: 68000 | M96: 【スカッとする話】義母に車を貸した翌日、事故で入院した私。義母「タイヤがパンクなんて不運w車椅子生活とか可哀想にw」私「車椅子は夫ですけど？」義母「え？」結果w
A97: 96 | D97: 96 | E97: ezebo chiamaka | F97: https://www.youtube.com/channel/UCE-qld23FOqFEVR1e-zZk_g | G97: https://www.youtube.com/watch?v=aUS_QDDx5aY | H97: 0.98 | I97: 1 年前 | J97: 2 | K97: https://www.youtube.com/watch?v=g3-T_5JMrcU | L97: 49000 | M97: 【スカッとする話】うつ病の義父の介護を私に押し付け愛人と海外旅行へ行った夫「親父の介護は任せたぞｗ」義父「今すぐこの家を売り払うぞ」義父と家を売却し更地にした結果w
A98: 97 | D98: 97 | E98: faustino karisa | F98: https://www.youtube.com/channel/UCh1wgkzk9PVxPJshc_EWlIA | G98: https://www.youtube.com/watch?v=7_2TawB2EPg | H98: 1 | I98: 2 年前 | J98: 0 | K98: https://www.youtube.com/watch?v=8r9b0asur18 | L98: 43000 | M98: 【スカッとする話】全員を私が養ってると知らずハワイ旅行で長男嫁「ババァは帰って掃除でもしろw」長男「タダで旅行とか100年早いw」私「承知しました...」速攻で帰宅し家を売り払い掃除した結果w
A99: 98 | D99: 98 | E99: 【経済的処刑】マウント成金の一文無し計画 | F99: https://www.youtube.com/channel/UCFrczgjtItoUn5iNZnathKA | G99: https://www.youtube.com/watch?v=qtDEJ912bEQ | H99: 1 | I99: 3 か月前 | J99: 0 | K99: https://www.youtube.com/watch?v=sYIoUlkI-BU | L99: 56000 | M99: 【スカッとする話】毎日9時間、義父の介護していると知らず新入社員と不倫し私を捨てた夫「これ離婚届w後は新嫁と母がやるw」私「はーい、じゃ介護9時間は宜しく」介護負担と症状伝えて引越した結果w
A100: 99 | D100: 99 | E100: 【鑑定書の告発】科学が暴く「ざまぁ」の真相 | F100: https://www.youtube.com/channel/UCQilFCU3Eok7gFShbP8i38w | G100: https://www.youtube.com/watch?v=Lew8zDbicYg | H100: 1 | I100: 3 か月前 | J100: 1 | K100: https://www.youtube.com/watch?v=4IAX-ZgUR2k | L100: 36000 | M100: 【スカッとする話】結婚3年目の夫を霊感のある姉に紹介…その直後、姉の一言でなぜか夫が動揺し始め…
A101: 100 | D101: 100 | E101: アヒルの子 | F101: https://www.youtube.com/channel/UCW4prcGFf0yqLylWHc8zRLQ | G101: https://www.youtube.com/watch?v=47slf20zh10 | H101: 1 | I101: 3 か月前 | J101: 0 | K101: https://www.youtube.com/watch?v=n-SwmIWzdeo | L101: 19000 | M101: 【スカッとする話】3年前に記入済みの離婚届を残し失踪した夫が突然帰宅「家に帰ってやったぞwビールと高級寿司用意しろw」無言で家の荷物を回収した私「じゃあ私も実家に帰りますね」夫「は？実家？」【修羅場】

Sheet ラウンド3
A1: No. | B1: 申請日 | C1: 削除確認 | D1: 順位 | E1: チャンネル名 | F1: チャンネルURL | G1: 転載動画URL | H1: 一致率 | I1: 転載の投稿 | J1: 転載の再生数 | K1: 元動画URL | L1: 元動画の再生数 | M1: 元タイトル | N1: メモ
A2: 1 | D2: 1 | E2: 藤田 七海 | F2: https://www.youtube.com/channel/UCe0KTxGVR84qUjkAHQb-wGg | G2: https://www.youtube.com/watch?v=4wCL6JN8awg | H2: 1 | I2: 4 週間前 | J2: 4 | K2: https://www.youtube.com/watch?v=lw1jxku6xxo | L2: 14000 | M2: 【スカッとする話】離婚した3日後に再婚した元夫「金持ちで若い嫁ゲットw」私「ごめん、笑いすぎて腹痛いwだって、その女は…w」真実を知った夫は顔面蒼白にw【朗読】【スカッと】
A3: 2 | D3: 2 | E3: スカッと物語 | F3: https://www.youtube.com/channel/UCLz5UoQMIAja9LyZIOCYmQg | G3: https://www.youtube.com/watch?v=kzk9Ium2XNM | H3: 1 | I3: 7 日前 | J3: 0 | K3: https://www.youtube.com/watch?v=W7iyZQfb2oU | L3: 41000 | M3: 【スカッとする話】父が毎日お茶漬けなので、私「仕送り10万じゃ足りない？」父「仕送り？貰ってないぞ」私「変ね…銀行に電話するわ」直後、夫がガタガタ震え出し…【朗読ドラマ】【朗読】【スカッと】
A4: 3 | D4: 3 | E4: 出る杭は打たれる | F4: https://www.youtube.com/channel/UCAmIDIbiOxKA9YSVK0aYSZQ | G4: https://www.youtube.com/watch?v=cZ_wZEMKHQQ | H4: 1 | I4: 2 か月前 | J4: 0 | K4: https://www.youtube.com/watch?v=7z-EBP9QVbU | L4: 18000 | M4: 【スカッとする話】両親と同居するための新築一軒家が完成すると、夫「お袋の介護か離婚か選べw」私「え？同居するつもり？2週間前から他人なのに？」夫「え？他人？」実はw
A5: 4 | D5: 4 | E5: 良い話 | F5: https://www.youtube.com/channel/UCSrk1OzKlw4sCvRbksLDgcQ | G5: https://www.youtube.com/watch?v=_17PdwgYQtA | H5: 1 | I5: 5 日前 | J5: 0 | K5: https://www.youtube.com/watch?v=VX7Q7VMHXOo | L5: 43000 | M5: 【スカッとする話】新婚3ヶ月で初めて義実家に泊まると、夫「もし嫁イビリされたら教えて」私「大丈夫。全力で反撃するから」結果w【スカッと】【朗読】
A6: 5 | D6: 5 | E6: 家庭の真実 5497 | F6: https://www.youtube.com/channel/UCqzVZHS7_AHD3WczZdnOkwg | G6: https://www.youtube.com/watch?v=Y9etLclFzxg | H6: 1 | I6: 4 週間前 | J6: 22 | K6: https://www.youtube.com/watch?v=6DiHSqB63W0 | L6: 41000 | M6: 【スカッとする話】夫が出張で遠出するたび、私を実家へ帰らせる義母。義母「理由はいいから！」不審に思い静かに家に戻ると、玄関から怪しい声が聞こえ…【朗読】【スカッと】
A7: 6 | D7: 6 | E7: スカッとストーリー 5006 | F7: https://www.youtube.com/channel/UC1x3I0LM2SzXkpn57uaFuQA | G7: https://www.youtube.com/watch?v=Q4TYGcJUdS4 | H7: 1 | I7: 1 か月前 | J7: 16 | K7: https://www.youtube.com/watch?v=p4pyD9SD1Tk | L7: 81000 | M7: 【スカッとする話】義両親に蹴られ骨折した私に夫「寝かせとけば治るw」翌日、病室に嘲笑いに来た義家族「あれ、嫁は？w」医師「警察署です」義家族「え？」【朗読】【スカッと】
A8: 7 | D8: 7 | E8: 嫁ゴコロ逆転朗読館 | F8: https://www.youtube.com/channel/UCQDSjWHn0tvkuVZav4jZnXQ | G8: https://www.youtube.com/watch?v=gf855k-72TE | H8: 1 | I8: 8 日前 | J8: 0 | K8: https://www.youtube.com/watch?v=bUesKx2d9r8 | L8: 27000 | M8: 【スカッとする話】夫「3年間アメリカに赴任する」私「長すぎる！私も一緒に行く」夫「お前は家を守っててくれ」1年後、デパートで夫と妊婦を目撃→証拠を押さえ全て開示すると…w
A9: 8 | D9: 8 | E9: 読書室【スカッとする話】 | F9: https://www.youtube.com/channel/UCjQd7ZVm5BPbGpB_V9B6kgQ | G9: https://www.youtube.com/watch?v=MfZT_x26nhg | H9: 1 | I9: 1 年前 | J9: 0 | K9: https://www.youtube.com/watch?v=Z2pKxDTj5Io | L9: 24000 | M9: 【スカッと】私と息子を捨てて私の妹と再婚した夫「邪魔者2人は失せろw」妹「3日以内に出てってねw」息子「母さん良かったね！」私「え？」息子「だってあの人たち…」
A10: 9 | D10: 9 | E10: 憂鬱よりスカッと | F10: https://www.youtube.com/channel/UC8bvniIkSPPf_5ELr1VNZCQ | G10: https://www.youtube.com/watch?v=mHSslWPvj0E | H10: 1 | I10: 2 年前 | J10: 49 | K10: https://www.youtube.com/watch?v=Ne3lH19M3rA | L10: 95000 | M10: 【スカッとする話】娘「毎月1300円の仕送り助かるよ！毎日半額の弁当食べてるよ！」私「え？毎月13万円振り込んでるわよ？」娘「え？」実は...
A11: 10 | D11: 10 | E11: とする話 | F11: https://www.youtube.com/channel/UC-1KoQRWd1ijwgKpAmRTQ7A | G11: https://www.youtube.com/watch?v=EqQHa2ddtO8 | H11: 1 | I11: 1 年前 | J11: 1 | K11: https://www.youtube.com/watch?v=_1Jc1H2WcQc | L11: 11000 | M11: 【スカッとする話】医者一族と結婚した義妹の結婚式で義妹「中卒の貧乏人は一族の恥wアンタらの席はないから帰れw」夫「帰るか」私「はい」30分後、義妹から鬼電がw
A12: 11 | D12: 11 | E12: Dima Tomashevich | F12: https://www.youtube.com/channel/UCkfiH3lPVPodePE4eNSDpWg | G12: https://www.youtube.com/watch?v=b4Hl6zXY_vI | H12: 1 | I12: 2 年前 | J12: 0 | K12: https://www.youtube.com/watch?v=samZXNv0pmY | L12: 30000 | M12: 【スカッとする話】医者の長男が亡くなり通夜振る舞いで私の席だけない。長男嫁「ババァは帰れw夫の遺産と家は嫁である私が相続しますw」それを聞いた私は大爆笑w→だって長男は…【修羅場】
A13: 12 | D13: 12 | E13: さあ、どうぞ | F13: https://www.youtube.com/channel/UCG-XF2tttCtNESz__p6GQ7w | G13: https://www.youtube.com/watch?v=8i7FiAPnp0Q | H13: 1 | I13: 2 か月前 | J13: 0 | K13: https://www.youtube.com/watch?v=ZOSTbqZ1QDQ | L13: 42000 | M13: 【スカッとする話】私の娘にだけお年玉をくれない義母「アンタに似た低学歴の孫は他人wもらえるのは家族だけよｗ」キレた私は義母への仕送り20万を停止→永久に他人扱いしてやった結果w
... A18: 17 | D18: 17 | E18: 義家族スカッと物語帳 | F18: https://www.youtube.com/channel/UCIZ41RBpQd7wBp_oOTGv1zw | G18: https://www.youtube.com/watch?v=e8AUCDntWUs | H18: 1 | I18: 7 日前 | J18: 1 | K18: https://www.youtube.com/watch?v=qORErX-vqL8 | L18: 32000 | M18: 【スカッとする話】同窓会で東大卒のイケメン医師が中卒でバイトの私に難病症例を提示。医師「解けたら何でもするw」私「あ、それ難しくないよ」【朗読】【スカッと】
A19: 18 | D19: 18 | E19: 静かな夜の物語、雨の中の記憶 | G19: https://www.youtube.com/watch?v=ze9iOqJewBo | H19: 1 | I19: 2 週間前 | J19: 0 | K19: https://www.youtube.com/watch?v=T40Q2m3NnVw | L19: 60000 | M19: 【スカッとする話】私の里帰り中に医者の婚約者を略奪した姉から連絡「彼の赤ちゃん妊娠したwアンタは帰ってくるなw」私「いいの？有り難う！」そのまま新居に引越した結果w
A20: 19 | D20: 19 | E20: Noah Qumi | F20: https://www.youtube.com/channel/UCH4l3-r5NgR2RlKdoRwfzAw | G20: https://www.youtube.com/watch?v=kwDoLkr5Sbk | H20: 1 | I20: 10 日前 | J20: 0 | K20: https://www.youtube.com/watch?v=aCFKEISe330 | L20: 360000 | M20: 【スカッとする話】同窓会で結婚直前に私を捨てた夫と再会。夫「金持ちの社長令嬢と結婚したw俺だけ幸せでごめんなw」私「本当にそう思う？」真実を伝えると元夫が震え出し…【朗読】【スカッと】
A21: 20 | D21: 20 | E21: Shinji Datの人生物語 | F21: https://www.youtube.com/channel/UCpdX_bFCePsYvPWZAMQoaeg | G21: https://www.youtube.com/watch?v=F-JFquYn4l8 | H21: 1 | I21: 2 か月前 | J21: 20 | K21: https://www.youtube.com/watch?v=C6r_ataNQZU | L21: 180000 | M21: 【スカッと総集編】起業した夫を支えてきた私を裏切った夫「21歳のバイトを妊娠させた！悪いが、離婚してくれ！」私「はーい、仕事も辞めるね！」夫「は？仕事は続けてくれよ」
A22: 21 | D22: 21 | E22: スカッとする話 5020 | F22: https://www.youtube.com/channel/UCAG5eZR0aJpGuShtjtimSEg | G22: https://www.youtube.com/watch?v=z0gg-kdn8Io | H22: 1 | I22: 3 週間前 | J22: 39 | K22: https://www.youtube.com/watch?v=azDvOP8I1Ck | L22: 22000 | M22: 【スカッとする話】同窓会に出席した肉屋の私。金持ち同級生「お前肉屋？wじゃあ旦那は豚かw呼べw」1時間後、社長の夫が会場に到着。キレた夫「豚だけど呼んだ？」【朗読】【スカッと】
A23: 22 | D23: 22 | E23: 人生の光と影 | F23: https://www.youtube.com/channel/UCYX4tsWpykTmtfNq_i36C_w | G23: https://www.youtube.com/watch?v=eKijFqrCIO4 | H23: 1 | I23: 5 日前 | J23: 62 | K23: https://www.youtube.com/watch?v=3ROoZpLQQvY | L23: 18000 | M23: 【スカッとする話】姉夫婦の婚約祝いに到着すると息子「ママ、今すぐ帰ろう！早く発車して！」混乱する息子に理由を聞くと、息子「後ろみて…」私「え？」【朗読】【スカッと】
A24: 23 | D24: 23 | E24: 美しい木 | F24: https://www.youtube.com/channel/UCKDhvWl0boDNeo65NQzjbOg | G24: https://www.youtube.com/watch?v=6OMd2U0O26s | H24: 1 | I24: 2 か月前 | J24: 2 | K24: https://www.youtube.com/watch?v=XeaG3k_O8iM | L24: 31000 | M24: 【スカッとする話】夫「もう我慢できん！クズ嫁とは離婚！」夫婦喧嘩の翌日出張から帰ると私「この前はごめ...ん？」机の上に記入済みの離婚届が...速攻で提出してやった結果w
A25: 24 | D25: 24 | E25: TINA SHTIBKO | F25: https://www.youtube.com/channel/UCIQbb4FNm2BhP5GfSTbrQ4w | G25: https://www.youtube.com/watch?v=OJFNQ_YQztc | H25: 1 | I25: 2 年前 | J25: 0 | K25: https://www.youtube.com/watch?v=iknFXLIJR7c | L25: 37000 | M25: 【スカッとする話】兄嫁に奴隷扱いされてる祖母「家から出して！」兄に相談すると「そんならお前らが引き取れ！」私「はい、預かります」祖母を夫の別荘に住ませた結果w
A26: 25 | D26: 25 | E26: フィクション 5634 | F26: https://www.youtube.com/channel/UCtx1aitp-eTJhv2c94bnBZQ | G26: https://www.youtube.com/watch?v=UmOdOkciR2g | H26: 1 | I26: 3 週間前 | J26: 186 | K26: https://www.youtube.com/watch?v=i4CX2w0EpjQ | L26: 65000 | M26: 【スカッとする話】不倫され無一文で追い出された私。偶然見た大富豪の継母募集に応募。1ヶ月後、知らせを聞いた元夫がいきなり家の前に現れ…w【朗読】【スカッと】
A27: 26 | D27: 26 | E27: 泥だらけの絆 5655 | F27: https://www.youtube.com/channel/UCdyvc7k9wPzVO9X62aCvguQ | G27: https://www.youtube.com/watch?v=uVKwqGj4XDE | H27: 1 | I27: 8 日前 | J27: 0 | K27: https://www.youtube.com/watch?v=FKxO2ZIWpyI | L27: 87000 | M27: 【スカッとする話】父「もう限界だ…助けて」息子夫婦から年金と貯金を摂取されボロボロな姿で現れた。私「一緒に暮らそ」父「ええんか？涙」翌日、息子夫婦が泣き叫びw【朗読】【スカッと】
A28: 27 | D28: 27 | E28: Bonnie Denver | F28: https://www.youtube.com/channel/UCsdndA886timZqWK6_b0d0Q | G28: https://www.youtube.com/watch?v=t9IBLjg2a_M | H28: 1 | I28: 1 年前 | J28: 0 | K28: https://www.youtube.com/watch?v=BEKjWcB_3Mk | L28: 56000 | M28: 【スカッと】孫の結婚式に行くと私達夫婦を嫌う新婦「中卒の貧乏ジジババは祝儀置いて田舎に帰れw」夫「…帰るか」私「…うん」30分後、半狂乱の新婦がw
A29: 28 | D29: 28 | E29: 心温まるストーリー 4989 | F29: https://www.youtube.com/channel/UCS-VuYFB_DXsDhPHAzUS0JA | G29: https://www.youtube.com/watch?v=2pKVUEdoXJI | H29: 1 | I29: 3 週間前 | J29: 19 | K29: https://www.youtube.com/watch?v=vQdhdcwgO20 | L29: 21000 | M29: 【スカッとする話】父が急逝し女社長になった私。副社長「これ退職届80人分wコネだけの女は皆無理ってw」翌日、新聞を見た元部下が土下座→全員を無視してあげた結果w【朗読】【スカッと】
A30: 29 | D30: 29 | E30: Jamison Abraham | F30: https://www.youtube.com/channel/UCcUsK23eqHw3ZQA5HjspM9Q | G30: https://www.youtube.com/watch?v=I1fCJmwv5aM | H30: 1 | I30: 1 年前 | J30: 0 | K30: https://www.youtube.com/watch?v=zZV5oL3aIHY | L30: 37000 | M30: 【スカッとする話】孫の七五三祝いに行くと私だけ席がない...夫の連れ子「家族以外は立ってろw」夫「...帰るか」私「うん」直後、連れ子に大惨事がw
A31: 30 | D31: 30 | E31: サヨナラの選択4848 | F31: https://www.youtube.com/channel/UCiDg2Vs1LHy6qIiV6ilje1A | G31: https://www.youtube.com/watch?v=9en_nSlDc5I | H31: 1 | I31: 2 週間前 | J31: 0 | K31: https://www.youtube.com/watch?v=XA-rA7VecBI | L31: 55000 | M31: 【スカッとする話】同居の約束で新築の4000万援助したのに勝手に嫁両親を住ませる息子夫婦「家の名義は私たちなのでw」キレた夫が銀行融資を停止→2週間後、息子から鬼電がw【朗読】【スカッと】
... A38: 37 | D38: 37 | E38: 痛快!!怒りのスカッとチャンネル【スカッと朗読】 | F38: https://www.youtube.com/channel/UC96mO8pXAaiP70V7KUjVHqg | G38: https://www.youtube.com/watch?v=704G8Q4fTlM | H38: 1 | I38: 1 年前 | J38: 20 | K38: https://www.youtube.com/watch?v=g4FVXeIsDTQ | L38: 140000 | M38: 【スカッとする話】夫を略奪した姉から結婚式の招待状が届くと、父「母さんと2人で行くよ」母「地獄を見せてくるわね」普段温厚な両親がこの後...w
A39: 38 | D39: 38 | E39: 雨の中の記憶、雨の中の記憶 | G39: https://www.youtube.com/watch?v=91jZsqJGQeo | H39: 1 | I39: 2 週間前 | J39: 6 | K39: https://www.youtube.com/watch?v=u2ktHPgl-Nc | L39: 39000 | M39: 【スカッとする話】義家族と高級料亭へ行くと義母「あんたのカードで払ったよw支払い30万円よろしくねw」私「え？私カード持ってないけど…」義母「は？」結果w
A40: 39 | D40: 39 | E40: スカっとゼミ!! | F40: https://www.youtube.com/channel/UC9Hd679L2faWD0aJQHeAlrA | G40: https://www.youtube.com/watch?v=8p3vkkh73Zo | H40: 0.81 | I40: 1 年前 | J40: 174305 | K40: https://www.youtube.com/watch?v=IIMdWb_44ts | L40: 370000 | M40: 【スカッとする話】風呂も寝室も完全別で夜の行為も一切しない夫が緊急入院し手術する事に→医師「い、一体なんだこれは…」夫の体を見た医師が震え出し...
A41: 40 | D41: 40 | E41: スカッと成敗ストーリー | F41: https://www.youtube.com/channel/UC1iIGo491nSYyJ_AsgmPzyw | G41: https://www.youtube.com/watch?v=m_8afsZanW4 | H41: 1 | I41: 2 か月前 | J41: 1 | K41: https://www.youtube.com/watch?v=SwTnBYd5lG0 | L41: 100000 | M41: 【スカッとする話】長男嫁「このタワマンは私の両親に住んでもらう！他人は出てけw」私「はーい、喜んで！」翌日、家の売却手続きを済ませ夫と1億の豪邸に引越した結果w
A42: 41 | D42: 41 | E42: 時を越える話 | F42: https://www.youtube.com/channel/UC_n9gc1na-2QpFv6TPInL3w | G42: https://www.youtube.com/watch?v=ycSulISX7t8 | H42: 1 | I42: 3 週間前 | J42: 489 | K42: https://www.youtube.com/watch?v=2t3thqCEE5U | L42: 43000 | M42: 【スカッとする話】旦那が出張中、手土産を持って夫を亡くした親友を訪ねた私。しかし玄関のドアを開け、目の前の光景を見た瞬間、私「今までありがとう」実は【朗読】【スカッと】
A43: 42 | D43: 42 | E43: 涙の向こう側 | F43: https://www.youtube.com/channel/UCOXAYjsxUMpublA1yS1ATIA | G43: https://www.youtube.com/watch?v=PDCuakh5uO4 | H43: 1 | I43: 2 日前 | J43: 27 | K43: https://www.youtube.com/watch?v=W8UO8b4fyYc | L43: 11000 | M43: 【スカッとする話】私が菜園と庭付き一戸建てを購入すると夫「両親と妹夫婦も引越して来るからw」義母「私たちの介護もよろしくねw」引越し当日、発狂した義母から鬼電→義母「と、隣の家の人って…」
A44: 43 | D44: 43 | E44: 老いの詩 | F44: https://www.youtube.com/channel/UClKj-HO63gh7qxtT7M0czEQ | G44: https://www.youtube.com/watch?v=z5nlzoCfBGg | H44: 1 | I44: 1 か月前 | J44: 5 | K44: https://www.youtube.com/watch?v=pdhclv8SJrI | L44: 85000 | M44: 【スカッとする話】昼休みに同僚とカフェに入ると、隣の席に夫と若い女性が…夫「妻は2年前に他界したからwこの後うち来ていいよw」先回りし最高のおもてなしをするとw【朗読】【スカッと】
A45: 44 | D45: 44 | E45: Ivan Ilencow | F45: https://www.youtube.com/channel/UC6IzQHpKzqIt1DgjPouEefQ | G45: https://www.youtube.com/watch?v=NF3p6kjJQmw | H45: 1 | I45: 2 年前 | J45: 3 | K45: https://www.youtube.com/watch?v=hhT_cSBqCts | L45: 60000 | M45: 【スカッとする話】私が社員900人の社長と知らず私の親友を妊娠させ再婚した夫「病気持ちの貧乏人とは離婚ｗ」退院後、真っ先に夫の勤め先へ。私「全取引を停止で」夫「は？」
A46: 45 | D46: 45 | E46: Legacy Apollo | F46: https://www.youtube.com/channel/UC2YwIXq-utTkNLQgcRVloyQ | G46: https://www.youtube.com/watch?v=HTl3ryWNJfI | H46: 1 | I46: 2 年前 | J46: 0 | K46: https://www.youtube.com/watch?v=W_2WifFIdxI | L46: 61000 | M46: 【スカッとする話】長男嫁のスマホに夫から着信。手を離せない長男嫁の代わりに私がスピーカーにして電話に出ると、嫁と勘違いした夫と長男がトンデモナイ会話をしはじめ…私は慌てて警察に通報した結果【修羅場】
A47: 46 | D47: 46 | E47: Pendelton Gideon | F47: https://www.youtube.com/channel/UCIRVjzjmTHwXA3X81dpyNeQ | G47: https://www.youtube.com/watch?v=BKdnXXwAz_8 | H47: 0.98 | I47: 1 年前 | J47: 0 | K47: https://www.youtube.com/watch?v=fz32YDbWe1Q | L47: 53000 | M47: 【スカッと】私が新築タワマンを購入した途端に夫「明日から愛人と同居する！」愛人「ババァは私の家から出てけw」私「え？私は独身ですが？」夫・愛人「は？」結果w
A48: 47 | D48: 47 | E48: Павел **** | F48: https://www.youtube.com/channel/UCSPg9ALk7YwnsqACClpErGg | G48: https://www.youtube.com/watch?v=-uUdEw9DTRY | H48: 1 | I48: 2 年前 | J48: 0 | K48: https://www.youtube.com/watch?v=OGc065QvS9Q | L48: 29000 | M48: 【スカッとする話】夫「赤ん坊はロッカーに放り込んどいたぞｗ」私「娘なら一緒にいるけど？」夫「は？」慌てて戻った夫が絶句。実はその子...
A49: 48 | D49: 48 | E49: 人生スカッと朗読館 | F49: https://www.youtube.com/channel/UChTkZ7g3oCCQG3XSqe69LWQ | G49: https://www.youtube.com/watch?v=KAK0g14QoEk | H49: 1 | I49: 2 日前 | J49: 0 | K49: https://www.youtube.com/watch?v=IsPanDg1vH0 | L49: 28000 | M49: 【スカッとする話】娘の葬儀に愛人を連れてきた婿「最期に間に合わなくて残念w」愛人「遺産2億は私達が相続ねw」私「…ですってw」夫「助かるなw」愛人「え？」実はw【朗読ドラマ】【朗読】【スカッと】
A50: 49 | D50: 49 | E50: 夜の語り部5056 | F50: https://www.youtube.com/channel/UCEvaB4r-6y7tj3UAoMEdqXA | G50: https://www.youtube.com/watch?v=TH7qfqD12cA | H50: 1 | I50: 1 か月前 | J50: 7 | K50: https://www.youtube.com/watch?v=DPS_qm8jKlI | L50: 100000 | M50: 【スカッとする話】私の年収が1000万と知らず夫と一緒に出ていった息子「毒親とは絶縁wバイバイw」私「じゃあ夫とも縁切るね」息子「勝手にどうぞw」2日後w【朗読】【スカッと】
A51: 50 | D51: 50 | E51: 妻の復讐 5649 | F51: https://www.youtube.com/channel/UC_-FBuCpoEW8RPG4j-oCbkg | G51: https://www.youtube.com/watch?v=hyAYIjXQyj0 | H51: 1 | I51: 3 週間前 | J51: 0 | K51: https://www.youtube.com/watch?v=7Vq5sNaCsNc | L51: 260000 | M51: 【スカッとする話】義母の嫁いびりが原因で夫と離婚。夫「今すぐ出てけ役立たずw」私「はい」両親と共に挨拶を済ませ迎えに来た車に乗り込むと→夫・義母「え？」
... A88: 87 | D88: 87 | E88: 逆転ストーリー 5008 | F88: https://www.youtube.com/channel/UCriVTHI8ZSlCtGVvqIqnMSw | G88: https://www.youtube.com/watch?v=oOG4kNeC0o8 | H88: 1 | I88: 4 週間前 | J88: 117 | K88: https://www.youtube.com/watch?v=sd51TvGQSo0 | L88: 49000 | M88: 【スカッとする話】夫と作業着で株主総会へ行くと総務部長「小汚い貧乏人は帰れw」夫「俺、大株主なんだけど…」部長「じゃあ全株売ってみろよw」私「もしもし？全株（999億）売却で」結果w【朗読】
A89: 88 | D89: 88 | E89: 雨の中の記憶、静かな心の記録 | G89: https://www.youtube.com/watch?v=VMGI0GJDgqA | H89: 1 | I89: 12 日前 | J89: 0 | K89: https://www.youtube.com/watch?v=c2AdQUXc1Hg | L89: 59000 | M89: 【スカッと総集編】入院した私に大量の塩をぶっかける長男嫁「このままあの世にいけwババァがいなくて最高w」キレた私は長男嫁への仕送りを停止→本当に帰らぬ人となった結果w
A90: 89 | D90: 89 | E90: 雨の中の記憶、静かな終わり | G90: https://www.youtube.com/watch?v=ZRc8IkmBlhw | H90: 0.99 | I90: 7 日前 | J90: 6 | K90: https://www.youtube.com/watch?v=HeH8HawqG-A | L90: 52000 | M90: 【スカッとする話】帰宅した私と息子に気づかない義両親。義母「バカ嫁が産んだ息子もバカｗ」義父「介護要員には良いだろｗ」私「…引っ越すわよ」息子「…うん」黙って豪邸に引越した結果ｗ
A91: 90 | D91: 90 | E91: 静かな夜の物語、お話の部屋 | G91: https://www.youtube.com/watch?v=ndorpzHpT74 | H91: 1 | I91: 4 週間前 | J91: 0 | K91: https://www.youtube.com/watch?v=GacXmYkB2z8 | L91: 110000 | M91: 【スカッと総集編】妊娠10ヶ月の私を地下室に閉じこめ夫とハワイ旅行に行った義両親「クズ嫁はそこで反省してなw」1週間後、帰宅した義母が腐敗臭に気づき慌てて地下室の扉を開けると...
A92: 91 | D92: 91 | E92: Avalynn Roderick | F92: https://www.youtube.com/channel/UC2ALeyYaaWwXZhLpaAxCjDA | G92: https://www.youtube.com/watch?v=PSSh0xDOrIo | H92: 1 | I92: 2 年前 | J92: 0 | K92: https://www.youtube.com/watch?v=Gujab48F13I | L92: 52000 | M92: 【スカッとする話】夫が出張に行った途端、5歳の娘が突然私に衝撃発言「今のうちにパパと離婚して！」私「はい？」理由を聞いて私は慌てて警察に通報した結果【修羅場】
A93: 92 | D93: 92 | E93: Chi Tông | F93: https://www.youtube.com/channel/UCQZmlpJ03rsGpabdpOyYt5g | G93: https://www.youtube.com/watch?v=k6-vdzKCc2w | H93: 0.99 | I93: 1 年前 | J93: 0 | K93: https://www.youtube.com/watch?v=BtTfiARWz5Y | L93: 90000 | M93: 【スカッとする話】出張帰りの夫のスーツのポッケからなぜか記入済みの離婚届が...私（出せって事だし提出しよw）速攻で提出し引越した結果w
A94: 93 | D94: 93 | E94: Malani Darren | F94: https://www.youtube.com/channel/UCGjfIdDymNvLcybwzheXAnQ | G94: https://www.youtube.com/watch?v=S7YEiucouR8 | H94: 1 | I94: 1 年前 | J94: 0 | K94: https://www.youtube.com/watch?v=lp-CDBvDiYk | L94: 20000 | M94: 【スカッとする話】長男夫婦が経営する高級寿司屋に行くとガリしか料理を出さない長男嫁「貧乏臭いジジババにはこれで十分w」直後、普段温厚な夫が大激怒「じゃあ賃料300万アップな」長男嫁「は？」【修羅場】
A95: 94 | D95: 94 | E95: Thuong Le | F95: https://www.youtube.com/channel/UCxXjwf3LJAKSZP_9Thu5meA | G95: https://www.youtube.com/watch?v=ZBhiDg4Gc2g | H95: 0.99 | I95: 1 年前 | J95: 0 | K95: https://www.youtube.com/watch?v=aWa2vGRXJF8 | L95: 38000 | M95: 【スカッと】10年介護した義父の葬儀後に夫「おい家政婦！これ洗濯しとけ！」なぜかポッケに記入済みの離婚届が…速攻で役所に提出し引越すと半狂乱の夫から鬼電がw
A96: 95 | D96: 95 | E96: anh le | F96: https://www.youtube.com/channel/UCarxn6vtJCi169Mjzrmzo4A | G96: https://www.youtube.com/watch?v=mXJGPiwViMI | H96: 0.96 | I96: 1 年前 | J96: 0 | K96: https://www.youtube.com/watch?v=GUlWy08QqT0 | L96: 68000 | M96: 【スカッとする話】体調不良で夕飯に冷凍食品を出すとビール瓶を投げてきた夫「家政婦が料理サボるとは何事だ！」間一髪避けると後ろから叫び声...→振り返ると鬼の形相の義父が...
A97: 96 | D97: 96 | E97: ezebo chiamaka | F97: https://www.youtube.com/channel/UCE-qld23FOqFEVR1e-zZk_g | G97: https://www.youtube.com/watch?v=kVZyTmqZFtc | H97: 0.98 | I97: 1 年前 | J97: 1 | K97: https://www.youtube.com/watch?v=UQlpAe4Omjw | L97: 61000 | M97: 【スカッとする話】夫が他界すると夫の連れ子「遺産いくら？」私「夫の両親が相続して0円よ...」連れ子「じゃアンタの娘辞めるわw」後日、テレビを見た連れ子から鬼電→永久に無視してやった結果w
A98: 97 | D98: 97 | E98: faustino karisa | F98: https://www.youtube.com/channel/UCh1wgkzk9PVxPJshc_EWlIA | G98: https://www.youtube.com/watch?v=U38XPq9Ek98 | H98: 1 | I98: 2 年前 | J98: 0 | K98: https://www.youtube.com/watch?v=5ASi2YeIxuc | L98: 69000 | M98: 【スカッとする話】母子家庭で育てた娘の結婚式当日、なぜか私の席だけが無い...。医者一族の義両親「席がないなら帰れw」私「では帰りますね」お望み通り帰った結果w
A99: 98 | D99: 98 | E99: 【経済的処刑】マウント成金の一文無し計画 | F99: https://www.youtube.com/channel/UCFrczgjtItoUn5iNZnathKA | G99: https://www.youtube.com/watch?v=Eclzt94z-y8 | H99: 1 | I99: 3 か月前 | J99: 0 | K99: https://www.youtube.com/watch?v=7Y1h9MMUaIU | L99: 70000 | M99: 【スカッとする話】半年入院していた私が退院し家に帰ると我が家に義母と義姉の大量の荷物が…義母「ここは私の家w」義姉「病人は出てけw」夫「出ていこう」私「そうね」家を売り払い引越した結果w
A100: 99 | D100: 99 | E100: 【鑑定書の告発】科学が暴く「ざまぁ」の真相 | F100: https://www.youtube.com/channel/UCQilFCU3Eok7gFShbP8i38w | G100: https://www.youtube.com/watch?v=lijjphDtTME | H100: 1 | I100: 3 か月前 | J100: 0 | K100: https://www.youtube.com/watch?v=td6d5s8qLow | L100: 140000 | M100: 【スカッとする話】銀行員の夫を略奪した親友「双子の赤ちゃん産んだのw出産祝い180万お願いねw」私「うん、銀行頭取の旦那と行くね！」親友「え？」結果w
A101: 100 | D101: 100 | E101: アヒルの子 | F101: https://www.youtube.com/channel/UCW4prcGFf0yqLylWHc8zRLQ | G101: https://www.youtube.com/watch?v=tl8Rw4bM3rs | H101: 1 | I101: 3 か月前 | J101: 0 | K101: https://www.youtube.com/watch?v=0sVwSDIsx5c | L101: 41000 | M101: 【スカッとする話】夫が誕生日に愛人と温泉旅行。夫「ケーキ？ゴミは捨てといて」私「わかった、ゴミは捨てておくね…」夫の大事なアレもコレも捨てた結果w【修羅場】

Sheet 全転載一覧
A1: No. | B1: チャンネル名 | C1: チャンネルURL | D1: 転載動画URL | E1: 形式 | F1: 一致率 | G1: 転載の投稿 | H1: 転載の再生数 | I1: 転載タイトル | J1: 元動画URL | K1: 元動画の投稿 | L1: 元動画の再生数 | M1: 元タイトル | N1: 申請日 | O1: 削除確認
A2: 1 | B2: 藤田 七海 | C2: https://www.youtube.com/channel/UCe0KTxGVR84qUjkAHQb-wGg | D2: https://www.youtube.com/watch?v=H3NTQ4PrQQY | E2: 朗読/同形式 | F2: 1 | G2: 2 週間前 | H2: 54 | I2: 【スカッとする話】私の退職金をやたら気にする夫「いくら貰ったの？」私「口座に2000万入った！」翌日、カードを手に夫が失踪。私（計画通りw）実は【朗読】【スカッと】 | J2: https://www.youtube.com/watch?v=dOy6I1JE_yY | K2: 3 週間前 | L2: 30000 | M2: 【スカッとする話】私の退職金をやたら気にする夫「いくら貰ったの？」私「口座に2000万入った！」翌日、カードを手に夫が失踪。私（計画通りw）実は【朗読】【スカッと】
A3: 2 | B3: 藤田 七海 | C3: https://www.youtube.com/channel/UCe0KTxGVR84qUjkAHQb-wGg | D3: https://www.youtube.com/watch?v=MCdA3DExAwI | E3: 朗読/同形式 | F3: 1 | G3: 2 週間前 | H3: 3 | I3: 【スカッとする話】娘の結婚式に愛人と共に現れた夫「彼女にも座らせてあげて」私は黙って愛人に席を譲った直後、グループ10社を束ねる新郎父「会長、お久しぶりです」【朗読】【スカッと】 | J3: https://www.youtube.com/watch?v=ZobJWKrmIzQ | K3: 4 週間前 | L3: 77000 | M3: 【スカッとする話】娘の結婚式に愛人と共に現れた夫「彼女にも座らせてあげて」私は黙って愛人に席を譲った直後、グループ10社を束ねる新郎父「会長、お久しぶりです」【朗読】【スカッと】
A4: 3 | B4: 藤田 七海 | C4: https://www.youtube.com/channel/UCe0KTxGVR84qUjkAHQb-wGg | D4: https://www.youtube.com/watch?v=4wCL6JN8awg | E4: 朗読/同形式 | F4: 1 | G4: 4 週間前 | H4: 4 | I4: 【スカッとする話】離婚した3日後に再婚した元夫「金持ちで若い嫁ゲットw」私「ごめん、笑いすぎて腹痛いwだって、その女は…w」真実を知った夫は顔面蒼白にw【朗読】【スカッと】 | J4: https://www.youtube.com/watch?v=lw1jxku6xxo | K4: 1 か月前 | L4: 14000 | M4: 【スカッとする話】離婚した3日後に再婚した元夫「金持ちで若い嫁ゲットw」私「ごめん、笑いすぎて腹痛いwだって、その女は…w」真実を知った夫は顔面蒼白にw【朗読】【スカッと】
A5: 4 | B5: 藤田 七海 | C5: https://www.youtube.com/channel/UCe0KTxGVR84qUjkAHQb-wGg | D5: https://www.youtube.com/watch?v=wrdB3yaai4M | E5: 朗読/同形式 | F5: 1 | G5: 4 週間前 | H5: 128 | I5: 【スカッとする話】旦那が出張中、手土産を持って夫を亡くした親友を訪ねた私。しかし玄関のドアを開け、目の前の光景を見た瞬間、私「今までありがとう」実は【朗読】【スカッと】 | J5: https://www.youtube.com/watch?v=2t3thqCEE5U | K5: 1 か月前 | L5: 43000 | M5: 【スカッとする話】旦那が出張中、手土産を持って夫を亡くした親友を訪ねた私。しかし玄関のドアを開け、目の前の光景を見た瞬間、私「今までありがとう」実は【朗読】【スカッと】
A6: 5 | B6: 藤田 七海 | C6: https://www.youtube.com/channel/UCe0KTxGVR84qUjkAHQb-wGg | D6: https://www.youtube.com/watch?v=PMDTClN0lT8 | E6: 朗読/同形式 | F6: 1 | G6: 4 週間前 | H6: 20 | I6: 【スカッとする話】お盆に親戚の集まりに行くと、親戚一同が私を無視…義母（うわw来たよ…）無言でその場を立ち去り4日後、親戚全員から大量着信が…w【朗読】【スカッと】 | J6: https://www.youtube.com/watch?v=uSakJfqMq3Y | K6: 1 か月前 | L6: 33000 | M6: 【スカッとする話】お盆に親戚の集まりに行くと、親戚一同が私を無視…義母（うわw来たよ…）無言でその場を立ち去り4日後、親戚全員から大量着信が…w【朗読】【スカッと】
A7: 6 | B7: 藤田 七海 | C7: https://www.youtube.com/channel/UCe0KTxGVR84qUjkAHQb-wGg | D7: https://www.youtube.com/watch?v=FQOy31WsX70 | E7: 朗読/同形式 | F7: 1 | G7: 4 週間前 | H7: 7 | I7: 【スカッとする話】私がビル100棟のオーナーと知らず、私を捨て社長令嬢と再婚した夫「俺だけ金持ちなってごめんw」私「本当にそう思ってるの？」夫「嫉妬すんなってw」→翌日w【朗読】【スカッと】 | J7: https://www.youtube.com/watch?v=IOzGqAeYdYQ | K7: 1 か月前 | L7: 48000 | M7: 【スカッとする話】私がビル100棟のオーナーと知らず、私を捨て社長令嬢と再婚した夫「俺だけ金持ちなってごめんw」私「本当にそう思ってるの？」夫「嫉妬すんなってw」→翌日w【朗読】【スカッと】
A8: 7 | B8: 藤田 七海 | C8: https://www.youtube.com/channel/UCe0KTxGVR84qUjkAHQb-wGg | D8: https://www.youtube.com/watch?v=rD8lL-lTo0A | E8: 朗読/同形式 | F8: 1 | G8: 4 週間前 | H8: 2 | I8: 【スカッとする話】私「正月に両親ウチ来るから」夫「新年から最悪の幕開けw来てる間は出てくわw」私「では私が出ていきます」離婚届を提出し永久に姿を消すとw【朗読】【スカッと】 | J8: https://www.youtube.com/watch?v=TUFznlJ6JeM | K8: 1 か月前 | L8: 22000 | M8: 【スカッとする話】私「正月に両親ウチ来るから」夫「新年から最悪の幕開けw来てる間は出てくわw」私「では私が出ていきます」離婚届を提出し永久に姿を消すとw【朗読】【スカッと】
A9: 8 | B9: 藤田 七海 | C9: https://www.youtube.com/channel/UCe0KTxGVR84qUjkAHQb-wGg | D9: https://www.youtube.com/watch?v=vVqgyRmaiKY | E9: 朗読/同形式 | F9: 1 | G9: 3 週間前 | H9: 7 | I9: 【スカッとする話】結婚挨拶から帰宅した息子「片親の貧乏人とは白紙って…」息子の頬にはビンタの痕が…キレた私は義家族に即電話→義家族全員が号泣の展開にw【朗読】【スカッと】 | J9: https://www.youtube.com/watch?v=sTmob2uIaqg | K9: 1 か月前 | L9: 72000 | M9: 【スカッとする話】結婚挨拶から帰宅した息子「片親の貧乏人とは白紙って…」息子の頬にはビンタの痕が…キレた私は義家族に即電話→義家族全員が号泣の展開にw【朗読】【スカッと】
A10: 9 | B10: 藤田 七海 | C10: https://www.youtube.com/channel/UCe0KTxGVR84qUjkAHQb-wGg | D10: https://www.youtube.com/watch?v=1xXNKv0BneY | E10: 朗読/同形式 | F10: 1 | G10: 3 週間前 | H10: 1 | I10: 【スカッとする話】娘がアスペルガーと診断されると、夫「離婚でw親権はお前なw」絶望の中、号泣する私に娘「ママ、これは何…？」娘が指差した紙を拾い上げると…【朗読】【スカッと】 | J10: https://www.youtube.com/watch?v=h7fUPWG2iGU | K10: 1 か月前 | L10: 16000 | M10: 【スカッとする話】娘がアスペルガーと診断されると、夫「離婚でw親権はお前なw」絶望の中、号泣する私に娘「ママ、これは何…？」娘が指差した紙を拾い上げると…【朗読】【スカッと】
A11: 10 | B11: 藤田 七海 | C11: https://www.youtube.com/channel/UCe0KTxGVR84qUjkAHQb-wGg | D11: https://www.youtube.com/watch?v=lFRyvF4udC4 | E11: 朗読/同形式 | F11: 1 | G11: 3 週間前 | H11: 5 | I11: 【スカッとする話】私を嫌う義両親が私を無視。私「おやすみ」2人「…」ハワイ旅行当日に姿を消すと鬼電。義両親「今どこ？」私「…」無視して空港に置き去りにするとw【朗読】【スカッと】 | J11: https://www.youtube.com/watch?v=VqAVQppeIsM | K11: 1 か月前 | L11: 20000 | M11: 【スカッとする話】私を嫌う義両親が私を無視。私「おやすみ」2人「…」ハワイ旅行当日に姿を消すと鬼電。義両親「今どこ？」私「…」無視して空港に置き去りにするとw【朗読】【スカッと】
A12: 11 | B12: 藤田 七海 | C12: https://www.youtube.com/channel/UCe0KTxGVR84qUjkAHQb-wGg | D12: https://www.youtube.com/watch?v=IgH2SYySqdI | E12: 朗読/同形式 | F12: 1 | G12: 3 週間前 | H12: 76 | I12: 【スカッとする話】息子のために貯めた800万の進学資金を勝手に義母に渡した夫「ママが家買うから渡したw文句あるなら離婚！」私「OK」息子「今までありがとう！」夫「え？」【朗読】【スカッと】 | J12: https://www.youtube.com/watch?v=UMALXNxEZ8g | K12: 1 か月前 | L12: 46000 | M12: 【スカッとする話】息子のために貯めた800万の進学資金を勝手に義母に渡した夫「ママが家買うから渡したw文句あるなら離婚！」私「OK」息子「今までありがとう！」夫「え？」【朗読】【スカッと】
A13: 12 | B13: 藤田 七海 | C13: https://www.youtube.com/channel/UCe0KTxGVR84qUjkAHQb-wGg | D13: https://www.youtube.com/watch?v=EE_JZnyJVgE | E13: 朗読/同形式 | F13: 1 | G13: 3 週間前 | H13: 38 | I13: 【スカッとする話】裕福な義家族と高級料亭に行くと、義兄嫁「その服で同席する気？お前とは格が違うんだよ」義母「ええ、あなたとは違うわね」義兄嫁「え？」実はw【朗読】【スカッと】 | J13: https://www.youtube.com/watch?v=InEluoUt8ik | K13: 1 か月前 | L13: 33000 | M13: 【スカッとする話】裕福な義家族と高級料亭に行くと、義兄嫁「その服で同席する気？お前とは格が違うんだよ」義母「ええ、あなたとは違うわね」義兄嫁「え？」実はw【朗読】【スカッと】
... A362: 361 | B362: 義家族スカッと物語帳 | C362: https://www.youtube.com/channel/UCIZ41RBpQd7wBp_oOTGv1zw | D362: https://www.youtube.com/watch?v=46Cl0fYNJIg | E362: 朗読/同形式 | F362: 0.85 | G362: 8 日前 | H362: 56 | I362: 【スカッとする話】夫婦で新築を購入すると、義家族が荷物を大量に搬入。義家族「私たちも住むからw」拒否すると夫が激怒したが、私の一言で義家族が震え出しw【朗読】【スカッと】 | J362: https://www.youtube.com/watch?v=cnmmrAEygJc | K362: 4 か月前 | L362: 15000 | M362: 【スカッとする話】夫婦で新築を購入すると、義家族が荷物を大量に搬入。義家族「私たちも住むからw」拒否すると夫が激怒したが、私の一言で義家族が震え出しw【朗読】【スカッと】
A363: 362 | B363: 静かな夜の物語、雨の中の記憶 | D363: https://www.youtube.com/watch?v=hKi2-HjQLs0 | E363: 朗読/同形式 | F363: 1 | G363: 2 週間前 | H363: 0 | I363: 【スカッと総集編】家事、育児、介護、パートをこなし15年。私「もう限界。実家に帰ります」夫「はぁ？ガキの面倒は？飯は？帰るなら離婚届書いてけ！」→速提出して両親に離婚報告すると涙を流した夫が家に来て… | J363: https://www.youtube.com/watch?v=Yrtj6pTpQ5A | K363: 2 年前 | L363: 100000 | M363: 【スカッと総集編】家事、育児、介護、パートをこなし15年。私「もう限界。実家に帰ります」夫「はぁ？ガキの面倒は？飯は？帰るなら離婚届書いてけ！」→速提出して両親に離婚報告すると涙を流した夫が家に来て…
A364: 363 | B364: 静かな夜の物語、雨の中の記憶 | D364: https://www.youtube.com/watch?v=4sbyeBKVtv0 | E364: 朗読/同形式 | F364: 1 | G364: 2 週間前 | H364: 0 | I364: 【スカッとする話】4人の子供に囲まれ幸せな日常を送る夫が急逝し2週間後、私宛に夫から手紙が届いた「連れ子に隠れて読んでくれ...」手紙に記された場所へ行き同封の鍵で金庫を開けると... | J364: https://www.youtube.com/watch?v=TKF2Pe7g2bE | K364: 2 年前 | L364: 49000 | M364: 【スカッとする話】4人の子供に囲まれ幸せな日常を送る夫が急逝し2週間後、私宛に夫から手紙が届いた「連れ子に隠れて読んでくれ...」手紙に記された場所へ行き同封の鍵で金庫を開けると...
A365: 364 | B365: 静かな夜の物語、雨の中の記憶 | D365: https://www.youtube.com/watch?v=ze9iOqJewBo | E365: 朗読/同形式 | F365: 1 | G365: 2 週間前 | H365: 0 | I365: 【スカッとする話】私の里帰り中に医者の婚約者を略奪した姉から連絡「彼の赤ちゃん妊娠したwアンタは帰ってくるなw」私「いいの？有り難う！」そのまま新居に引越した結果w | J365: https://www.youtube.com/watch?v=T40Q2m3NnVw | K365: 2 年前 | L365: 60000 | M365: 【スカッとする話】私の里帰り中に医者の婚約者を略奪した姉から連絡「彼の赤ちゃん妊娠したwアンタは帰ってくるなw」私「いいの？有り難う！」そのまま新居に引越した結果w
A366: 365 | B366: 静かな夜の物語、雨の中の記憶 | D366: https://www.youtube.com/watch?v=sxpe2kRt6MQ | E366: 朗読/同形式 | F366: 1 | G366: 2 週間前 | H366: 0 | I366: 【スカッとする話】私が社員9000人の社長と知らず父が亡くなった途端に豹変した夫「お前の遺産は俺が管理する！文句あるなら離婚して失せろw」私「はーい」即離婚して夫の勤め先へ→私「全取引中止で」 | J366: https://www.youtube.com/watch?v=AG72nH3Qr4E | K366: 2 年前 | L366: 270000 | M366: 【スカッとする話】私が社員9000人の社長と知らず父が亡くなった途端に豹変した夫「お前の遺産は俺が管理する！文句あるなら離婚して失せろw」私「はーい」即離婚して夫の勤め先へ→私「全取引中止で」
A367: 366 | B367: 静かな夜の物語、雨の中の記憶 | D367: https://www.youtube.com/watch?v=dsXb5aq2bps | E367: 朗読/同形式 | F367: 1 | G367: 2 週間前 | H367: 0 | I367: 【スカッとする話】親族の集まりで30人分のおせちを床にぶちまけた長男嫁「親族にゴミ食わせる気かw」孫「急いで肉買ってこいw」私「え？私は今買い出し中だけど？」長男嫁「え？」実は... | J367: https://www.youtube.com/watch?v=ncvmZKkz9Hw | K367: 2 年前 | L367: 92000 | M367: 【スカッとする話】親族の集まりで30人分のおせちを床にぶちまけた長男嫁「親族にゴミ食わせる気かw」孫「急いで肉買ってこいw」私「え？私は今買い出し中だけど？」長男嫁「え？」実は...
A368: 367 | B368: 静かな夜の物語、雨の中の記憶 | D368: https://www.youtube.com/watch?v=Tyv1Jl6SFJ8 | E368: 朗読/同形式 | F368: 1 | G368: 13 日前 | H368: 0 | I368: 【スカッとする話】私が資産170億の不動産王と知らず私から夫を奪った美人な姉「生活保護でも貰え貧乏人w」後日、示談交渉で弁護士が大爆笑→弁護士「生活保護はアナタでは？w」姉「え？」実は... | J368: https://www.youtube.com/watch?v=y8ReyKKeUUQ | K368: 2 年前 | L368: 100000 | M368: 【スカッとする話】私が資産170億の不動産王と知らず私から夫を奪った美人な姉「生活保護でも貰え貧乏人w」後日、示談交渉で弁護士が大爆笑→弁護士「生活保護はアナタでは？w」姉「え？」実は...
A369: 368 | B369: 静かな夜の物語、雨の中の記憶 | D369: https://www.youtube.com/watch?v=1ohy7LZ6Wdo | E369: 朗読/同形式 | F369: 1 | G369: 2 週間前 | H369: 0 | I369: 【スカッとする話】私の父が亡くなった途端、実家を無断で解体した夫「ここは更地にして民宿にするw」それを聞いた娘が大爆笑→娘「お父さん知らないの？w」実は... | J369: https://www.youtube.com/watch?v=KlztcZvQraE | K369: 2 年前 | L369: 91000 | M369: 【スカッとする話】私の父が亡くなった途端、実家を無断で解体した夫「ここは更地にして民宿にするw」それを聞いた娘が大爆笑→娘「お父さん知らないの？w」実は...
A370: 369 | B370: 静かな夜の物語、雨の中の記憶 | D370: https://www.youtube.com/watch?v=o0udygfbu2Y | E370: 朗読/同形式 | F370: 1 | G370: 9 日前 | H370: 2 | I370: 【スカッとする話】地下室に隠れ夫と親友が真っ最中だった...母「嫁子、戸締りしておいたわよ！」ど天然の母が気づかず鍵を閉めたので永遠に放置し新居に引越した結果 | J370: https://www.youtube.com/watch?v=cF4ti4NhgGU | K370: 2 年前 | L370: 170000 | M370: 【スカッとする話】地下室に隠れ夫と親友が真っ最中だった...母「嫁子、戸締りしておいたわよ！」ど天然の母が気づかず鍵を閉めたので永遠に放置し新居に引越した結果w
A371: 370 | B371: 静かな夜の物語、雨の中の記憶 | D371: https://www.youtube.com/watch?v=XFnYvkDe64A | E371: 朗読/同形式 | F371: 1 | G371: 8 日前 | H371: 1 | I371: 【スカッとする話】超高級車を10台持つ金持ち自慢の婚約者の実家へ結婚挨拶に行くと、義母「私の奴隷さんいらっしゃいw」婚約者「貧乏な顔だろ？親の顔が見たいぜw」→父「奴隷の父です」「え？」 | J371: https://www.youtube.com/watch?v=qn_AexjYLOo | K371: 2 年前 | L371: 100000 | M371: 【スカッとする話】超高級車を10台持つ金持ち自慢の婚約者の実家へ結婚挨拶に行くと、義母「私の奴隷さんいらっしゃいw」婚約者「貧乏な顔だろ？親の顔が見たいぜw」→父「奴隷の父です」「え？」
A372: 371 | B372: 静かな夜の物語、雨の中の記憶 | D372: https://www.youtube.com/watch?v=-9_qZv_QZQU | E372: 朗読/同形式 | F372: 1 | G372: 3 日前 | H372: 1 | I372: 【スカッとする話】私が役員報酬で家計を支えていると知らず夫と引っ越した連れ子の娘。連れ子「家政婦で良いなら住所教えるよw」私「では無職のクズ夫とは離婚で」夫「おもしれぇw」結果w | J372: https://www.youtube.com/watch?v=FeWYwxOB9EE | K372: 2 年前 | L372: 89000 | M372: 【スカッとする話】私が役員報酬で家計を支えていると知らず夫と引っ越した連れ子の娘。連れ子「家政婦で良いなら住所教えるよw」私「では無職のクズ夫とは離婚で」夫「おもしれぇw」結果w
A373: 372 | B373: 静かな夜の物語、雨の中の記憶 | D373: https://www.youtube.com/watch?v=FtkiCIJXyhg | E373: 朗読/同形式 | F373: 1 | G373: 2 日前 | H373: 0 | I373: 【スカッとする話】夫「今日から長男夫婦と孫と同居する！」長男嫁「ババァは家から出てけw」私（私が生活費33万払ってるのに）翌日、業者に電話して家具家電を回収→1億の高級タワマンに引越した結果w | J373: https://www.youtube.com/watch?v=M2hAF-Scj3M | K373: 2 年前 | L373: 160000 | M373: 【スカッとする話】夫「今日から長男夫婦と孫と同居する！」長男嫁「ババァは家から出てけw」私（私が生活費33万払ってるのに）翌日、業者に電話して家具家電を回収→1億の高級タワマンに引越した結果w
A374: 373 | B374: 静かな夜の物語、雨の中の記憶 | D374: https://www.youtube.com/watch?v=E7LaAMY2_Rw | E374: 朗読/同形式 | F374: 0.99 | G374: 12 日前 | H374: 1 | I374: 【スカッとする話】車椅子の母と散歩中、9年前に私を捨てた夫と再会。元夫「お前の母親歩けないのか？娘に似て不良品だなw」直後、私の旦那を見た元夫は震えだ | J374: https://www.youtube.com/watch?v=BucW38NrA9o | K374: 2 年前 | L374: 74000 | M374: 【スカッとする話】車椅子の母と散歩中、9年前に私を捨てた夫と再会。元夫「お前の母親歩けないのか？娘に似て不良品だなw」直後、私の旦那を見た元夫は震えだしw
... A377: 376 | B377: 静かな夜の物語、雨の中の記憶 | D377: https://www.youtube.com/watch?v=hKi2-HjQLs0 | E377: 朗読/同形式 | F377: 0.97 | G377: 2 週間前 | H377: 0 | I377: 【スカッと総集編】家事、育児、介護、パートをこなし15年。私「もう限界。実家に帰ります」夫「はぁ？ガキの面倒は？飯は？帰るなら離婚届書いてけ！」→速提出して両親に離婚報告すると涙を流した夫が家に来て… | J377: https://www.youtube.com/watch?v=GmBCty_zSQs | K377: 1 年前 | L377: 41000 | M377: 【スカッとする話】家事、育児、介護、パートをこなし15年。私「もう限界。実家に帰ります」夫「はぁ？ガキの面倒は？飯は？帰るなら離婚届書いてけ！」→速提出して両親に離婚報告すると涙を流した夫が…
A378: 377 | B378: Noah Qumi | C378: https://www.youtube.com/channel/UCH4l3-r5NgR2RlKdoRwfzAw | D378: https://www.youtube.com/watch?v=MHsVbMKecBY | E378: 朗読/同形式 | F378: 1 | G378: 7 日前 | H378: 0 | I378: 【スカッとする話】愛人に夫を奪われた私。2人「すまん、離婚してくれ…」離婚届が置かれた瞬間、即サインし夫を譲ると、相手弁護士がガタガタ震え出しw【朗読】【スカッと】 | J378: https://www.youtube.com/watch?v=blo_a56_T1U | K378: 2 か月前 | L378: 370000 | M378: 【スカッとする話】愛人に夫を奪われた私。2人「すまん、離婚してくれ…」離婚届が置かれた瞬間、即サインし夫を譲ると、相手弁護士がガタガタ震え出しw【朗読】【スカッと】
A379: 378 | B379: Noah Qumi | C379: https://www.youtube.com/channel/UCH4l3-r5NgR2RlKdoRwfzAw | D379: https://www.youtube.com/watch?v=0HyRkakDfNI | E379: 朗読/同形式 | F379: 1 | G379: 7 日前 | H379: 1 | I379: 【スカッとする話】母の手術費のためにバケモノ御曹司と婚約した私。父「すまんな…」結婚初日、別人の彼の姿に驚愕し…【朗読】【スカッと】 | J379: https://www.youtube.com/watch?v=2meTtNT2fJ8 | K379: 7 か月前 | L379: 250000 | M379: 【スカッとする話】母の手術費のためにバケモノ御曹司と婚約した私。父「すまんな…」結婚初日、別人の彼の姿に驚愕し…【朗読】【スカッと】
A380: 379 | B380: Noah Qumi | C380: https://www.youtube.com/channel/UCH4l3-r5NgR2RlKdoRwfzAw | D380: https://www.youtube.com/watch?v=kwDoLkr5Sbk | E380: 朗読/同形式 | F380: 1 | G380: 10 日前 | H380: 0 | I380: 【スカッとする話】同窓会で結婚直前に私を捨てた夫と再会。夫「金持ちの社長令嬢と結婚したw俺だけ幸せでごめんなw」私「本当にそう思う？」真実を伝えると元夫が震え出し…【朗読】【スカッと】 | J380: https://www.youtube.com/watch?v=aCFKEISe330 | K380: 1 年前 | L380: 360000 | M380: 【スカッとする話】同窓会で結婚直前に私を捨てた夫と再会。夫「金持ちの社長令嬢と結婚したw俺だけ幸せでごめんなw」私「本当にそう思う？」真実を伝えると元夫が震え出し…【朗読】【スカッと】
A381: 380 | B381: Noah Qumi | C381: https://www.youtube.com/channel/UCH4l3-r5NgR2RlKdoRwfzAw | D381: https://www.youtube.com/watch?v=95_XVcEcx7c | E381: 朗読/同形式 | F381: 1 | G381: 11 日前 | H381: 0 | I381: 【スカッとする話】35歳で妊娠した私を捨て19歳の女子大生と再婚した学歴主義の夫。夫「高齢出産だとバカ生まれそうw」15年後、学校で元夫と遭遇すると息子を見た元夫は震えだし…【朗読】【スカッと】 | J381: https://www.youtube.com/watch?v=Q8wTXMZ6iys | K381: 1 年前 | L381: 140000 | M381: 【スカッとする話】35歳で妊娠した私を捨て19歳の女子大生と再婚した学歴主義の夫。夫「高齢出産だとバカ生まれそうw」15年後、学校で元夫と遭遇すると息子を見た元夫は震えだし…【朗読】【スカッと】
A382: 381 | B382: Noah Qumi | C382: https://www.youtube.com/channel/UCH4l3-r5NgR2RlKdoRwfzAw | D382: https://www.youtube.com/watch?v=Mrocl2zI9zA | E382: 朗読/同形式 | F382: 1 | G382: 8 日前 | H382: 0 | I382: 【スカッとする話】夫「限界だ…。離婚してくれ…。お前と老後は耐えられん…」私「はい離婚届。義父の介護任せるね」即離婚して姿を消すと夫から大量着信→私（あ、もうバレたかw）実は…【朗読】【スカッと】 | J382: https://www.youtube.com/watch?v=HTXg2kgO-aI | K382: 1 年前 | L382: 140000 | M382: 【スカッとする話】夫「限界だ…。離婚してくれ…。お前と老後は耐えられん…」私「はい離婚届。義父の介護任せるね」即離婚して姿を消すと夫から大量着信→私（あ、もうバレたかw）実は…【朗読】【スカッと】
A383: 382 | B383: Noah Qumi | C383: https://www.youtube.com/channel/UCH4l3-r5NgR2RlKdoRwfzAw | D383: https://www.youtube.com/watch?v=-pck5MfMrj4 | E383: 朗読/同形式 | F383: 1 | G383: 10 日前 | H383: 0 | I383: 【スカッとする話】亭主関白夫「明日から食費は月3000円！予算超えたら離婚だからな！」私「はーい、後悔しないでね？」夫「しねぇよw」1ヶ月後w【朗読】【スカッと】 | J383: https://www.youtube.com/watch?v=PN93A1chfSU | K383: 1 年前 | L383: 170000 | M383: 【スカッとする話】亭主関白夫「明日から食費は月3000円！予算超えたら離婚だからな！」私「はーい、後悔しないでね？」夫「しねぇよw」1ヶ月後w【朗読】【スカッと】
A384: 383 | B384: Noah Qumi | C384: https://www.youtube.com/channel/UCH4l3-r5NgR2RlKdoRwfzAw | D384: https://www.youtube.com/watch?v=_KqB9ErM7HI | E384: 朗読/同形式 | F384: 1 | G384: 7 日前 | H384: 0 | I384: 【スカッとする話】月9万円で年金暮らしの私に長男嫁「頼られるの嫌だし絶縁でw」長男「今後一切関わらないからw」私「本当にいいのね？」長男嫁「え？」絶縁して2ヶ月後…w | J384: https://www.youtube.com/watch?v=_m8w5ILU3u0 | K384: 1 年前 | L384: 330000 | M384: 【スカッとする話】月9万円で年金暮らしの私に長男嫁「頼られるの嫌だし絶縁でw」長男「今後一切関わらないからw」私「本当にいいのね？」長男嫁「え？」絶縁して2ヶ月後…w
A385: 384 | B385: Noah Qumi | C385: https://www.youtube.com/channel/UCH4l3-r5NgR2RlKdoRwfzAw | D385: https://www.youtube.com/watch?v=zBTIx1Hbi6c | E385: 朗読/同形式 | F385: 0.95 | G385: 11 日前 | H385: 0 | I385: 【スカッとする話】18年親代わりに私を育ててくれた兄とエリート銀行員の婚約者との結婚挨拶に行くと、義母「貧乏人とは婚約破棄でw」直後、キレた兄が銀行へ連絡 | J385: https://www.youtube.com/watch?v=Hj7yYfAf4ow | K385: 1 年前 | L385: 160000 | M385: 【スカッとする話】18年親代わりに私を育ててくれた兄とエリート銀行員の婚約者との結婚挨拶に行くと、義母「貧乏人とは婚約破棄でw」直後、キレた兄が銀行へ連絡
A386: 385 | B386: Noah Qumi | C386: https://www.youtube.com/channel/UCH4l3-r5NgR2RlKdoRwfzAw | D386: https://www.youtube.com/watch?v=FNOxd1vSuQs | E386: 朗読/同形式 | F386: 0.95 | G386: 10 日前 | H386: 0 | I386: 【スカッとする話】余命3ヶ月と診断された夫「俺の貯金も家も車もすべて愛人に渡す。お前に渡す金は無いw」翌朝、荷物をまとめ出ていくと、真実を知った夫から鬼電がw | J386: https://www.youtube.com/watch?v=JuCiUOLk2v4 | K386: 1 年前 | L386: 160000 | M386: 【スカッとする話】余命3ヶ月と診断された夫「俺の貯金も家も車もすべて愛人に渡す。お前に渡す金は無いw」翌朝、荷物をまとめ出ていくと、真実を知った夫から鬼電がw
A387: 386 | B387: Noah Qumi | C387: https://www.youtube.com/channel/UCH4l3-r5NgR2RlKdoRwfzAw | D387: https://www.youtube.com/watch?v=_KqB9ErM7HI | E387: 朗読/同形式 | F387: 0.9 | G387: 7 日前 | H387: 0 | I387: 【スカッとする話】月9万円で年金暮らしの私に長男嫁「頼られるの嫌だし絶縁でw」長男「今後一切関わらないからw」私「本当にいいのね？」長男嫁「え？」絶縁して2ヶ月後…w | J387: https://www.youtube.com/watch?v=2jJCIGafP3k | K387: 1 年前 | L387: 87000 | M387: 【スカッと総集編】月9万円で年金暮らしの私に長男嫁「頼られるの嫌だし絶縁w」長男「今後一切関わらないw」私「本当にいいのね？」長男嫁「え？」【朗読】【スカッと】【スカッとする話】
A388: 387 | B388: Noah Qumi | C388: https://www.youtube.com/channel/UCH4l3-r5NgR2RlKdoRwfzAw | D388: https://www.youtube.com/watch?v=s22fDmWOq9s | E388: 朗読/同形式 | F388: 0.89 | G388: 8 日前 | H388: 0 | I388: 【スカッとする話】夫を亡くし1Kのアパートで年金暮らしの私を見下す長男嫁「孤独で極貧人生惨めですねw」1ヶ月後、娘夫婦と一軒家建て同居する事になり新居に長男夫婦も招くと…【朗読】【スカッと | J388: https://www.youtube.com/watch?v=FBxAecHRyv4 | K388: 1 年前 | L388: 270000 | M388: 【スカッとする話】夫を亡くし1Kのアパートで年金暮らしの私を見下す長男嫁「孤独で極貧人生惨めですねw」1ヶ月後、娘夫婦と一軒家建て同居する事になり新居に長男夫婦も招くと…【朗読】【スカッと】
A389: 388 | B389: Noah Qumi | C389: https://www.youtube.com/channel/UCH4l3-r5NgR2RlKdoRwfzAw | D389: https://www.youtube.com/watch?v=rQ-I-Ahmn_k | E389: 朗読/同形式 | F389: 0.87 | G389: 10 日前 | H389: 0 | I389: 【スカッとする話】入院中、義父から突然怒りの電話。義父「夫が入院中なのに嫁のお前が何遊んでるんだ！」私「え？入院してるのは私ですよ？」義父「え？」実は…【朗読】【スカッと】 | J389: https://www.youtube.com/watch?v=aaaPLdvdBeU | K389: 10 か月前 | L389: 150000 | M389: 【スカッとする話】入院中、義父から突然怒りの電話。義父「夫が入院中なのに嫁のお前が何遊んでるんだ！」私「え？入院してるのは私ですよ？」義父「え？」実は…【朗読】【スカッと】
... A609: 608 | B609: 痛快!!怒りのスカッとチャンネル【スカッと朗読】 | C609: https://www.youtube.com/channel/UC96mO8pXAaiP70V7KUjVHqg | D609: https://www.youtube.com/watch?v=DgbiU0EwjXk | E609: 朗読/同形式 | F609: 0.96 | G609: 1 年前 | H609: 27 | I609: 【スカッと】母の葬儀中に夫から電話「親戚達の集まりなのにサボるな!!親の葬儀とか知るか今すぐ来い」私「分かりました」喪服のまま駆け付け吊し上げた結果w【修羅場】 | J609: https://www.youtube.com/watch?v=wdxUcG1tem8 | K609: 2 年前 | L609: 200000 | M609: 【スカッとする話】母の葬儀中に夫から電話「親戚の集まりなのにサボるな！親の葬儀とか知るか今すぐ来い」私「分かりました」喪服のまま駆け付けた結果ｗ
A610: 609 | B610: 雨の中の記憶、雨の中の記憶 | D610: https://www.youtube.com/watch?v=D7M2p9ALM9c | E610: 朗読/同形式 | F610: 1 | G610: 3 週間前 | H610: 19 | I610: 【スカッと総集編】私が総資産が28億の社長令嬢と知らず私を裏切り職場の美人同僚と再婚した夫「美人同僚と再婚するから離婚w」同僚「子供は1人で頑張れｗ」私「はーい」1ヶ月後、夫達から鬼電がw | J610: https://www.youtube.com/watch?v=KKEWop4fNrk | K610: 1 年前 | L610: 66000 | M610: 【スカッと総集編】私が総資産が28億の社長令嬢と知らず私を裏切り職場の美人同僚と再婚した夫「美人同僚と再婚するから離婚w」同僚「子供は1人で頑張れｗ」私「はーい」1ヶ月後、夫達から鬼電がw
A611: 610 | B611: 雨の中の記憶、雨の中の記憶 | D611: https://www.youtube.com/watch?v=jzQ7tWnYBb4 | E611: 朗読/同形式 | F611: 1 | G611: 3 週間前 | H611: 9 | I611: 【スカッと総集編】入院した私に大量の塩をぶっかける長男嫁「このままあの世にいけwババァがいなくて最高w」キレた私は長男嫁への仕送りを停止→本当に帰らぬ人となった結果w | J611: https://www.youtube.com/watch?v=c2AdQUXc1Hg | K611: 1 年前 | L611: 59000 | M611: 【スカッと総集編】入院した私に大量の塩をぶっかける長男嫁「このままあの世にいけwババァがいなくて最高w」キレた私は長男嫁への仕送りを停止→本当に帰らぬ人となった結果w
A612: 611 | B612: 雨の中の記憶、雨の中の記憶 | D612: https://www.youtube.com/watch?v=91jZsqJGQeo | E612: 朗読/同形式 | F612: 1 | G612: 2 週間前 | H612: 6 | I612: 【スカッとする話】義家族と高級料亭へ行くと義母「あんたのカードで払ったよw 支払い30万円よろしくねw」 私「え?私カード持ってないけど...」義母「は?」→結果 | J612: https://www.youtube.com/watch?v=u2ktHPgl-Nc | K612: 1 年前 | L612: 39000 | M612: 【スカッとする話】義家族と高級料亭へ行くと義母「あんたのカードで払ったよw支払い30万円よろしくねw」私「え？私カード持ってないけど…」義母「は？」結果w
A613: 612 | B613: 雨の中の記憶、雨の中の記憶 | D613: https://www.youtube.com/watch?v=F0XGuiwOK4Y | E613: 朗読/同形式 | F613: 0.98 | G613: 1 か月前 | H613: 5 | I613: 資産3億を築いた長男が他界すると長男嫁「夫の遺産は全て私のものw」 孫「ババァには1円もあげないw」1ヶ月後、血相変えた嫁から大量着信嫁「あ、あの遺産って...」→結果w W | J613: https://www.youtube.com/watch?v=IaSMuG9SQHg | K613: 1 年前 | L613: 33000 | M613: 【スカッとする話】資産3億を築いた長男が他界すると長男嫁「夫の遺産は全て私のものw」孫「ババァには1円もあげないw」1ヶ月後、血相変えた嫁から大量着信→嫁「あ、あの遺産って」
A614: 613 | B614: 雨の中の記憶、雨の中の記憶 | D614: https://www.youtube.com/watch?v=6r9nopea82s | E614: 朗読/同形式 | F614: 0.98 | G614: 12 日前 | H614: 151 | I614: 【スカッとする話】帰省すると妹が全身の毛を剃られ赤ん坊を抱いて泣いていた... 私「今どこ?」母「家族で旅行中w」 私「は?」家を売り払い更地にし帰る場所を消してやった結果w | J614: https://www.youtube.com/watch?v=ic9sL-ViLjw | K614: 1 年前 | L614: 44000 | M614: 【スカッと総集編】実家に帰省すると妹が全身の毛を剃られ赤ん坊を抱いて泣いていた…私「今どこ？」母「家族で旅行中w」私「は？」家を売り払い更地にし帰る場所を消してやった結果w
A615: 614 | B615: 雨の中の記憶、雨の中の記憶 | D615: https://www.youtube.com/watch?v=iLduhZdDq8c | E615: 朗読/同形式 | F615: 0.97 | G615: 3 週間前 | H615: 0 | I615: 【スカッとする話】7000万で新築を購入した途端愛人・隠し子・義母を連れ帰宅した夫夫「俺たちが住むから離婚して失せろw」私「え?ここ私の家じゃないよ?」夫・愛人・義母「え?」→結果w W | J615: https://www.youtube.com/watch?v=D66705hwMgg | K615: 1 年前 | L615: 52000 | M615: 【スカッとする話】7000万で新築を購入した途端、愛人・隠し子・義母を連れ帰宅した夫「俺たちが住むから離婚して失せろw」私「え？ここ私の家じゃないよ？」夫・愛人・義母「え？」
A616: 615 | B616: 雨の中の記憶、雨の中の記憶 | D616: https://www.youtube.com/watch?v=jicHDA2WT1I | E616: 朗読/同形式 | F616: 0.97 | G616: 7 日前 | H616: 0 | I616: 【スカッとする話】義家族と高級料亭へ行くと義母「あんたのカードで払ったよw 支払い30万円よろしくねw」 私「え?私カード持ってないけど･･･」 義母「は?」→結果w | J616: https://www.youtube.com/watch?v=u2ktHPgl-Nc | K616: 1 年前 | L616: 39000 | M616: 【スカッとする話】義家族と高級料亭へ行くと義母「あんたのカードで払ったよw支払い30万円よろしくねw」私「え？私カード持ってないけど…」義母「は？」結果w
A617: 616 | B617: 雨の中の記憶、雨の中の記憶 | D617: https://www.youtube.com/watch?v=wNk-zervUEE | E617: 朗読/同形式 | F617: 0.96 | G617: 1 か月前 | H617: 2 | I617: 突然、義妹夫婦を連れてきた義母義母「今日から皆で暮らすW」 義妹「文句あるなら出てってねw」夫「じゃ引っ越すか」私「お達者で」義母・義妹「え?」→結果w | J617: https://www.youtube.com/watch?v=KKvSV1JKlt0 | K617: 1 年前 | L617: 29000 | M617: 【スカッとする話】突然、義妹夫婦を連れてきた義母「今日から皆で暮らすｗ」義妹「文句あるなら出てってねｗ」夫「じゃ引っ越すか」私「お達者で」義母・義妹「え？」
A618: 617 | B618: 雨の中の記憶、雨の中の記憶 | D618: https://www.youtube.com/watch?v=KIqtDF7vbMA | E618: 朗読/同形式 | F618: 0.96 | G618: 1 か月前 | H618: 12 | I618: 医者一族である婚約者の親族の集まりで私だけバナナ1本婚約者「他人だから仕方ないだろw」 彼母「それ食べたら帰ってねw」私「ではアンタらの病院潰すわ」 | J618: https://www.youtube.com/watch?v=J3z5MRu6918 | K618: 1 年前 | L618: 23000 | M618: 【スカッとする話】医者一族である婚約者の親族の集まりに行くと私だけバナナ1本。婚約者「他人だから仕方ないだろw」彼母「それ食べたら帰ってねw」私「ではアンタらの病院潰すわ」
A619: 618 | B619: 雨の中の記憶、雨の中の記憶 | D619: https://www.youtube.com/watch?v=-edR9_-olnY | E619: 朗読/同形式 | F619: 0.95 | G619: 5 日前 | H619: 0 | I619: 【スカッとする話】生まれた息子が夫に似てない夫「浮気してたな?離婚だ!」 義父「今すぐ出てけアバズレが!」 10年後、夫と義父と遭遇し2人は発狂 →だって息子は... | J619: https://www.youtube.com/watch?v=DeIUkxQ3Yjg | K619: 1 年前 | L619: 10000 | M619: 【スカッとする話】生まれた息子が夫に似てない。夫「浮気してたな？離婚だ！」義父「今すぐ出てけアバズレが」10年後、夫と義父と遭遇すると2人が発狂。だって息子は…
A620: 619 | B620: 雨の中の記憶、雨の中の記憶 | D620: https://www.youtube.com/watch?v=plFEwAiZdeA | E620: 朗読/同形式 | F620: 0.93 | G620: 11 日前 | H620: 18 | I620: 【スカッとする話】義両親の居酒屋を手伝って10年義母「私たち引退することにしたのw」 義父「店は長男嫁に任せることにしたw」私「ご自由に。私今日で辞めるので」 義両親「え?」→結果w | J620: https://www.youtube.com/watch?v=F1mnzuaYuqM | K620: 1 年前 | L620: 66000 | M620: 【スカッとする話】義両親の居酒屋を手伝って10年の私に義母「私達引退することにしたのw」義父「店は長男嫁に任せることにしたよw」私「ご自由に。私今日で辞めるので」義両親「え？」
A621: 620 | B621: スカっとゼミ!! | C621: https://www.youtube.com/channel/UC9Hd679L2faWD0aJQHeAlrA | D621: https://www.youtube.com/watch?v=tc-9FGKPWTs | E621: 朗読/同形式 | F621: 0.96 | G621: 1 年前 | H621: 7509 | I621: 【スカッとする話】単身赴任中の私に夫から速達で離婚届…夫「息子も離婚して欲しいってw」私（やっと自由になれるw）大喜びして離婚届を提出し家を売り払い更地にし携帯も解約するとw | J621: https://www.youtube.com/watch?v=VrctjOjY0Ts | K621: 1 年前 | L621: 88000 | M621: 【スカッとする話】単身赴任中の私に夫から速達で離婚届…夫「息子も離婚して欲しいってw」私（やっと自由になれるw）大喜びして離婚届を提出し家を売り払い更地にするとw
A622: 621 | B622: スカっとゼミ!! | C622: https://www.youtube.com/channel/UC9Hd679L2faWD0aJQHeAlrA | D622: https://www.youtube.com/watch?v=DKzM1r5EGpw | E622: 朗読/同形式 | F622: 0.83 | G622: 2 年前 | H622: 112 | I622: 【スカッとする話】母子家庭で育てた娘の結婚式へ行くと私の席が無い…義家族「貧乏人の席はないわよw」娘「帰ろっか..」私「うん…」義家族は全てを失う結果にw【修羅場】【厳選総集編】 | J622: https://www.youtube.com/watch?v=6UWe8WooXpM | K622: 2 年前 | L622: 100000 | M622: 【スカッとする話】母子家庭で育てた長男の結婚式へ行くと私の席が無い...姑「貧乏人の席はありませんw」長男「帰ろっか..」私「うん...」義家族は全てを失う結果にw
A623: 622 | B623: スカっとゼミ!! | C623: https://www.youtube.com/channel/UC9Hd679L2faWD0aJQHeAlrA | D623: https://www.youtube.com/watch?v=8p3vkkh73Zo | E623: 朗読/同形式 | F623: 0.81 | G623: 1 年前 | H623: 174305 | I623: 【スカッとする話】風呂も寝室も完全別で夜の行為も一切ない私が緊急入院し手術する事に→医師「い…一体これはなんなんだ！」私の体を見た医師が震えだし…後日、顔面蒼白の夫が【修羅場】【朗読】 | J623: https://www.youtube.com/watch?v=IIMdWb_44ts | K623: 2 年前 | L623: 370000 | M623: 【スカッとする話】風呂も寝室も完全別で夜の行為も一切しない夫が緊急入院し手術する事に→医師「い、一体なんだこれは…」夫の体を見た医師が震え出し...
A624: 623 | B624: スカっとゼミ!! | C624: https://www.youtube.com/channel/UC9Hd679L2faWD0aJQHeAlrA | D624: https://www.youtube.com/watch?v=jjdUMvdaKxU | E624: 朗読/同形式 | F624: 0.81 | G624: 3 年前 | H624: 6867 | I624: 【スカッとする話】私名義のマンションとは知らずに私を追い出す息子嫁「義母の全てが気に入らない！家族だけで暮らすから出て行け！」稼ぎ頭の私「わかりました…」→即絶縁して私物を全て回収。家賃だけ残した結果 | J624: https://www.youtube.com/watch?v=k11Y7DA0DRk | K624: 3 年前 | L624: 120000 | M624: 【スカッとする話】私名義のマンションとは知らず私を追い出す長男嫁「お義母さんの全部が気に入らない！家族だけで暮らすから出てけ！」稼ぎ頭の私「じゃあ出ていきます」家の私物を全て回収し、家賃だけ残した結果
A625: 624 | B625: スカっとゼミ!! | C625: https://www.youtube.com/channel/UC9Hd679L2faWD0aJQHeAlrA | D625: https://www.youtube.com/watch?v=styiBssopwY | E625: 朗読/同形式 | F625: 0.79 | G625: 3 年前 | H625: 85009 | I625: 【スカッとする話】母の遺産をあてにはしゃぐ弟嫁。母が危篤状態になると枕元で「これでババアの遺産は私たちの物ｗ」高笑いをして病院を去った次の瞬間、寝たきりの母が起き上がり満面の笑みで…【修羅場】 | J625: https://www.youtube.com/watch?v=yrrQ18CMZjQ | K625: 3 年前 | L625: 21000 | M625: 【スカッとする話】私の遺産をあてにする長男夫婦。私が危篤状態になると枕元で長男嫁「これでババアの遺産は私たちの物ｗ」高笑いをして病室を去った次の瞬間、寝たきりの私が笑顔で起き上がり… 【修羅場】
A626: 625 | B626: スカっとゼミ!! | C626: https://www.youtube.com/channel/UC9Hd679L2faWD0aJQHeAlrA | D626: https://www.youtube.com/watch?v=kUHjfkX7-Zg | E626: 朗読/同形式 | F626: 0.77 | G626: 2 年前 | H626: 8229 | I626: 【スカッと☆厳選7本総集編】母の遺産をあてにはしゃぐ弟嫁。母が危篤状態になると枕元で「これでババアの遺産は私たちの物ｗ」高笑いをして病院を去った次の瞬間、寝たきりの母が起き上がり満面の笑みで…【修羅場 | J626: https://www.youtube.com/watch?v=yrrQ18CMZjQ | K626: 3 年前 | L626: 21000 | M626: 【スカッとする話】私の遺産をあてにする長男夫婦。私が危篤状態になると枕元で長男嫁「これでババアの遺産は私たちの物ｗ」高笑いをして病室を去った次の瞬間、寝たきりの私が笑顔で起き上がり… 【修羅場】
A627: 626 | B627: スカっとゼミ!! | C627: https://www.youtube.com/channel/UC9Hd679L2faWD0aJQHeAlrA | D627: https://www.youtube.com/watch?v=e-Biz2n8D-8 | E627: 朗読/同形式 | F627: 0.76 | G627: 3 年前 | H627: 200958 | I627: 【スカッとする話】私「ボーナスとピアノが消えた！」夫「出産祝いで妹に渡した。俺の稼いだ金だし文句ないだろ」私は離婚届を即提出→後日、大慌ての嫁いびり義妹から電話。私「アンタ誰？」義妹「え？」【修羅場】 | J627: https://www.youtube.com/watch?v=kiUx3a37Lv4 | K627: 3 年前 | L627: 90000 | M627: 【スカッとする話】私「ボーナスとピアノが消えた！」夫「出産祝いで長男嫁に渡した。俺の稼いだ金だし文句ないだろ」私は離婚届を即提出→後日、パニックの長男嫁から鬼電→私「あんた誰？」長男嫁「え？」【修羅場
A628: 627 | B628: スカっとゼミ!! | C628: https://www.youtube.com/channel/UC9Hd679L2faWD0aJQHeAlrA | D628: https://www.youtube.com/watch?v=JwU2_PZrMD8 | E628: 朗読/同形式 | F628: 0.74 | G628: 3 年前 | H628: 47622 | I628: 【スカッとする話】継母の私を結婚式に招待せず住所すら教えない娘「偽物の母親に個人情報は教えませんｗ」私「そう、それは残念だわ…」→本物の娘に財産全てを譲った結果ｗｗｗ【修羅場】 | J628: https://www.youtube.com/watch?v=mOy5nZK4Phw | K628: 3 年前 | L628: 73000 | M628: 【スカッとする話】義母の私だけ新築祝いに招待せず引っ越し先すら教えない長男嫁「偽物の母親に個人情報は教えませんw」私「そう、残念ね…」→本物の娘に財産を全て譲った結果w【修羅場】
A629: 628 | B629: スカっとゼミ!! | C629: https://www.youtube.com/channel/UC9Hd679L2faWD0aJQHeAlrA | D629: https://www.youtube.com/watch?v=G-PrX312MyU | E629: 朗読/同形式 | F629: 0.73 | G629: 1 年前 | H629: 2459 | I629: 【スカッと】親戚の集まりで主婦の私を見下す長男嫁「専業主婦って寄生虫だよねｗ」夫「俺らがいないと終わりだもんな」息子「間違いないｗ」私「じゃ嫁も姑も母も仕事も全部やめるね」一同「え？仕事？」【修羅場】 | J629: https://www.youtube.com/watch?v=VD6RZRSRF7s | K629: 2 年前 | L629: 76000 | M629: 【スカッとする話】親族の集まりで主婦の私を見下す娘「専業主婦って寄生虫だよねw」夫「俺がいないと終わりだなw」私「じゃあ嫁も母親も辞めるね」夫・娘「え？」結果w【スカッと】【朗読】【修羅場】
A630: 629 | B630: スカっとゼミ!! | C630: https://www.youtube.com/channel/UC9Hd679L2faWD0aJQHeAlrA | D630: https://www.youtube.com/watch?v=KRPAry0foPU | E630: 朗読/同形式 | F630: 0.72 | G630: 3 年前 | H630: 349452 | I630: 【スカッとする話】代表弁護士の兄が亡くなり葬儀後、義姉「遺産8000万とこの家は嫁である私が相続しますのｗ」兄の部下一同が大爆笑ｗ→だって義姉は…【修羅場】 | J630: https://www.youtube.com/watch?v=dLHFLGIOs2s | K630: 3 年前 | L630: 12000 | M630: 【スカッとする話】弁護士の長男が亡くなり葬儀後、長男嫁「遺産8000万とこの家は嫁である私が相続しますｗ」長男の部下一同が大爆笑ｗ→だって長男は…【修羅場】
A631: 630 | B631: スカッと成敗ストーリー | C631: https://www.youtube.com/channel/UC1iIGo491nSYyJ_AsgmPzyw | D631: https://www.youtube.com/watch?v=cmr_Wm_l0r0 | E631: 朗読/同形式 | F631: 1 | G631: 2 か月前 | H631: 0 | I631: 【スカッとする話】私がグループ13社の社長と知らず、母の葬儀後に銀行員の夫「相続少ねぇなw離婚でw」即離婚届を提出し夫の銀行へ→私「700億の法人口座は解約で」 | J631: https://www.youtube.com/watch?v=NskvXTGiyMY | K631: 1 年前 | L631: 34000 | M631: 【スカッとする話】私がグループ13社の社長と知らず、母の葬儀後に銀行員の夫「相続少ねぇなw離婚でw」即離婚届を提出し夫の銀行へ→私「700億の法人口座は解約で」
A632: 631 | B632: スカッと成敗ストーリー | C632: https://www.youtube.com/channel/UC1iIGo491nSYyJ_AsgmPzyw | D632: https://www.youtube.com/watch?v=SrlJ46l-aQs | E632: 朗読/同形式 | F632: 1 | G632: 2 か月前 | H632: 0 | I632: 【スカッとする話】長男が双子の娘を残して他界。長男嫁「発達障害のガキは中卒の貧乏ババァに譲ってあげるw」私「では私が育てます…」10年後、まさかの展開に | J632: https://www.youtube.com/watch?v=3v1qqv9z0yE | K632: 2 年前 | L632: 35000 | M632: 【スカッとする話】長男が双子の娘を残して他界。長男嫁「発達障害のガキは中卒の貧乏ババァに譲ってあげるw」私「では私が育てます…」10年後、まさかの展開にw
... A1028: 1027 | B1028: 雨の中の記憶 | C1028: https://www.youtube.com/channel/UCJ_Zte-T_DYEEvf5DqPciGg | D1028: https://www.youtube.com/watch?v=-olARGeQJ6Y | E1028: 朗読/同形式 | F1028: 0.94 | G1028: 1 か月前 | H1028: 4 | I1028: 母子家庭で育てた息子の結婚挨拶で私たちだけ納豆ご飯だった... 義父「貧乏人はそれ好きだろw」 3秒後、婚約者が私を見て震え出し義家族は全てを失う結果にw | J1028: https://www.youtube.com/watch?v=nShlR1YbtJs | K1028: 1 年前 | L1028: 55000 | M1028: 【スカッとする話】母子家庭で育てた息子の結婚挨拶へ行くと私たちだけ納豆ご飯…義父「貧乏人はそれ好きだろw」3秒後、婚約者が私を見て震え出し…義家族は全てを失う結果にw
A1029: 1028 | B1029: 雨の中の記憶、静かな心の記録 | D1029: https://www.youtube.com/watch?v=WfmGCr48Es4 | E1029: 朗読/同形式 | F1029: 1 | G1029: 10 日前 | H1029: 0 | I1029: 【スカッと総集編】私が家族全員を養ってたと知らず新築に引越す義母「アンタの全てが気に入らないw家族だけで暮らすから消えろw」 即離婚して全名義を夫に変更→半狂乱の義母から鬼電が | J1029: https://www.youtube.com/watch?v=29F5nZ8UXYQ | K1029: 1 年前 | L1029: 96000 | M1029: 【スカッと総集編】私が家族全員を養ってたと知らず新築に引越す義母「アンタの全てが気に入らないw家族だけで暮らすから消えろw」 即離婚して全名義を夫に変更→半狂乱の義母から鬼電がw
A1030: 1029 | B1030: 雨の中の記憶、静かな心の記録 | D1030: https://www.youtube.com/watch?v=JFWqw8vLobc | E1030: 朗読/同形式 | F1030: 1 | G1030: 11 日前 | H1030: 1 | I1030: 【スカッと総集編】私が総資産が28億の社長令嬢と知らず私を裏切り職場の美人同僚と再婚した夫「美人同僚と再婚するから離婚w」同僚「子供は1人で頑張れｗ」私「はーい」1ヶ月後、夫達から鬼電が | J1030: https://www.youtube.com/watch?v=KKEWop4fNrk | K1030: 1 年前 | L1030: 66000 | M1030: 【スカッと総集編】私が総資産が28億の社長令嬢と知らず私を裏切り職場の美人同僚と再婚した夫「美人同僚と再婚するから離婚w」同僚「子供は1人で頑張れｗ」私「はーい」1ヶ月後、夫達から鬼電がw
A1031: 1030 | B1031: 雨の中の記憶、静かな心の記録 | D1031: https://www.youtube.com/watch?v=VMGI0GJDgqA | E1031: 朗読/同形式 | F1031: 1 | G1031: 12 日前 | H1031: 0 | I1031: 【スカッと総集編】入院した私に大量の塩をぶっかける長男嫁「このままあの世にいけwババァがいなくて最高w」キレた私は長男嫁への仕送りを停止→本当に帰らぬ人となった結果w | J1031: https://www.youtube.com/watch?v=c2AdQUXc1Hg | K1031: 1 年前 | L1031: 59000 | M1031: 【スカッと総集編】入院した私に大量の塩をぶっかける長男嫁「このままあの世にいけwババァがいなくて最高w」キレた私は長男嫁への仕送りを停止→本当に帰らぬ人となった結果w
A1032: 1031 | B1032: 雨の中の記憶、静かな心の記録 | D1032: https://www.youtube.com/watch?v=KLlUmrWBL2c | E1032: 朗読/同形式 | F1032: 0.98 | G1032: 13 日前 | H1032: 0 | I1032: 【スカッとする話】7000万で新築を購入した途端愛人・隠し子・義母を連れ帰宅した夫夫「俺たちが住むから離婚して失せろw」 私「え?ここ私の家じゃないよ?」夫・愛人・義母「え?」→結果w | J1032: https://www.youtube.com/watch?v=D66705hwMgg | K1032: 1 年前 | L1032: 52000 | M1032: 【スカッとする話】7000万で新築を購入した途端、愛人・隠し子・義母を連れ帰宅した夫「俺たちが住むから離婚して失せろw」私「え？ここ私の家じゃないよ？」夫・愛人・義母「え？」
A1033: 1032 | B1033: 雨の中の記憶、静かな心の記録 | D1033: https://www.youtube.com/watch?v=6iZ3hygGdSQ | E1033: 朗読/同形式 | F1033: 0.96 | G1033: 2 日前 | H1033: 0 | I1033: 【スカッとする話】突然、義妹夫婦を連れてきた義母義母「今日から皆で暮らすW」 義妹「文句あるなら出てってねw」 夫「じゃ引っ越すか」私「お達者で」義母・義妹「え?」→結果w | J1033: https://www.youtube.com/watch?v=KKvSV1JKlt0 | K1033: 1 年前 | L1033: 29000 | M1033: 【スカッとする話】突然、義妹夫婦を連れてきた義母「今日から皆で暮らすｗ」義妹「文句あるなら出てってねｗ」夫「じゃ引っ越すか」私「お達者で」義母・義妹「え？」
A1034: 1033 | B1034: 雨の中の記憶、静かな心の記録 | D1034: https://www.youtube.com/watch?v=UGDdKlExhB4 | E1034: 朗読/同形式 | F1034: 0.96 | G1034: 3 週間前 | H1034: 2 | I1034: 【スカッとする話】医者一族である婚約者の親族の集まりで私だけバナナ1本婚約者「他人だから仕方ないだろw」 彼母「それ食べたら帰ってねw」私「ではアンタらの病院潰すわ」 | J1034: https://www.youtube.com/watch?v=J3z5MRu6918 | K1034: 1 年前 | L1034: 23000 | M1034: 【スカッとする話】医者一族である婚約者の親族の集まりに行くと私だけバナナ1本。婚約者「他人だから仕方ないだろw」彼母「それ食べたら帰ってねw」私「ではアンタらの病院潰すわ」
A1035: 1034 | B1035: 雨の中の記憶、静かな心の記録 | D1035: https://www.youtube.com/watch?v=W_o79vrL1P0 | E1035: 朗読/同形式 | F1035: 0.93 | G1035: 1 日前 | H1035: 0 | I1035: 【スカッとする話】義両親の居酒屋を手伝って10年義母「私たち引退することにしたのw」 義父「店は長男嫁に任せることにしたw」 私「ご自由に。私今日で辞めるので」 義両親「え?」→結果w | J1035: https://www.youtube.com/watch?v=F1mnzuaYuqM | K1035: 1 年前 | L1035: 66000 | M1035: 【スカッとする話】義両親の居酒屋を手伝って10年の私に義母「私達引退することにしたのw」義父「店は長男嫁に任せることにしたよw」私「ご自由に。私今日で辞めるので」義両親「え？」
A1036: 1035 | B1036: 雨の中の記憶、静かな終わり | D1036: https://www.youtube.com/watch?v=fz0_OTDIvpQ | E1036: 朗読/同形式 | F1036: 0.99 | G1036: 1 か月前 | H1036: 6 | I1036: 新婚旅行中に私を雪山に置き去りにし夫「俺に意見するバカは帰ってくるなw 反省するまでそこにいろw」 私「さむい...置いてかないで...」翌日、夫がありえない姿で発見され... | J1036: https://www.youtube.com/watch?v=Bz-9j9l6enc | K1036: 1 年前 | L1036: 16000 | M1036: 【スカッとする話】新婚旅行中に私を雪山に置き去りにした夫「俺に意見するバカは帰ってくるなw反省するまでそこにいろw」私「さむい…置いてかないで…」翌日、夫がありえない姿で発見され…
A1037: 1036 | B1037: 雨の中の記憶、静かな終わり | D1037: https://www.youtube.com/watch?v=OQIXO7vA7VU | E1037: 朗読/同形式 | F1037: 0.99 | G1037: 1 日前 | H1037: 6 | I1037: 【スカッとする話】医師「奥様と娘さんが退院しましたお迎えをお願いいたします」 私「え?私に娘はいませんが?」直後、隣で聞いていた霊感のある母母「その電話、切ったらダメよ!」 | J1037: https://www.youtube.com/watch?v=2kqFB_BTrsg | K1037: 1 年前 | L1037: 26000 | M1037: 【スカッとする話】医師「奥様と娘さんが退院しました。お迎えお願いいたします」私「え？私に娘はいませんが？」直後、隣で聞いていた霊感のある母→母「その電話、切ったらダメよ！」
A1038: 1037 | B1038: 雨の中の記憶、静かな終わり | D1038: https://www.youtube.com/watch?v=ZRc8IkmBlhw | E1038: 朗読/同形式 | F1038: 0.99 | G1038: 7 日前 | H1038: 6 | I1038: 【スカッとする話】帰宅した私と息子に気づかない義両親義母「バカ嫁が産んだ息子もバカw」 義父「介護要員には良いだろw」 私「... 引越すわよ」息子「....うん」黙って豪邸に引越した結果w | J1038: https://www.youtube.com/watch?v=HeH8HawqG-A | K1038: 1 年前 | L1038: 52000 | M1038: 【スカッとする話】帰宅した私と息子に気づかない義両親。義母「バカ嫁が産んだ息子もバカｗ」義父「介護要員には良いだろｗ」私「…引っ越すわよ」息子「…うん」黙って豪邸に引越した結果ｗ
A1039: 1038 | B1039: 雨の中の記憶、静かな終わり | D1039: https://www.youtube.com/watch?v=wy9ND01qNfU | E1039: 朗読/同形式 | F1039: 0.98 | G1039: 2 日前 | H1039: 5 | I1039: 【スカッとする話】日曜の昼間に警察から突然の連絡警察「息子さんを万引きで逮捕した署までお越しください」 私「私の子供は娘ですが?」 娘の部屋へ向かうと... | J1039: https://www.youtube.com/watch?v=ujLRk5msBsw | K1039: 1 年前 | L1039: 18000 | M1039: 【スカッとする話】日曜の昼間に警察から突然の連絡。警察「息子さんを万引きで逮捕しました。署までお越しください」私「私の子供は娘ですが？」娘の部屋へ向かうと…
A1040: 1039 | B1040: 雨の中の記憶、静かな終わり | D1040: https://www.youtube.com/watch?v=8UMynxAnEK0 | E1040: 朗読/同形式 | F1040: 0.96 | G1040: 3 週間前 | H1040: 1 | I1040: 【スカッとする話】家のローンを毎月18万払う私に夫「家と財産は長男夫婦に譲った!」 長男「寄生虫の穀潰しは出てけw」 キレた私が全ての支払いを停止家も売り払い解体すると...W | J1040: https://www.youtube.com/watch?v=OGQqqSZ2qR0 | K1040: 1 年前 | L1040: 12000 | M1040: 【スカッとする話】家のローンを毎月18万払い続ける私に夫「家と財産は長男夫婦に譲った！」長男「寄生虫の穀潰しは出てけw」キレた私が全ての支払いを停止→家も売り払い解体すると…w
... A1049: 1048 | B1049: 静かな夜の物語、お話の部屋 | D1049: https://www.youtube.com/watch?v=hVeiYFB22h0 | E1049: 朗読/同形式 | F1049: 1 | G1049: 1 日前 | H1049: 3 | I1049: 【スカッとする話】夫の連れ子の結婚式に行くと、連れ子「アンタは戸籍上は他人w入るなら入場料300万w」夫「...帰ろう」私「はい」速攻で帰宅→3分後、連れ子から鬼電が | J1049: https://www.youtube.com/watch?v=TaT-Ww_mqxA | K1049: 2 年前 | L1049: 82000 | M1049: 【スカッとする話】夫の連れ子の結婚式に行くと、連れ子「アンタは戸籍上は他人w入るなら入場料300万w」夫「...帰ろう」私「はい」速攻で帰宅→3分後、連れ子から鬼電がw
A1050: 1049 | B1050: Avalynn Roderick | C1050: https://www.youtube.com/channel/UC2ALeyYaaWwXZhLpaAxCjDA | D1050: https://www.youtube.com/watch?v=Rzltaxpy2-U | E1050: 朗読/同形式 | F1050: 1 | G1050: 2 年前 | H1050: 2 | I1050: 【スカッとする話】家事に疲れて休憩していると妊娠9ヶ月の私を蹴ってきた夫「妊婦だからは甘え！家事サボるな！」無視した私に夫がビール瓶を投げるも当たって血まみれになったのは | J1050: https://www.youtube.com/watch?v=14YEbx6YYwk | K1050: 3 年前 | L1050: 42000 | M1050: 【スカッとする話】家事に疲れて休憩していると妊娠9ヶ月の私を蹴ってきた夫「妊婦だからは甘え！家事サボるな！」無視した私に夫がビール瓶を投げるも当たって血まみれになったのは...
A1051: 1050 | B1051: Avalynn Roderick | C1051: https://www.youtube.com/channel/UC2ALeyYaaWwXZhLpaAxCjDA | D1051: https://www.youtube.com/watch?v=0MrNXOwrCi4 | E1051: 朗読/同形式 | F1051: 1 | G1051: 2 年前 | H1051: 0 | I1051: 【スカッとする話】育休を終え職場に出社した私が新しい女部長に挨拶すると「あれ？清掃のおばちゃん？邪魔だから床掃除でもしてろw」直後、全社員がブルブル震え出し | J1051: https://www.youtube.com/watch?v=ZWebgSwWOzY | K1051: 3 年前 | L1051: 27000 | M1051: 【スカッとする話】育休を終え職場に出社した私が新しい女部長に挨拶すると「あれ？清掃のおばちゃん？邪魔だから床掃除でもしてろw」直後、全社員がブルブル震え出し...
A1052: 1051 | B1052: Avalynn Roderick | C1052: https://www.youtube.com/channel/UC2ALeyYaaWwXZhLpaAxCjDA | D1052: https://www.youtube.com/watch?v=PSSh0xDOrIo | E1052: 朗読/同形式 | F1052: 1 | G1052: 2 年前 | H1052: 0 | I1052: 【スカッとする話】夫が出張に行った途端、5歳の娘が突然私に衝撃発言「今のうちにパパと離婚して！」私「はい？」理由を聞いて私は慌てて警察に通報した結果 | J1052: https://www.youtube.com/watch?v=Gujab48F13I | K1052: 3 年前 | L1052: 52000 | M1052: 【スカッとする話】夫が出張に行った途端、5歳の娘が突然私に衝撃発言「今のうちにパパと離婚して！」私「はい？」理由を聞いて私は慌てて警察に通報した結果【修羅場】
A1053: 1052 | B1053: Avalynn Roderick | C1053: https://www.youtube.com/channel/UC2ALeyYaaWwXZhLpaAxCjDA | D1053: https://www.youtube.com/watch?v=UyB3devKmuE | E1053: 朗読/同形式 | F1053: 1 | G1053: 2 年前 | H1053: 0 | I1053: 【スカッとする話】新築の我が家が3ヶ月で全焼し現場確認に行くと、長男夫婦が何かを探している 話かけようとすると長男と長男嫁の会話が聞こえてきて→慌てて警察に通報した結果 | J1053: https://www.youtube.com/watch?v=y6TWW4C9Zhg | K1053: 3 年前 | L1053: 100000 | M1053: 【スカッとする話】新築の我が家が3ヶ月で全焼し現場確認に行くと、長男夫婦が何かを探している....話かけようとすると長男と長男嫁の会話が聞こえてきて→慌てて警察に通報した結果【修羅場】
A1054: 1053 | B1054: Avalynn Roderick | C1054: https://www.youtube.com/channel/UC2ALeyYaaWwXZhLpaAxCjDA | D1054: https://www.youtube.com/watch?v=BhEaxbJn-lY | E1054: 朗読/同形式 | F1054: 0.99 | G1054: 2 年前 | H1054: 0 | I1054: 【スカッとする話】ある日突然、大激怒の夫が「毎月仕送りした800万は！？長男夫婦がボロボロだったぞ！」私「長男嫁の通帳確認した？」夫「え？通帳？」真実を知ると 【スカッと】【修羅場】 1 | J1054: https://www.youtube.com/watch?v=L1iFf6yo66k | K1054: 3 年前 | L1054: 14000 | M1054: 【スカッとする話】ある日突然、大激怒の夫が「毎月仕送りした800万は！？長男夫婦がボロボロだったぞ！」私「長男嫁の通帳確認した？」夫「え？通帳？」真実を知ると...【スカッと】【修羅場】
A1055: 1054 | B1055: Avalynn Roderick | C1055: https://www.youtube.com/channel/UC2ALeyYaaWwXZhLpaAxCjDA | D1055: https://www.youtube.com/watch?v=RPeKXNaAMZU | E1055: 朗読/同形式 | F1055: 0.89 | G1055: 2 年前 | H1055: 0 | I1055: 【スカッとする話】兄嫁が出産プレゼントにくれた高級ベビー服を燃やした私。義両親「なぜそんな事を！！」私「これ見ました？」義両親「は？」プレゼントを見た義両親は鬼の形相で飛び出し | J1055: https://www.youtube.com/watch?v=-T8Z_uoombA | K1055: 3 年前 | L1055: 27000 | M1055: 【スカッとする話】兄嫁が出産プレゼントにくれた高級ベビー服を燃やした私。義両親「なぜそんな事を！！」私「これ見ました？」義両親「は？」プレゼントを見た義両親は鬼の形相で飛び出し...
A1056: 1055 | B1056: Chi Tông | C1056: https://www.youtube.com/channel/UCQZmlpJ03rsGpabdpOyYt5g | D1056: https://www.youtube.com/watch?v=YyHW5siTvnw | E1056: 朗読/同形式 | F1056: 1 | G1056: 1 年前 | H1056: 2 | I1056: 【スカッとする話】自ら命を絶った夫の葬儀後、墓参りに行くと１通の手紙が…手紙「俺の代わりに母さんに復讐を…」手紙の中身を読み進めると→私はガクガク震え始め… | J1056: https://www.youtube.com/watch?v=U2N_1lBpoWY | K1056: 2 年前 | L1056: 56000 | M1056: 【スカッとする話】自ら命を絶った夫の葬儀後、墓参りに行くと１通の手紙が…手紙「俺の代わりに母さんに復讐を…」手紙の中身を読み進めると→私はガクガク震え始め…
A1057: 1056 | B1057: Chi Tông | C1057: https://www.youtube.com/channel/UCQZmlpJ03rsGpabdpOyYt5g | D1057: https://www.youtube.com/watch?v=i0IlkEaZ0l4 | E1057: 朗読/同形式 | F1057: 1 | G1057: 1 年前 | H1057: 0 | I1057: 【スカッとする話】夫と姉の出産祝いに行くと5歳の娘「赤ちゃんが言いたい事あるみたい」不思議な力を持つ娘の言葉に戦慄し私は慌てて警察へ駆け込み | J1057: https://www.youtube.com/watch?v=b8ZAxV1gG_4 | K1057: 2 年前 | L1057: 20000 | M1057: 【スカッとする話】夫と姉の出産祝いに行くと5歳の娘「赤ちゃんが言いたい事あるみたい」不思議な力を持つ娘の言葉に戦慄し私は慌てて警察へ駆け込み...
A1058: 1057 | B1058: Chi Tông | C1058: https://www.youtube.com/channel/UCQZmlpJ03rsGpabdpOyYt5g | D1058: https://www.youtube.com/watch?v=k6-vdzKCc2w | E1058: 朗読/同形式 | F1058: 0.99 | G1058: 1 年前 | H1058: 0 | I1058: 【スカッとする話】出張帰りの夫のスーツのポッケからなぜか記入済みの離婚届が 私（出せって事だし提出しよw）速攻で提出し引越した結 | J1058: https://www.youtube.com/watch?v=BtTfiARWz5Y | K1058: 3 年前 | L1058: 90000 | M1058: 【スカッとする話】出張帰りの夫のスーツのポッケからなぜか記入済みの離婚届が...私（出せって事だし提出しよw）速攻で提出し引越した結果w
A1059: 1058 | B1059: Chi Tông | C1059: https://www.youtube.com/channel/UCQZmlpJ03rsGpabdpOyYt5g | D1059: https://www.youtube.com/watch?v=PbHTt9PGy-s | E1059: 朗読/同形式 | F1059: 0.98 | G1059: 1 年前 | H1059: 0 | I1059: 【スカッとする話】1歳姪の初めての誕生日会に行くと私の席だけない 長男嫁「他人の席は用意してないw」夫「 帰るか」私「そうね」3分後、長男夫婦に大惨 | J1059: https://www.youtube.com/watch?v=n-6PsuXWlY4 | K1059: 2 年前 | L1059: 110000 | M1059: 【スカッとする話】1歳姪の初めての誕生日会に行くと私の席だけない...長男嫁「他人の席は用意してないw」夫「...帰るか」私「そうね」3分後、長男夫婦に大惨事がw
A1060: 1059 | B1060: Chi Tông | C1060: https://www.youtube.com/channel/UCQZmlpJ03rsGpabdpOyYt5g | D1060: https://www.youtube.com/watch?v=1A2xPTP-kVU | E1060: 朗読/同形式 | F1060: 0.97 | G1060: 1 年前 | H1060: 1 | I1060: 【スカッとする話】結婚式に元カノを招待し嫁サゲする夫「俺の元カノが会場で一番可愛いだろw」元カノ「え？あんたの嫁ブスじゃんw」私「やっぱ結婚辞めるわ」婚約破棄して人生終了さ | J1060: https://www.youtube.com/watch?v=5HL1qvVFXnk | K1060: 2 年前 | L1060: 74000 | M1060: 【スカッとする話】結婚式に元カノを招待し嫁サゲする夫「俺の元カノが会場で一番可愛いだろw」元カノ「え？あんたの嫁ブスじゃんw」私「やっぱ結婚辞めるわ」婚約破棄して人生終了させた結果w
A1061: 1060 | B1061: Chi Tông | C1061: https://www.youtube.com/channel/UCQZmlpJ03rsGpabdpOyYt5g | D1061: https://www.youtube.com/watch?v=jwFk0EokrDM | E1061: 朗読/同形式 | F1061: 0.94 | G1061: 1 年前 | H1061: 2 | I1061: 【スカッとする話】夫の会社が倒産し解雇通知が届いたので出張中の夫へ電話すると、浮気夫「商談中だから後にしろ！」私「はーい」全てを悟った私→離婚届置いて新居 | J1061: https://www.youtube.com/watch?v=yXjk9KcZRys | K1061: 2 年前 | L1061: 78000 | M1061: 【スカッとする話】夫の会社が倒産し解雇通知が届いたので出張中の夫へ電話すると、浮気夫「商談中だから後にしろ！」私「はーい」全てを悟った私→離婚届置いて新居に引越した結果w
... A1313: 1312 | B1313: 街の物語 5687 | C1313: https://www.youtube.com/channel/UCxterQPS0akz9_edy6xAiDw | D1313: https://www.youtube.com/watch?v=zXDp7Lbl-9g | E1313: 朗読/同形式 | F1313: 1 | G1313: 3 週間前 | H1313: 1336 | I1313: 【スカッとする話】長男の葬儀中にペットカメラを確認すると、家の風呂場で夫と長男嫁が真っ最中 私「うわ…気持ち悪い」音量を最大にし浴室に閉じ込め、家族全員呼んでみた結果ｗ【修羅場】【スカッと】 | J1313: https://www.youtube.com/watch?v=IkjrifvTA_A | K1313: 3 年前 | L1313: 180000 | M1313: 【スカッと総集編】長男の葬儀中にペットカメラを確認すると、家の風呂場で夫と長男嫁が真っ最中 私「うわ…気持ち悪い」音量を最大にし浴室に閉じ込め、家族全員呼んでみた結果ｗ【修羅場】【スカッと】
A1314: 1313 | B1314: 雨の中の記憶、お話の部屋 | D1314: https://www.youtube.com/watch?v=mAz5AIyyMYs | E1314: 朗読/同形式 | F1314: 1 | G1314: 3 週間前 | H1314: 2 | I1314: 【スカッとする話】新築一軒家の我が家が全焼し現場確認に行くと夫と幼馴染が何か探している…。2人に声をかけようとすると恐ろしい会話を聞いてしまい慌てて警察に駆け込むと… | J1314: https://www.youtube.com/watch?v=rSLi31Fw8tI | K1314: 1 年前 | L1314: 14000 | M1314: 【スカッとする話】新築一軒家の我が家が全焼し現場確認に行くと夫と幼馴染が何か探している…。2人に声をかけようとすると恐ろしい会話を聞いてしまい慌てて警察に駆け込むと…
A1315: 1314 | B1315: 雨の中の記憶、お話の部屋 | D1315: https://www.youtube.com/watch?v=FrxyFWxugt8 | E1315: 朗読/同形式 | F1315: 1 | G1315: 8 日前 | H1315: 27 | I1315: 【スカッとする話】娘と義実家の大掃除をしてると突然、娘「母さん帰るよ!」 慌てた様子で車を急発進させた私「どうしたの?」娘「見なかった?」私「え?」帰宅すると... | J1315: https://www.youtube.com/watch?v=rYAfWQF1W-0 | K1315: 1 年前 | L1315: 66000 | M1315: 【スカッとする話】娘と義実家の大掃除をしてると突然、娘「母さん帰るよ！」慌てた様子で車を急発進させた。私「どうしたの？」娘「見なかった？」私「え？」帰宅すると…
A1316: 1315 | B1316: 雨の中の記憶、お話の部屋 | D1316: https://www.youtube.com/watch?v=NGczH5b9BE0 | E1316: 朗読/同形式 | F1316: 0.99 | G1316: 2 週間前 | H1316: 1 | I1316: 【スカッとする話】実家で母の同居介護中に娘が記入済みの離婚届を持ってきた... 娘「パパが私とママはいらないって...」私「やったね!」→即提出し家を売り払い更地にすると...W | J1316: https://www.youtube.com/watch?v=CjxJ0f62VMM | K1316: 1 年前 | L1316: 26000 | M1316: 【スカッとする話】実家で母の同居介護中に娘が記入済みの離婚届を持ってきた…娘「パパが私とママはいらないって…」私「やったね！」即提出し家を売り払い更地にすると…w
A1317: 1316 | B1317: 雨の中の記憶、お話の部屋 | D1317: https://www.youtube.com/watch?v=CIJOaOhk7ZI | E1317: 朗読/同形式 | F1317: 0.99 | G1317: 1 時間前 | H1317: 0 | I1317: 【スカッとする話】38歳で妊娠した私を捨て19歳の浮気相手と再婚した警察官の夫夫「若い女が良いから離婚でw」20年後、警察で元夫と再会直後、息子を見た元夫が震えだし...W | J1317: https://www.youtube.com/watch?v=Fiv9d71jhj4 | K1317: 1 年前 | L1317: 21000 | M1317: 【スカッとする話】38歳で妊娠した私を捨て19歳の浮気相手と再婚した警察官の夫「若い女が良いから離婚でw」20年後、警察で元夫と再会→直後、息子を見た元夫が震えだし…w
A1318: 1317 | B1318: 雨の中の記憶、お話の部屋 | D1318: https://www.youtube.com/watch?v=qpUGtsvPtRY | E1318: 朗読/同形式 | F1318: 0.97 | G1318: 2 週間前 | H1318: 10 | I1318: 【スカッとする話】夫の葬儀中、涙を流す私に義母「遺産は私たちが貰うわねw」 義父「これで高級老人ホーム入れるw」 私「あなたらは1円も相続できないよ?」義両親「え?」→結果w W | J1318: https://www.youtube.com/watch?v=ixDA5L4ob04 | K1318: 1 年前 | L1318: 58000 | M1318: 【スカッとする話】夫の葬儀中、涙を流す私に義母「遺産は私たちが貰うわねw」義父「これで高級老人ホーム入れるw」私「え？あなたらは1円も相続できないよ？」義両親「え？」
A1319: 1318 | B1319: 静かな夜の物語、静かな心の記録 | D1319: https://www.youtube.com/watch?v=GzdH1HjwK5s | E1319: 朗読/同形式 | F1319: 1 | G1319: 4 週間前 | H1319: 0 | I1319: 【スカッとする話】8歳の姪「1日だけ泊めて下さい...」大雪の中、赤ちゃんを抱き抱えボロボロの姿で現れた姪...。夫「え？それは無理だよ？」姪「そんな…涙」→結果 | J1319: https://www.youtube.com/watch?v=Eh0FIn_sub0 | K1319: 2 年前 | L1319: 56000 | M1319: 【スカッとする話】8歳の姪「1日だけ泊めて下さい...」大雪の中、赤ちゃんを抱き抱えボロボロの姿で現れた姪...。夫「え？それは無理だよ？」姪「そんな…涙」→結果
A1320: 1319 | B1320: 静かな夜の物語、静かな心の記録 | D1320: https://www.youtube.com/watch?v=BGTCsj16a2I | E1320: 朗読/同形式 | F1320: 1 | G1320: 3 週間前 | H1320: 0 | I1320: 【スカッとする話】長男夫婦に初孫が生まれ出産祝いに行くと長男嫁「二人は汚いので床でいいですか？w」長男「ジジババは段ボールの上でw」夫「...帰るか」私「うん」速帰宅し→永久に無視した結果w | J1320: https://www.youtube.com/watch?v=Y2GawdK7Q9E | K1320: 2 年前 | L1320: 100000 | M1320: 【スカッとする話】長男夫婦に初孫が生まれ出産祝いに行くと長男嫁「二人は汚いので床でいいですか？w」長男「ジジババは段ボールの上でw」夫「...帰るか」私「うん」速帰宅し→永久に無視した結果w
A1321: 1320 | B1321: 静かな夜の物語、静かな心の記録 | D1321: https://www.youtube.com/watch?v=JHUnHhyu7AU | E1321: 朗読/同形式 | F1321: 1 | G1321: 3 週間前 | H1321: 2 | I1321: 【スカッとする話】なぜか夫の連れ子が湯船に入った後、必ず茶色の液体が浮いている...後日、高熱が出て病院に行くと医師「今すぐ離婚して下さい」私「え？」実は... | J1321: https://www.youtube.com/watch?v=xCscEAOYwvs | K1321: 2 年前 | L1321: 35000 | M1321: 【スカッとする話】なぜか夫の連れ子が湯船に入った後、必ず茶色の液体が浮いている...後日、高熱が出て病院に行くと医師「今すぐ離婚して下さい」私「え？」実は...
A1322: 1321 | B1322: 静かな夜の物語、静かな心の記録 | D1322: https://www.youtube.com/watch?v=p_7Pbr4_LJQ | E1322: 朗読/同形式 | F1322: 1 | G1322: 4 日前 | H1322: 0 | I1322: 【スカッとする話】長男夫婦の家へ孫に会いに行くと、孫娘が真っ暗な物置で食事し軒下で寝ていた。私「一体どうしたの！？」孫「１年間ずっとここで...」私「は？」直後、キレた私は... | J1322: https://www.youtube.com/watch?v=cYm3AWOE2Yc | K1322: 2 年前 | L1322: 57000 | M1322: 【スカッとする話】長男夫婦の家へ孫に会いに行くと、孫娘が真っ暗な物置で食事し軒下で寝ていた。私「一体どうしたの！？」孫「１年間ずっとここで...」私「は？」直後、キレた私は...
A1323: 1322 | B1323: 静かな夜の物語、静かな心の記録 | D1323: https://www.youtube.com/watch?v=aK06k2dCG3Q | E1323: 朗読/同形式 | F1323: 1 | G1323: 5 日前 | H1323: 0 | I1323: 【スカッとする話】K察「お宅の旦那がﾀﾋにそうです！至急現場に来て下さい！」私「え？」親族全員を呼び現場に駆けつけた結果w | J1323: https://www.youtube.com/watch?v=Hdd6qR2k6_Q | K1323: 2 年前 | L1323: 40000 | M1323: 【スカッとする話】K察「お宅の旦那がﾀﾋにそうです！至急現場に来て下さい！」私「え？」親族全員を呼び現場に駆けつけた結果w
...

Sheet 本家が圏外
A1: No. | B1: 元動画URL | C1: 投稿 | D1: 再生数 | E1: タイトル | F1: 確認メモ
A2: 1 | B2: https://www.youtube.com/watch?v=tQe8apURLKM | C2: 1 年前 | D2: 200000 | E2: 【スカッとする話】女4姉妹を育てる私に夫「離婚して愛人と再婚するから」私「いいけど長女は連れてってね」夫「え？母親のお前が育てろよ」私「嫌よ。だって…」
A3: 2 | B3: https://www.youtube.com/watch?v=5OeuGN05XeY | C3: 1 年前 | D3: 14000 | E3: 【スカッとする話】ハワイ旅行中の夫から突然の連絡「女子大生の愛人と再婚するから離婚でwガキ連れて家から出ていけw」私「もう娘と引越し済みだけど？」夫「え？」結果w
A4: 3 | B4: https://www.youtube.com/watch?v=J569p3RUscE | C4: 1 年前 | D4: 75000 | E4: 【スカッとする話】単身赴任中の夫から離婚届が郵送されてきた→家族全員で大喜びして即提出、家を売り払い引越すと…w【スカッと】【朗読】【修羅場】
A5: 4 | B5: https://www.youtube.com/watch?v=EdukiB7Cm5k | C5: 1 年前 | D5: 92000 | E5: 【スカッとする話】婿両親がウチの娘と孫を引きずってきた。義父「月100万の息子と釣り合わんw」義母「役立たずの家政婦は返品でw」私「じゃ明日から路上生活がんばれw」義父・義母「は？」
A6: 5 | B6: https://www.youtube.com/watch?v=s8zl0VxtC2k | C6: 2 年前 | D6: 63000 | E6: 【スカッと総集編】離婚から２週間で再婚した元夫「家柄、性格ともに最高の嫁w」夫の新しい嫁を見た瞬間、私は思わず大爆笑www→だってその嫁は…w
A7: 6 | B7: https://www.youtube.com/watch?v=IIMdWb_44ts | C7: 2 年前 | D7: 370000 | E7: 【スカッとする話】風呂も寝室も完全別で夜の行為も一切しない夫が緊急入院し手術する事に→医師「い、一体なんだこれは…」夫の体を見た医師が震え出し...
A8: 7 | B8: https://www.youtube.com/watch?v=cF4ti4NhgGU | C8: 2 年前 | D8: 170000 | E8: 【スカッとする話】地下室に隠れ夫と親友が真っ最中だった...母「嫁子、戸締りしておいたわよ！」ど天然の母が気づかず鍵を閉めたので永遠に放置し新居に引越した結果w
A9: 8 | B9: https://www.youtube.com/watch?v=7gR3-5GCVtk | C9: 2 年前 | D9: 47000 | E9: 【スカッとする話】熱で早退した息子を連れて帰ると葬儀に行ったはずの夫が姉と真っ最中…息子「大変！おばさんが襲われてる！」息子が２人の動画を撮影し義父と親戚一同に送った結果ｗ
A10: 9 | B10: https://www.youtube.com/watch?v=4HBdhL1n_XU | C10: 2 年前 | D10: 280000 | E10: 【スカッと総集編】新築4LDKを購入した途端、夫「明日から長男夫婦と同居する！」長男嫁「逆らったら介護しませんよw」私「は？私は独身ですけど？」夫・長男夫婦「は？」結果w
A11: 10 | B11: https://www.youtube.com/watch?v=z-k8D-43D14 | C11: 2 年前 | D11: 60000 | E11: 【スカッとする話】ハネムーン先で目覚めると夫と社長令嬢の浮気相手が真っ最中...夫の財布とパスポートを持って勝手に帰国し海外に閉じ込めてやった結果w
A12: 11 | B12: https://www.youtube.com/watch?v=IjcqpMyHjf0 | C12: 3 年前 | D12: 95000 | E12: 【スカッとする話】次男の葬儀中にペットカメラを確認すると、誰もいないはずの私の部屋で夫と長男嫁が真っ最中…音量を最大にして親戚中に実況中継してやった結果w【修羅場】
A13: 12 | B13: https://www.youtube.com/watch?v=0ilhld7tjCo | C13: 3 年前 | D13: 270000 | E13: 【スカッと総集編】私が余命３ヶ月と聞いて愛人と豪遊しはじめた夫「お前まだ生きてんのか？w」 私「え？余命３ヶ月はアナタよ？」 夫「は？」実は... 【修羅場】【スカッとする話】
